Workbook

Sheet PANEL
B2: 🏛️ CENTRO DE CONTROL FINANCIERO — MARLON MUÑOZ | H2: 📅 AÑO: | I2: 2026 | K2: 🔍 MES: | L2: octubre
B3: ⚡ Sincronización Automática en Tiempo Real • Bot de Telegram • Facturación Gmail • Nómina y Ahorros Colanta
B5: INGRESO TOTAL DEL MES | E5: GASTO TOTAL DEL MES | H5: AHORRO DEL PERÍODO (COLANTA) | K5: DISPONIBLE LIBRE EN CAJA
B6: =IF(N(H15)>0, H15 + IFERROR(SUMIFS(MOVIMIENTOS!$H$4:$H$246, MOVIMIENTOS!$D$4:$D$246, "Ingreso", MOVIMIENTOS!$E$4:$E$246, "<>Salario", MOVIMIENTOS!$K$4:$K$246, $L$2, MOVIMIENTOS!$L$4:$L$246, $I$2), 0), IFERROR(SUMIFS(MOVIMIENTOS!$H$4:$H$246, MOVIMIENTOS!$D$4:$D$246, "Ingreso", MOVIMIENTOS!$K$4:$K$246, $L$2, MOVIMIENTOS!$L$4:$L$246, $I$2), 0)) -> 0 | E6: =IFERROR(SUMIFS(MOVIMIENTOS!$H$4:$H$246, MOVIMIENTOS!$D$4:$D$246, "Gasto", MOVIMIENTOS!$K$4:$K$246, $L$2, MOVIMIENTOS!$L$4:$L$246, $I$2), 0) -> 207123 | H6: =C16 -> 0 | K6: =B6 - E6 -> -207123
B8: ="⚡ ESTADO FINANCIERO: " & IF(AND(B6=0, E6=0), "⚪ SIN MOVIMIENTOS EN EL MES", IF(K6<=0, "🚨 GASTO SUPERA INGRESOS", IF(K6<300000, "⚠️ CAJA AJUSTADA", "🟢 SALUDABLE Y EN SUPERÁVIT"))) & " | LIQUIDEZ INMEDIATA EN CUENTAS: " & TEXT(J42, "$ #,##0") & " | QUINCENAS SINCRONIZADAS" -> ⚡ ESTADO FINANCIERO: 🚨 GASTO SUPERA INGRESOS | LIQUIDEZ INMEDIATA EN CUENTAS: $ 3,390,857 | QUINCENAS SINCRONIZADAS
B10: AHORROS POR TIPO — FONDO COLANTA | G10: AUDITORÍA NÓMINA COLANTA & FLUJO DE CAJA
B11: Tipo de Ahorro | C11: Mes Seleccionado ($) | D11: Acumulado Total ($) | E11: % Participación | G11: Concepto Nómina / Flujo | H11: Monto ($ COP) | I11: Impacto | J11: Detalle Operativo
B12: Ahorro Ordinario | C12: =AHORROS!B8 -> 0 | D12: =AHORROS!C8 -> 594000 | E12: =AHORROS!D8 -> 0.1510951 | G12: Total Devengado Colanta | H12: =IFERROR(SUMIFS('COLILLAS DE PAGO'!$J$4:$J$22, 'COLILLAS DE PAGO'!$B$4:$B$22, $L$2, 'COLILLAS DE PAGO'!$C$4:$C$22, $I$2), 0) -> 0 | I12: (+) Ingreso Bruto | J12: Salario base + recargos
B13: Ahorro Navideño | C13: =AHORROS!B9 -> 0 | D13: =AHORROS!C9 -> 2160000 | E13: =AHORROS!D9 -> 0.54943671 | G13: Salud y Pensión Ley (8%) | H13: =IFERROR(SUMIFS('COLILLAS DE PAGO'!$K$4:$K$22, 'COLILLAS DE PAGO'!$B$4:$B$22, $L$2, 'COLILLAS DE PAGO'!$C$4:$C$22, $I$2) + SUMIFS('COLILLAS DE PAGO'!$L$4:$L$22, 'COLILLAS DE PAGO'!$B$4:$B$22, $L$2, 'COLILLAS DE PAGO'!$C$4:$C$22, $I$2), 0) -> 0 | I13: (-) Deducción Ley | J13: EPS Sura + Porvenir
B14: Aportes Cooperativos | C14: =AHORROS!B10 -> 0 | D14: =AHORROS!C10 -> 995083 | E14: =AHORROS!D10 -> 0.25311812 | G14: Ahorros Nómina Colanta | H14: =C16 -> 0 | I14: (🐷) Reserva | J14: Deducción Fondo Colanta
B15: Aporte Afiliación / Otros | C15: =AHORROS!B11 -> 0 | D15: =AHORROS!C11 -> 182216 | E15: =AHORROS!D11 -> 0.046350074 | G15: Neto Consignado Colanta | H15: =IFERROR(SUMIFS('COLILLAS DE PAGO'!$O$4:$O$22, 'COLILLAS DE PAGO'!$B$4:$B$22, $L$2, 'COLILLAS DE PAGO'!$C$4:$C$22, $I$2), 0) -> 0 | I15: (=) Consignado | J15: Ingreso efectivo AyC Colanta
B16: TOTAL AHORROS COLANTA | C16: =AHORROS!B12 -> 0 | D16: =AHORROS!C12 -> 3931299 | E16: =AHORROS!D12 -> 1 | G16: Compromisos Fijos Abiertos | H16: =IFERROR('CONTROL FIJOS'!G5, 0) -> 2557000 | I16: (-) Obligación | J16: Pendiente por pagar en el mes
B18: CONTROL PRESUPUESTAL POR CATEGORÍA | I18: INDICADORES DE COBERTURA MENSUAL
B19: Categoría | C19: Gasto Real ($) | D19: Límite ($) | E19: % Uso | F19: Semáforo | G19: Desvío | I19: Total Cuotas Programadas | K19: ='CONTROL FIJOS'!A5 -> 2611000
B20: Alimentación | C20: =SUMIFS(MOVIMIENTOS!$H$4:$H$246, MOVIMIENTOS!$D$4:$D$246, "Gasto", MOVIMIENTOS!$E$4:$E$246, "Alimentaci*", MOVIMIENTOS!$K$4:$K$246, $L$2, MOVIMIENTOS!$L$4:$L$246, $I$2) -> 0 | D20: 800000 | E20: =IF(D20=0, 0, C20/D20) -> 0 | F20: =IF(D20=0, "⚪ Sin límite", IF(E20<=0.8, "🟢 En regla", IF(E20<=1, "🟡 Límite", "🔴 Excedido"))) -> 🟢 En regla | G20: =IF(D20=0, 0, D20-C20) -> 800000 | I20: Total Pagado / Abonado | K20: ='CONTROL FIJOS'!D5 -> 54000
B21: ARRIENDO CASA | C21: =SUMIFS(MOVIMIENTOS!$H$4:$H$246, MOVIMIENTOS!$D$4:$D$246, "Gasto", MOVIMIENTOS!$E$4:$E$246, "Vivienda", MOVIMIENTOS!$K$4:$K$246, $L$2, MOVIMIENTOS!$L$4:$L$246, $I$2)+SUMIFS(MOVIMIENTOS!$H$4:$H$246, MOVIMIENTOS!$D$4:$D$246, "Gasto", MOVIMIENTOS!$E$4:$E$246, "Arriendo Casa", MOVIMIENTOS!$K$4:$K$246, $L$2, MOVIMIENTOS!$L$4:$L$246, $I$2) -> 0 | D21: 900000 | E21: =IF(D21=0, 0, C21/D21) -> 0 | F21: =IF(D21=0, "⚪ Sin límite", IF(E21<=0.8, "🟢 En regla", IF(E21<=1, "🟡 Límite", "🔴 Excedido"))) -> 🟢 En regla | G21: =IF(D21=0, 0, D21-C21) -> 900000 | I21: Saldo Pendiente de Pago | K21: ='CONTROL FIJOS'!G5 -> 2557000
B22: Servicios Públicos | C22: =SUMIFS(MOVIMIENTOS!$H$4:$H$246, MOVIMIENTOS!$D$4:$D$246, "Gasto", MOVIMIENTOS!$E$4:$E$246, "Servicios*", MOVIMIENTOS!$K$4:$K$246, $L$2, MOVIMIENTOS!$L$4:$L$246, $I$2) -> 0 | D22: 300000 | E22: =IF(D22=0, 0, C22/D22) -> 0 | F22: =IF(D22=0, "⚪ Sin límite", IF(E22<=0.8, "🟢 En regla", IF(E22<=1, "🟡 Límite", "🔴 Excedido"))) -> 🟢 En regla | G22: =IF(D22=0, 0, D22-C22) -> 300000 | I22: Obligaciones Pagadas | K22: =COUNTIF('CONTROL FIJOS'!$G$9:$G$26, "🟢 Pagado") -> 2
B23: Transporte y Moto | C23: =SUMIFS(MOVIMIENTOS!$H$4:$H$246, MOVIMIENTOS!$D$4:$D$246, "Gasto", MOVIMIENTOS!$E$4:$E$246, "Transporte*", MOVIMIENTOS!$K$4:$K$246, $L$2, MOVIMIENTOS!$L$4:$L$246, $I$2)+SUMIFS(MOVIMIENTOS!$H$4:$H$246, MOVIMIENTOS!$D$4:$D$246, "Gasto", MOVIMIENTOS!$E$4:$E$246, "Moto", MOVIMIENTOS!$K$4:$K$246, $L$2, MOVIMIENTOS!$L$4:$L$246, $I$2) -> 116000 | D23: 240000 | E23: =IF(D23=0, 0, C23/D23) -> 0.48333333 | F23: =IF(D23=0, "⚪ Sin límite", IF(E23<=0.8, "🟢 En regla", IF(E23<=1, "🟡 Límite", "🔴 Excedido"))) -> 🟢 En regla | G23: =IF(D23=0, 0, D23-C23) -> 124000 | I23: Abonos Parciales | K23: =COUNTIF('CONTROL FIJOS'!$G$9:$G$26, "🟡 Abono Parcial") -> 0
B24: Gastos Hormiga / Dulces | C24: =SUMIFS(MOVIMIENTOS!$H$4:$H$246, MOVIMIENTOS!$D$4:$D$246, "Gasto", MOVIMIENTOS!$E$4:$E$246, "*Hormiga*", MOVIMIENTOS!$K$4:$K$246, $L$2, MOVIMIENTOS!$L$4:$L$246, $I$2)+SUMIFS(MOVIMIENTOS!$H$4:$H$246, MOVIMIENTOS!$D$4:$D$246, "Gasto", MOVIMIENTOS!$E$4:$E$246, "Helado", MOVIMIENTOS!$K$4:$K$246, $L$2, MOVIMIENTOS!$L$4:$L$246, $I$2)+SUMIFS(MOVIMIENTOS!$H$4:$H$246, MOVIMIENTOS!$D$4:$D$246, "Gasto", MOVIMIENTOS!$E$4:$E$246, "Pastillas Garganta", MOVIMIENTOS!$K$4:$K$246, $L$2, MOVIMIENTOS!$L$4:$L$246, $I$2) -> 67000 | D24: 50000 | E24: =IF(D24=0, 0, C24/D24) -> 1.34 | F24: =IF(D24=0, "⚪ Sin límite", IF(E24<=0.8, "🟢 En regla", IF(E24<=1, "🟡 Límite", "🔴 Excedido"))) -> 🔴 Excedido | G24: =IF(D24=0, 0, D24-C24) -> -17000 | I24: Obligaciones Pendientes | K24: =COUNTIF('CONTROL FIJOS'!$G$9:$G$26, "🔴 Pendiente") -> 13
B25: Ocio y Entretenimiento | C25: =SUMIFS(MOVIMIENTOS!$H$4:$H$246, MOVIMIENTOS!$D$4:$D$246, "Gasto", MOVIMIENTOS!$E$4:$E$246, "*Entretenimiento*", MOVIMIENTOS!$F$4:$F$246, "<>Pago fijo", MOVIMIENTOS!$K$4:$K$246, $L$2, MOVIMIENTOS!$L$4:$L$246, $I$2)+SUMIFS(MOVIMIENTOS!$H$4:$H$246, MOVIMIENTOS!$D$4:$D$246, "Gasto", MOVIMIENTOS!$E$4:$E$246, "Ocio*", MOVIMIENTOS!$K$4:$K$246, $L$2, MOVIMIENTOS!$L$4:$L$246, $I$2) -> 14023 | D25: 100000 | E25: =IF(D25=0, 0, C25/D25) -> 0.14023 | F25: =IF(D25=0, "⚪ Sin límite", IF(E25<=0.8, "🟢 En regla", IF(E25<=1, "🟡 Límite", "🔴 Excedido"))) -> 🟢 En regla | G25: =IF(D25=0, 0, D25-C25) -> 85977 | I25: Compromisos Q1 (Día <=15) | K25: =SUMIFS('CONTROL FIJOS'!$I$9:$I$26, 'CONTROL FIJOS'!$D$9:$D$26, "<=15") -> 1332000
B26: Suscripciones | C26: =SUMIFS(MOVIMIENTOS!$H$4:$H$246, MOVIMIENTOS!$D$4:$D$246, "Gasto", MOVIMIENTOS!$E$4:$E$246, "Suscripciones*", MOVIMIENTOS!$K$4:$K$246, $L$2, MOVIMIENTOS!$L$4:$L$246, $I$2)+SUMIFS(MOVIMIENTOS!$H$4:$H$246, MOVIMIENTOS!$D$4:$D$246, "Gasto", MOVIMIENTOS!$E$4:$E$246, "*Entretenimiento*", MOVIMIENTOS!$F$4:$F$246, "Pago fijo", MOVIMIENTOS!$K$4:$K$246, $L$2, MOVIMIENTOS!$L$4:$L$246, $I$2) -> 10100 | D26: 0 | E26: =IF(D26=0, 0, C26/D26) -> 0 | F26: =IF(D26=0, "⚪ Sin límite", IF(E26<=0.8, "🟢 En regla", IF(E26<=1, "🟡 Límite", "🔴 Excedido"))) -> ⚪ Sin límite | G26: =IF(D26=0, 0, D26-C26) -> 0 | I26: Compromisos Q2 (Día >15) | K26: =SUMIFS('CONTROL FIJOS'!$I$9:$I$26, 'CONTROL FIJOS'!$D$9:$D$26, ">15") -> 1225000
B27: Compras | C27: =SUMIFS(MOVIMIENTOS!$H$4:$H$246, MOVIMIENTOS!$D$4:$D$246, "Gasto", MOVIMIENTOS!$E$4:$E$246, "Compras*", MOVIMIENTOS!$K$4:$K$246, $L$2, MOVIMIENTOS!$L$4:$L$246, $I$2) -> 0 | D27: 0 | E27: =IF(D27=0, 0, C27/D27) -> 0 | F27: =IF(D27=0, "⚪ Sin límite", IF(E27<=0.8, "🟢 En regla", IF(E27<=1, "🟡 Límite", "🔴 Excedido"))) -> ⚪ Sin límite | G27: =IF(D27=0, 0, D27-C27) -> 0 | I27: Estado Cobertura Mes | K27: =IF('CONTROL FIJOS'!A5=0, "⚪ Sin Obligaciones", IF('CONTROL FIJOS'!G5=0, "🟢 100% Cubierto", "🟡 Pendiente de Pago")) -> 🟡 Pendiente de Pago
B28: Otras categorías sin presupuesto | C28: =MAX(0, E6-SUM(C20:C27)) -> 0 | D28: 0 | E28: =IF(D28=0, 0, C28/D28) -> 0 | F28: =IF(D28=0, "⚪ Sin límite", IF(E28<=0.8, "🟢 En regla", IF(E28<=1, "🟡 Límite", "🔴 Excedido"))) -> ⚪ Sin límite | G28: =IF(D28=0, 0, D28-C28) -> 0
B30: BALANZA Y FLUJO DE CAJA QUINCENAL ESTIMADO (COLANTA) | I30: RADAR DE GASTOS HORMIGA & FUGAS DEL MES
B31: Período / Quincena | C31: Ingreso Est. ($) | D31: Fijos Est. ($) | E31: Gastos Var. ($) | F31: Caja Libre ($) | G31: Semáforo | I31: Métrica de Control | J31: Monto / Valor | K31: Semáforo | L31: Diagnóstico
B32: Quincena 1 (Día 1-15) | C32: =H15/2 -> 0 | D32: ='CONTROL FIJOS'!J5 -> 1332000 | E32: =IFERROR(SUMIFS(MOVIMIENTOS!$H$4:$H$246, MOVIMIENTOS!$D$4:$D$246, "Gasto", MOVIMIENTOS!$K$4:$K$246, $L$2, MOVIMIENTOS!$L$4:$L$246, $I$2, MOVIMIENTOS!$P$4:$P$246, "Q1"), 0) -> 207123 | F32: =C32-D32-E32 -> -1539123 | G32: =IF(F32>0, "🟢 Superávit", "🔴 Ajustado") -> 🔴 Ajustado | I32: Gasto Hormiga del Mes | J32: =PANEL!C24 -> 67000 | K32: =IF(J32>120000, "🔴 Crítico", IF(J32>50000, "🟡 Moderado", "🟢 Bajo")) -> 🟡 Moderado | L32: Impacto en caja
B33: Quincena 2 (Día 16-30) | C33: =H15/2 -> 0 | D33: ='CONTROL FIJOS'!A5 - 'CONTROL FIJOS'!J5 -> 1279000 | E33: =MAX(0, E6-E32) -> 0 | F33: =C33-D33-E33 -> -1279000 | G33: =IF(F33>0, "🟢 Excedente", "🔴 Ajustado") -> 🔴 Ajustado | I33: N° Compras Hormiga | J33: =IFERROR(COUNTIFS(MOVIMIENTOS!$D$4:$D$246, "Gasto", MOVIMIENTOS!$E$4:$E$246, "*Hormiga*", MOVIMIENTOS!$K$4:$K$246, $L$2, MOVIMIENTOS!$L$4:$L$246, $I$2)+COUNTIFS(MOVIMIENTOS!$D$4:$D$246, "Gasto", MOVIMIENTOS!$E$4:$E$246, "Helado", MOVIMIENTOS!$K$4:$K$246, $L$2, MOVIMIENTOS!$L$4:$L$246, $I$2)+COUNTIFS(MOVIMIENTOS!$D$4:$D$246, "Gasto", MOVIMIENTOS!$E$4:$E$246, "Pastillas Garganta", MOVIMIENTOS!$K$4:$K$246, $L$2, MOVIMIENTOS!$L$4:$L$246, $I$2), 0) -> 2 | K33: =IF(J33>15, "🔴 Frecuente", IF(J33>7, "🟡 Regular", "🟢 Ocasional")) -> 🟢 Ocasional | L33: Frecuencia de compra
B34: Consolidado Mes Libre | C34: =C32+C33 -> 0 | D34: =D32+D33 -> 2611000 | E34: =E32+E33 -> 207123 | F34: =C34-D34-E34 -> -2818123 | G34: =IF(F34>0, "✅ Sostenible", "🚨 Alerta") -> 🚨 Alerta | I34: Ticket Promedio por Antojo | J34: =IF(J33=0, 0, J32/J33) -> 33500 | K34: 📊 Promedio | L34: Costo medio por microgasto
I35: % Impacto vs. Ahorro Colanta | J35: =IF(C16=0, 0, J32/C16) -> 0 | K35: =IF(J35>0.5, "⚠️ Muy Alto", "🟢 Razonable") -> 🟢 Razonable | L35: Equivalente de tu ahorro
B37: 🎄 PROYECCIÓN CIERRE DE AÑO 2026 (FIN DE AÑO MARLON) | I37: 💳 ARQUEO DE LIQUIDEZ POR CUENTA / BOLSILLO
B38: Concepto de Cierre 2026 | C38: Fecha Estimada | D38: Monto Proyectado ($) | F38: Impacto / Destino | I38: Cuenta / Depósito | J38: Monto ($) | K38: Estado | L38: Tipo de Acceso
B39: Entrega Ahorro Navideño Colanta | C39: 01/12/2026 | D39: =AHORROS!C9 -> 2160000 | F39: Liquidación de fondo contractual | I39: 🥛 AyC Colanta (Nómina) | J39: 3319057 | K39: 🟢 Activa | L39: Ahorro / Nómina
B40: Prima Legal de Servicios (Diciembre) | C40: 20/12/2026 | D40: ='COLILLAS DE PAGO'!I26 -> 2418909.1 | F40: Beneficio legal semestral Colanta | I40: 📱 Nequi | J40: 0 | K40: 🟢 Activa | L40: Móvil / Inmediato
B41: Ahorros Totales Colanta Acumulados | C41: 31/12/2026 | D41: =AHORROS!C12 -> 3931299 | F41: Patrimonio acumulado en la cooperativa | I41: 💵 Efectivo | J41: 71800 | K41: 🟢 Disponible | L41: Efectivo Mano
B42: Total Liquidez Extra Proyectada Diciembre | C42: 31/12/2026 | D42: =D39+D40 -> 4578909.1 | F42: Capital disponible fin de año | I42: 📦 Total Liquidez Inmediata | J42: =SUM(J39:J41) -> 3390857 | K42: 💎 Consolidado | L42: Disponibilidad Total

Sheet MOVIMIENTOS
A1: 💳 REGISTRO MAESTRO DE MOVIMIENTOS
A2: Bitácora contable sincronizada con bot de Telegram y clasificación automática de gastos.
A4: ID | B4: Fecha | C4: Hora | D4: Tipo | E4: Categoría | F4: Subcategoría | G4: Descripción | H4: Valor ($ COP) | I4: Método de Pago | J4: Cuenta / Origen | K4: Mes | L4: Año | M4: Comprobante / Ref | N4: Notas | O4: _IndexFiltro | P4: Quincena
A5: M-0255 | B5: 46310 | C5: 05:58 PM | D5: Gasto | E5: Entretenimiento | F5: Pago fijo | G5: Spotify - Factura octubre 2026 | H5: 10100 | I5: Tarjeta Nequi | J5: Nequi | K5: octubre | L5: 2026 | M5: Gmail | N5: PAGO_FIJO|F-0114|octubre|2026|REF:GPA.3333-4099-9556-15284..13 | O5: =IF(ISBLANK(A5), "", IF(AND(LOWER(TRIM(K5))=LOWER(TRIM(PANEL!$L$2)), L5=PANEL!$I$2), MAX($O$4:O4)+1, "")) -> 1 | P5: =IF(ISBLANK(A5), "", IF(OR(B5="Q1", B5="Q2"), B5, IF(ISNUMBER(B5), IF(DAY(B5)<=15, "Q1", "Q2"), IF(MID(TRIM(B5),3,1)="/", IF(VALUE(LEFT(TRIM(B5),2))<=15, "Q1", "Q2"), IF(MID(TRIM(B5),5,1)="-", IF(VALUE(MID(TRIM(B5),9,2))<=15, "Q1", "Q2"), "Q1"))))) -> Q1
A6: M-0242 | B6: 46302 | C6: 01:22 PM | D6: Gasto | E6: Entretenimiento | F6: Videojuegos / Eneba | G6: Compra en Eneba por E-Wallet / EBANX | H6: 14023 | I6: Tarjeta | J6: Bancolombia | K6: octubre | L6: 2026 | M6: Gmail | N6: GMAIL:1a117998a2bbdde6|REF:783dcfda-c27b-11f1-8fdf-6e753a749966 | O6: =IF(ISBLANK(A6), "", IF(AND(LOWER(TRIM(K6))=LOWER(TRIM(PANEL!$L$2)), L6=PANEL!$I$2), MAX($O$4:O5)+1, "")) -> 2 | P6: =IF(ISBLANK(A6), "", IF(OR(B6="Q1", B6="Q2"), B6, IF(ISNUMBER(B6), IF(DAY(B6)<=15, "Q1", "Q2"), IF(MID(TRIM(B6),3,1)="/", IF(VALUE(LEFT(TRIM(B6),2))<=15, "Q1", "Q2"), IF(MID(TRIM(B6),5,1)="-", IF(VALUE(MID(TRIM(B6),9,2))<=15, "Q1", "Q2"), "Q1"))))) -> Q1
A7: M-0241 | B7: 46301 | C7: 07:07 PM | D7: Gasto | E7: Moto | F7: Mantenimiento | G7: Lavada de Moto | H7: 19000 | I7: Transferencia | J7: Nequi | K7: octubre | L7: 2026 | M7: Telegram | O7: =IF(ISBLANK(A7), "", IF(AND(LOWER(TRIM(K7))=LOWER(TRIM(PANEL!$L$2)), L7=PANEL!$I$2), MAX($O$4:O6)+1, "")) -> 3 | P7: =IF(ISBLANK(A7), "", IF(OR(B7="Q1", B7="Q2"), B7, IF(ISNUMBER(B7), IF(DAY(B7)<=15, "Q1", "Q2"), IF(MID(TRIM(B7),3,1)="/", IF(VALUE(LEFT(TRIM(B7),2))<=15, "Q1", "Q2"), IF(MID(TRIM(B7),5,1)="-", IF(VALUE(MID(TRIM(B7),9,2))<=15, "Q1", "Q2"), "Q1"))))) -> Q1
A8: M-0240 | B8: 46301 | C8: 07:07 PM | D8: Gasto | E8: Moto | F8: Gasolina | G8: Tanqueada de Gasolina para Moto | H8: 31000 | I8: Transferencia | J8: Nequi | K8: octubre | L8: 2026 | M8: Telegram | O8: =IF(ISBLANK(A8), "", IF(AND(LOWER(TRIM(K8))=LOWER(TRIM(PANEL!$L$2)), L8=PANEL!$I$2), MAX($O$4:O7)+1, "")) -> 4 | P8: =IF(ISBLANK(A8), "", IF(OR(B8="Q1", B8="Q2"), B8, IF(ISNUMBER(B8), IF(DAY(B8)<=15, "Q1", "Q2"), IF(MID(TRIM(B8),3,1)="/", IF(VALUE(LEFT(TRIM(B8),2))<=15, "Q1", "Q2"), IF(MID(TRIM(B8),5,1)="-", IF(VALUE(MID(TRIM(B8),9,2))<=15, "Q1", "Q2"), "Q1"))))) -> Q1
A9: M-0238 | B9: 46297 | C9: 10:09 PM | D9: Gasto | E9: Moto | F9: Gasolina | G9: Gasolina moto | H9: 33000 | I9: Transferencia | J9: Nequi | K9: octubre | L9: 2026 | M9: Telegram | O9: =IF(ISBLANK(A9), "", IF(AND(LOWER(TRIM(K9))=LOWER(TRIM(PANEL!$L$2)), L9=PANEL!$I$2), MAX($O$4:O8)+1, "")) -> 5 | P9: =IF(ISBLANK(A9), "", IF(OR(B9="Q1", B9="Q2"), B9, IF(ISNUMBER(B9), IF(DAY(B9)<=15, "Q1", "Q2"), IF(MID(TRIM(B9),3,1)="/", IF(VALUE(LEFT(TRIM(B9),2))<=15, "Q1", "Q2"), IF(MID(TRIM(B9),5,1)="-", IF(VALUE(MID(TRIM(B9),9,2))<=15, "Q1", "Q2"), "Q1"))))) -> Q1
A10: M-0237 | B10: 46297 | C10: 09:57 PM | D10: Gasto | E10: Gastos Hormiga / Dulces | F10: General | G10: Endulzada de amigo secreto | H10: 33000 | I10: Efectivo | J10: Efectivo | K10: octubre | L10: 2026 | M10: Telegram | O10: =IF(ISBLANK(A10), "", IF(AND(LOWER(TRIM(K10))=LOWER(TRIM(PANEL!$L$2)), L10=PANEL!$I$2), MAX($O$4:O9)+1, "")) -> 6 | P10: =IF(ISBLANK(A10), "", IF(OR(B10="Q1", B10="Q2"), B10, IF(ISNUMBER(B10), IF(DAY(B10)<=15, "Q1", "Q2"), IF(MID(TRIM(B10),3,1)="/", IF(VALUE(LEFT(TRIM(B10),2))<=15, "Q1", "Q2"), IF(MID(TRIM(B10),5,1)="-", IF(VALUE(MID(TRIM(B10),9,2))<=15, "Q1", "Q2"), "Q1"))))) -> Q1
A11: M-0235 | B11: 46295 | C11: 09:40 PM | D11: Gasto | E11: Vivienda | F11: Pago fijo | G11: ARRIENDO CASA - Factura septiembre 2026 | H11: 900000 | I11: Transferencia | J11: Nequi | K11: septiembre | L11: 2026 | M11: Telegram | N11: PAGO_FIJO|F-0101|septiembre|2026 | O11: =IF(ISBLANK(A11), "", IF(AND(LOWER(TRIM(K11))=LOWER(TRIM(PANEL!$L$2)), L11=PANEL!$I$2), MAX($O$4:O10)+1, "")) | P11: =IF(ISBLANK(A11), "", IF(OR(B11="Q1", B11="Q2"), B11, IF(ISNUMBER(B11), IF(DAY(B11)<=15, "Q1", "Q2"), IF(MID(TRIM(B11),3,1)="/", IF(VALUE(LEFT(TRIM(B11),2))<=15, "Q1", "Q2"), IF(MID(TRIM(B11),5,1)="-", IF(VALUE(MID(TRIM(B11),9,2))<=15, "Q1", "Q2"), "Q1"))))) -> Q2
A12: M-0234 | B12: 46295 | C12: 09:38 PM | D12: Gasto | E12: Servicios | F12: Pago fijo | G12: CUOTA DATOS CELULAR - Factura septiembre 2026 | H12: 43900 | I12: Transferencia | J12: Nequi | K12: septiembre | L12: 2026 | M12: Telegram | N12: PAGO_FIJO|F-0100|septiembre|2026 | O12: =IF(ISBLANK(A12), "", IF(AND(LOWER(TRIM(K12))=LOWER(TRIM(PANEL!$L$2)), L12=PANEL!$I$2), MAX($O$4:O11)+1, "")) | P12: =IF(ISBLANK(A12), "", IF(OR(B12="Q1", B12="Q2"), B12, IF(ISNUMBER(B12), IF(DAY(B12)<=15, "Q1", "Q2"), IF(MID(TRIM(B12),3,1)="/", IF(VALUE(LEFT(TRIM(B12),2))<=15, "Q1", "Q2"), IF(MID(TRIM(B12),5,1)="-", IF(VALUE(MID(TRIM(B12),9,2))<=15, "Q1", "Q2"), "Q1"))))) -> Q2
A13: M-0233 | B13: 46297 | C13: 12:54 PM | D13: Gasto | E13: Gastos Hormiga / Dulces | F13: General | G13: Endulzada | H13: 34000 | I13: Efectivo | J13: Efectivo | K13: octubre | L13: 2026 | M13: Telegram | O13: =IF(ISBLANK(A13), "", IF(AND(LOWER(TRIM(K13))=LOWER(TRIM(PANEL!$L$2)), L13=PANEL!$I$2), MAX($O$4:O12)+1, "")) -> 7 | P13: =IF(ISBLANK(A13), "", IF(OR(B13="Q1", B13="Q2"), B13, IF(ISNUMBER(B13), IF(DAY(B13)<=15, "Q1", "Q2"), IF(MID(TRIM(B13),3,1)="/", IF(VALUE(LEFT(TRIM(B13),2))<=15, "Q1", "Q2"), IF(MID(TRIM(B13),5,1)="-", IF(VALUE(MID(TRIM(B13),9,2))<=15, "Q1", "Q2"), "Q1"))))) -> Q1
A14: M-0232 | B14: 46296 | C14: 09:42 PM | D14: Gasto | E14: Moto | F14: Gasolina | G14: Gasolina para moto | H14: 33000 | I14: Transferencia | J14: Nequi | K14: octubre | L14: 2026 | M14: Telegram | O14: =IF(ISBLANK(A14), "", IF(AND(LOWER(TRIM(K14))=LOWER(TRIM(PANEL!$L$2)), L14=PANEL!$I$2), MAX($O$4:O13)+1, "")) -> 8 | P14: =IF(ISBLANK(A14), "", IF(OR(B14="Q1", B14="Q2"), B14, IF(ISNUMBER(B14), IF(DAY(B14)<=15, "Q1", "Q2"), IF(MID(TRIM(B14),3,1)="/", IF(VALUE(LEFT(TRIM(B14),2))<=15, "Q1", "Q2"), IF(MID(TRIM(B14),5,1)="-", IF(VALUE(MID(TRIM(B14),9,2))<=15, "Q1", "Q2"), "Q1"))))) -> Q1
A15: M-0230 | B15: Q1 | C15: 08:22 PM | D15: Ingreso | E15: Salario | F15: Nómina | G15: Nómina Colanta | H15: 2339862 | I15: Transferencia / Nómina | J15: Colilla_Enero_Q1.pdf | K15: enero | L15: 2026 | M15: Telegram | N15: Ref Colilla: CP-0003 | O15: =IF(ISBLANK(A15), "", IF(AND(LOWER(TRIM(K15))=LOWER(TRIM(PANEL!$L$2)), L15=PANEL!$I$2), MAX($O$4:O14)+1, "")) | P15: =IF(ISBLANK(A15), "", IF(OR(B15="Q1", B15="Q2"), B15, IF(ISNUMBER(B15), IF(DAY(B15)<=15, "Q1", "Q2"), IF(MID(TRIM(B15),3,1)="/", IF(VALUE(LEFT(TRIM(B15),2))<=15, "Q1", "Q2"), IF(MID(TRIM(B15),5,1)="-", IF(VALUE(MID(TRIM(B15),9,2))<=15, "Q1", "Q2"), "Q1"))))) -> Q1
A16: M-0229 | B16: Q2 | C16: 08:22 PM | D16: Ingreso | E16: Salario | F16: Nómina | G16: Nómina Colanta | H16: 1502360 | I16: Transferencia / Nómina | J16: Colilla_Enero_Q2.pdf | K16: enero | L16: 2026 | M16: Telegram | N16: Ref Colilla: CP-0002 | O16: =IF(ISBLANK(A16), "", IF(AND(LOWER(TRIM(K16))=LOWER(TRIM(PANEL!$L$2)), L16=PANEL!$I$2), MAX($O$4:O15)+1, "")) | P16: =IF(ISBLANK(A16), "", IF(OR(B16="Q1", B16="Q2"), B16, IF(ISNUMBER(B16), IF(DAY(B16)<=15, "Q1", "Q2"), IF(MID(TRIM(B16),3,1)="/", IF(VALUE(LEFT(TRIM(B16),2))<=15, "Q1", "Q2"), IF(MID(TRIM(B16),5,1)="-", IF(VALUE(MID(TRIM(B16),9,2))<=15, "Q1", "Q2"), "Q1"))))) -> Q2
A17: M-0228 | B17: Q1 | C17: 08:22 PM | D17: Ingreso | E17: Salario | F17: Nómina | G17: Nómina Colanta | H17: 1687372 | I17: Transferencia / Nómina | J17: Colilla_Febrero_Q1.pdf | K17: febrero | L17: 2026 | M17: Telegram | N17: Ref Colilla: CP-0005 | O17: =IF(ISBLANK(A17), "", IF(AND(LOWER(TRIM(K17))=LOWER(TRIM(PANEL!$L$2)), L17=PANEL!$I$2), MAX($O$4:O16)+1, "")) | P17: =IF(ISBLANK(A17), "", IF(OR(B17="Q1", B17="Q2"), B17, IF(ISNUMBER(B17), IF(DAY(B17)<=15, "Q1", "Q2"), IF(MID(TRIM(B17),3,1)="/", IF(VALUE(LEFT(TRIM(B17),2))<=15, "Q1", "Q2"), IF(MID(TRIM(B17),5,1)="-", IF(VALUE(MID(TRIM(B17),9,2))<=15, "Q1", "Q2"), "Q1"))))) -> Q1
A18: M-0227 | B18: Q2 | C18: 08:22 PM | D18: Ingreso | E18: Salario | F18: Nómina | G18: Nómina Colanta | H18: 1046300 | I18: Transferencia / Nómina | J18: Colilla_Febrero_Q2.pdf | K18: febrero | L18: 2026 | M18: Telegram | N18: Ref Colilla: CP-0004 | O18: =IF(ISBLANK(A18), "", IF(AND(LOWER(TRIM(K18))=LOWER(TRIM(PANEL!$L$2)), L18=PANEL!$I$2), MAX($O$4:O17)+1, "")) | P18: =IF(ISBLANK(A18), "", IF(OR(B18="Q1", B18="Q2"), B18, IF(ISNUMBER(B18), IF(DAY(B18)<=15, "Q1", "Q2"), IF(MID(TRIM(B18),3,1)="/", IF(VALUE(LEFT(TRIM(B18),2))<=15, "Q1", "Q2"), IF(MID(TRIM(B18),5,1)="-", IF(VALUE(MID(TRIM(B18),9,2))<=15, "Q1", "Q2"), "Q1"))))) -> Q2
A19: M-0226 | B19: Q1 | C19: 08:22 PM | D19: Ingreso | E19: Salario | F19: Nómina | G19: Nómina Colanta | H19: 1750495 | I19: Transferencia / Nómina | J19: Colilla_Marzo_Q1.pdf | K19: marzo | L19: 2026 | M19: Telegram | N19: Ref Colilla: CP-0011 | O19: =IF(ISBLANK(A19), "", IF(AND(LOWER(TRIM(K19))=LOWER(TRIM(PANEL!$L$2)), L19=PANEL!$I$2), MAX($O$4:O18)+1, "")) | P19: =IF(ISBLANK(A19), "", IF(OR(B19="Q1", B19="Q2"), B19, IF(ISNUMBER(B19), IF(DAY(B19)<=15, "Q1", "Q2"), IF(MID(TRIM(B19),3,1)="/", IF(VALUE(LEFT(TRIM(B19),2))<=15, "Q1", "Q2"), IF(MID(TRIM(B19),5,1)="-", IF(VALUE(MID(TRIM(B19),9,2))<=15, "Q1", "Q2"), "Q1"))))) -> Q1
A20: M-0225 | B20: Q2 | C20: 08:22 PM | D20: Ingreso | E20: Salario | F20: Nómina | G20: Nómina Colanta | H20: 1758916 | I20: Transferencia / Nómina | J20: Colilla_Marzo_Q2.pdf | K20: marzo | L20: 2026 | M20: Telegram | N20: Ref Colilla: CP-0012 | O20: =IF(ISBLANK(A20), "", IF(AND(LOWER(TRIM(K20))=LOWER(TRIM(PANEL!$L$2)), L20=PANEL!$I$2), MAX($O$4:O19)+1, "")) | P20: =IF(ISBLANK(A20), "", IF(OR(B20="Q1", B20="Q2"), B20, IF(ISNUMBER(B20), IF(DAY(B20)<=15, "Q1", "Q2"), IF(MID(TRIM(B20),3,1)="/", IF(VALUE(LEFT(TRIM(B20),2))<=15, "Q1", "Q2"), IF(MID(TRIM(B20),5,1)="-", IF(VALUE(MID(TRIM(B20),9,2))<=15, "Q1", "Q2"), "Q1"))))) -> Q2
A21: M-0224 | B21: Q1 | C21: 08:22 PM | D21: Ingreso | E21: Salario | F21: Nómina | G21: Nómina Colanta | H21: 1918622 | I21: Transferencia / Nómina | J21: Colilla_Abril_Q1.pdf | K21: abril | L21: 2026 | M21: Telegram | N21: Ref Colilla: CP-0013 | O21: =IF(ISBLANK(A21), "", IF(AND(LOWER(TRIM(K21))=LOWER(TRIM(PANEL!$L$2)), L21=PANEL!$I$2), MAX($O$4:O20)+1, "")) | P21: =IF(ISBLANK(A21), "", IF(OR(B21="Q1", B21="Q2"), B21, IF(ISNUMBER(B21), IF(DAY(B21)<=15, "Q1", "Q2"), IF(MID(TRIM(B21),3,1)="/", IF(VALUE(LEFT(TRIM(B21),2))<=15, "Q1", "Q2"), IF(MID(TRIM(B21),5,1)="-", IF(VALUE(MID(TRIM(B21),9,2))<=15, "Q1", "Q2"), "Q1"))))) -> Q1
A22: M-0223 | B22: Q2 | C22: 08:22 PM | D22: Ingreso | E22: Salario | F22: Nómina | G22: Nómina Colanta | H22: 1575490 | I22: Transferencia / Nómina | J22: Colilla_Abril_Q2.pdf | K22: abril | L22: 2026 | M22: Telegram | N22: Ref Colilla: CP-0014 | O22: =IF(ISBLANK(A22), "", IF(AND(LOWER(TRIM(K22))=LOWER(TRIM(PANEL!$L$2)), L22=PANEL!$I$2), MAX($O$4:O21)+1, "")) | P22: =IF(ISBLANK(A22), "", IF(OR(B22="Q1", B22="Q2"), B22, IF(ISNUMBER(B22), IF(DAY(B22)<=15, "Q1", "Q2"), IF(MID(TRIM(B22),3,1)="/", IF(VALUE(LEFT(TRIM(B22),2))<=15, "Q1", "Q2"), IF(MID(TRIM(B22),5,1)="-", IF(VALUE(MID(TRIM(B22),9,2))<=15, "Q1", "Q2"), "Q1"))))) -> Q2
A23: M-0222 | B23: Q1 | C23: 08:22 PM | D23: Ingreso | E23: Salario | F23: Nómina | G23: Nómina Colanta | H23: 1637623 | I23: Transferencia / Nómina | J23: Colilla_Mayo_Q1.pdf | K23: mayo | L23: 2026 | M23: Telegram | N23: Ref Colilla: CP-0015 | O23: =IF(ISBLANK(A23), "", IF(AND(LOWER(TRIM(K23))=LOWER(TRIM(PANEL!$L$2)), L23=PANEL!$I$2), MAX($O$4:O22)+1, "")) | P23: =IF(ISBLANK(A23), "", IF(OR(B23="Q1", B23="Q2"), B23, IF(ISNUMBER(B23), IF(DAY(B23)<=15, "Q1", "Q2"), IF(MID(TRIM(B23),3,1)="/", IF(VALUE(LEFT(TRIM(B23),2))<=15, "Q1", "Q2"), IF(MID(TRIM(B23),5,1)="-", IF(VALUE(MID(TRIM(B23),9,2))<=15, "Q1", "Q2"), "Q1"))))) -> Q1
A24: M-0221 | B24: Q2 | C24: 08:22 PM | D24: Ingreso | E24: Salario | F24: Nómina | G24: Nómina Colanta | H24: 1526130 | I24: Transferencia / Nómina | J24: Colilla_Mayo_Q2.pdf | K24: mayo | L24: 2026 | M24: Telegram | N24: Ref Colilla: CP-0006 | O24: =IF(ISBLANK(A24), "", IF(AND(LOWER(TRIM(K24))=LOWER(TRIM(PANEL!$L$2)), L24=PANEL!$I$2), MAX($O$4:O23)+1, "")) | P24: =IF(ISBLANK(A24), "", IF(OR(B24="Q1", B24="Q2"), B24, IF(ISNUMBER(B24), IF(DAY(B24)<=15, "Q1", "Q2"), IF(MID(TRIM(B24),3,1)="/", IF(VALUE(LEFT(TRIM(B24),2))<=15, "Q1", "Q2"), IF(MID(TRIM(B24),5,1)="-", IF(VALUE(MID(TRIM(B24),9,2))<=15, "Q1", "Q2"), "Q1"))))) -> Q2
A25: M-0220 | B25: Q1 | C25: 08:22 PM | D25: Ingreso | E25: Salario | F25: Nómina | G25: Nómina Colanta | H25: 3519208 | I25: Transferencia / Nómina | J25: Colilla_Junio_Q1_Prima.pdf | K25: junio | L25: 2026 | M25: Telegram | N25: Ref Colilla: CP-0016 | O25: =IF(ISBLANK(A25), "", IF(AND(LOWER(TRIM(K25))=LOWER(TRIM(PANEL!$L$2)), L25=PANEL!$I$2), MAX($O$4:O24)+1, "")) | P25: =IF(ISBLANK(A25), "", IF(OR(B25="Q1", B25="Q2"), B25, IF(ISNUMBER(B25), IF(DAY(B25)<=15, "Q1", "Q2"), IF(MID(TRIM(B25),3,1)="/", IF(VALUE(LEFT(TRIM(B25),2))<=15, "Q1", "Q2"), IF(MID(TRIM(B25),5,1)="-", IF(VALUE(MID(TRIM(B25),9,2))<=15, "Q1", "Q2"), "Q1"))))) -> Q1
A26: M-0219 | B26: Q2 | C26: 08:22 PM | D26: Ingreso | E26: Salario | F26: Nómina | G26: Nómina Colanta | H26: 1938906 | I26: Transferencia / Nómina | J26: Colilla_Junio_Q2.pdf | K26: junio | L26: 2026 | M26: Telegram | N26: Ref Colilla: CP-0017 | O26: =IF(ISBLANK(A26), "", IF(AND(LOWER(TRIM(K26))=LOWER(TRIM(PANEL!$L$2)), L26=PANEL!$I$2), MAX($O$4:O25)+1, "")) | P26: =IF(ISBLANK(A26), "", IF(OR(B26="Q1", B26="Q2"), B26, IF(ISNUMBER(B26), IF(DAY(B26)<=15, "Q1", "Q2"), IF(MID(TRIM(B26),3,1)="/", IF(VALUE(LEFT(TRIM(B26),2))<=15, "Q1", "Q2"), IF(MID(TRIM(B26),5,1)="-", IF(VALUE(MID(TRIM(B26),9,2))<=15, "Q1", "Q2"), "Q1"))))) -> Q2
... A31: M-0214 | B31: Q1 | C31: 08:21 PM | D31: Ingreso | E31: Salario | F31: Nómina | G31: Nómina Colanta | H31: 1702727 | I31: Transferencia / Nómina | J31: Colilla_Pago_Periodo_17.pdf | K31: septiembre | L31: 2026 | M31: Telegram | N31: Ref Colilla: CP-0010 | O31: =IF(ISBLANK(A31), "", IF(AND(LOWER(TRIM(K31))=LOWER(TRIM(PANEL!$L$2)), L31=PANEL!$I$2), MAX($O$4:O30)+1, "")) | P31: =IF(ISBLANK(A31), "", IF(OR(B31="Q1", B31="Q2"), B31, IF(ISNUMBER(B31), IF(DAY(B31)<=15, "Q1", "Q2"), IF(MID(TRIM(B31),3,1)="/", IF(VALUE(LEFT(TRIM(B31),2))<=15, "Q1", "Q2"), IF(MID(TRIM(B31),5,1)="-", IF(VALUE(MID(TRIM(B31),9,2))<=15, "Q1", "Q2"), "Q1"))))) -> Q1
A32: M-0212 | B32: 46295 | C32: 04:24 PM | D32: Gasto | E32: Transporte | F32: Parqueadero | G32: Parqueadero semanal | H32: 8500 | I32: No especificado | J32: No especificada | K32: septiembre | L32: 2026 | M32: Telegram | O32: =IF(ISBLANK(A32), "", IF(AND(LOWER(TRIM(K32))=LOWER(TRIM(PANEL!$L$2)), L32=PANEL!$I$2), MAX($O$4:O31)+1, "")) | P32: =IF(ISBLANK(A32), "", IF(OR(B32="Q1", B32="Q2"), B32, IF(ISNUMBER(B32), IF(DAY(B32)<=15, "Q1", "Q2"), IF(MID(TRIM(B32),3,1)="/", IF(VALUE(LEFT(TRIM(B32),2))<=15, "Q1", "Q2"), IF(MID(TRIM(B32),5,1)="-", IF(VALUE(MID(TRIM(B32),9,2))<=15, "Q1", "Q2"), "Q1"))))) -> Q2
A33: M-0210 | B33: 46293 | C33: 06:40 PM | D33: Gasto | E33: Gastos Hormiga / Dulces | F33: General | G33: Mecato en tiendas | H33: 13200 | I33: No especificado | J33: No especificada | K33: septiembre | L33: 2026 | M33: Telegram | O33: =IF(ISBLANK(A33), "", IF(AND(LOWER(TRIM(K33))=LOWER(TRIM(PANEL!$L$2)), L33=PANEL!$I$2), MAX($O$4:O32)+1, "")) | P33: =IF(ISBLANK(A33), "", IF(OR(B33="Q1", B33="Q2"), B33, IF(ISNUMBER(B33), IF(DAY(B33)<=15, "Q1", "Q2"), IF(MID(TRIM(B33),3,1)="/", IF(VALUE(LEFT(TRIM(B33),2))<=15, "Q1", "Q2"), IF(MID(TRIM(B33),5,1)="-", IF(VALUE(MID(TRIM(B33),9,2))<=15, "Q1", "Q2"), "Q1"))))) -> Q2
A34: M-0209 | B34: 46293 | C34: 03:20 PM | D34: Gasto | E34: Transporte | F34: General | G34: 8500 parqueadero trabajo | H34: 8500 | I34: No especificado | J34: No especificada | K34: septiembre | L34: 2026 | M34: Telegram | O34: =IF(ISBLANK(A34), "", IF(AND(LOWER(TRIM(K34))=LOWER(TRIM(PANEL!$L$2)), L34=PANEL!$I$2), MAX($O$4:O33)+1, "")) | P34: =IF(ISBLANK(A34), "", IF(OR(B34="Q1", B34="Q2"), B34, IF(ISNUMBER(B34), IF(DAY(B34)<=15, "Q1", "Q2"), IF(MID(TRIM(B34),3,1)="/", IF(VALUE(LEFT(TRIM(B34),2))<=15, "Q1", "Q2"), IF(MID(TRIM(B34),5,1)="-", IF(VALUE(MID(TRIM(B34),9,2))<=15, "Q1", "Q2"), "Q1"))))) -> Q2
A35: M-0208 | B35: 46291 | C35: 01:33 PM | D35: Gasto | E35: Otros | F35: General | G35: 80 mil gastos concierto feid | H35: 80000 | I35: No especificado | J35: No especificada | K35: septiembre | L35: 2026 | M35: Telegram | O35: =IF(ISBLANK(A35), "", IF(AND(LOWER(TRIM(K35))=LOWER(TRIM(PANEL!$L$2)), L35=PANEL!$I$2), MAX($O$4:O34)+1, "")) | P35: =IF(ISBLANK(A35), "", IF(OR(B35="Q1", B35="Q2"), B35, IF(ISNUMBER(B35), IF(DAY(B35)<=15, "Q1", "Q2"), IF(MID(TRIM(B35),3,1)="/", IF(VALUE(LEFT(TRIM(B35),2))<=15, "Q1", "Q2"), IF(MID(TRIM(B35),5,1)="-", IF(VALUE(MID(TRIM(B35),9,2))<=15, "Q1", "Q2"), "Q1"))))) -> Q2
A36: M-0207 | B36: 46290 | C36: 02:05 PM | D36: Gasto | E36: Otros | F36: General | G36: 22 mil pesos corte cabello | H36: 22000 | I36: No especificado | J36: No especificada | K36: septiembre | L36: 2026 | M36: Telegram | O36: =IF(ISBLANK(A36), "", IF(AND(LOWER(TRIM(K36))=LOWER(TRIM(PANEL!$L$2)), L36=PANEL!$I$2), MAX($O$4:O35)+1, "")) | P36: =IF(ISBLANK(A36), "", IF(OR(B36="Q1", B36="Q2"), B36, IF(ISNUMBER(B36), IF(DAY(B36)<=15, "Q1", "Q2"), IF(MID(TRIM(B36),3,1)="/", IF(VALUE(LEFT(TRIM(B36),2))<=15, "Q1", "Q2"), IF(MID(TRIM(B36),5,1)="-", IF(VALUE(MID(TRIM(B36),9,2))<=15, "Q1", "Q2"), "Q1"))))) -> Q2
A37: M-0206 | B37: 46290 | C37: 11:43 AM | D37: Gasto | E37: Otros | F37: General | G37: 8 mil recarga cívica metro | H37: 8000 | I37: No especificado | J37: No especificada | K37: septiembre | L37: 2026 | M37: Telegram | O37: =IF(ISBLANK(A37), "", IF(AND(LOWER(TRIM(K37))=LOWER(TRIM(PANEL!$L$2)), L37=PANEL!$I$2), MAX($O$4:O36)+1, "")) | P37: =IF(ISBLANK(A37), "", IF(OR(B37="Q1", B37="Q2"), B37, IF(ISNUMBER(B37), IF(DAY(B37)<=15, "Q1", "Q2"), IF(MID(TRIM(B37),3,1)="/", IF(VALUE(LEFT(TRIM(B37),2))<=15, "Q1", "Q2"), IF(MID(TRIM(B37),5,1)="-", IF(VALUE(MID(TRIM(B37),9,2))<=15, "Q1", "Q2"), "Q1"))))) -> Q2
A38: M-0205 | B38: 46290 | C38: 11:43 AM | D38: Gasto | E38: Moto | F38: General | G38: 8 mil didi moto transporte | H38: 8000 | I38: No especificado | J38: No especificada | K38: septiembre | L38: 2026 | M38: Telegram | O38: =IF(ISBLANK(A38), "", IF(AND(LOWER(TRIM(K38))=LOWER(TRIM(PANEL!$L$2)), L38=PANEL!$I$2), MAX($O$4:O37)+1, "")) | P38: =IF(ISBLANK(A38), "", IF(OR(B38="Q1", B38="Q2"), B38, IF(ISNUMBER(B38), IF(DAY(B38)<=15, "Q1", "Q2"), IF(MID(TRIM(B38),3,1)="/", IF(VALUE(LEFT(TRIM(B38),2))<=15, "Q1", "Q2"), IF(MID(TRIM(B38),5,1)="-", IF(VALUE(MID(TRIM(B38),9,2))<=15, "Q1", "Q2"), "Q1"))))) -> Q2
A39: M-0204 | B39: 46289 | C39: 05:37 AM | D39: Gasto | E39: Moto | F39: General | G39: 90 mil arreglo moto | H39: 90000 | I39: No especificado | J39: No especificada | K39: septiembre | L39: 2026 | M39: Telegram | O39: =IF(ISBLANK(A39), "", IF(AND(LOWER(TRIM(K39))=LOWER(TRIM(PANEL!$L$2)), L39=PANEL!$I$2), MAX($O$4:O38)+1, "")) | P39: =IF(ISBLANK(A39), "", IF(OR(B39="Q1", B39="Q2"), B39, IF(ISNUMBER(B39), IF(DAY(B39)<=15, "Q1", "Q2"), IF(MID(TRIM(B39),3,1)="/", IF(VALUE(LEFT(TRIM(B39),2))<=15, "Q1", "Q2"), IF(MID(TRIM(B39),5,1)="-", IF(VALUE(MID(TRIM(B39),9,2))<=15, "Q1", "Q2"), "Q1"))))) -> Q2
A40: M-0203 | B40: 46288 | C40: 07:50 PM | D40: Gasto | E40: Moto | F40: General | G40: 31 mil pesos gasolina moto | H40: 31000 | I40: No especificado | J40: No especificada | K40: septiembre | L40: 2026 | M40: Telegram | O40: =IF(ISBLANK(A40), "", IF(AND(LOWER(TRIM(K40))=LOWER(TRIM(PANEL!$L$2)), L40=PANEL!$I$2), MAX($O$4:O39)+1, "")) | P40: =IF(ISBLANK(A40), "", IF(OR(B40="Q1", B40="Q2"), B40, IF(ISNUMBER(B40), IF(DAY(B40)<=15, "Q1", "Q2"), IF(MID(TRIM(B40),3,1)="/", IF(VALUE(LEFT(TRIM(B40),2))<=15, "Q1", "Q2"), IF(MID(TRIM(B40),5,1)="-", IF(VALUE(MID(TRIM(B40),9,2))<=15, "Q1", "Q2"), "Q1"))))) -> Q2
A41: M-0202 | B41: 46288 | C41: 06:29 PM | D41: Gasto | E41: Alimentación | F41: Lácteos y Colanta | G41: Factura Electrónica DIAN COOPERATIVA COLANTA 804P222666 | H41: 11950 | I41: Transferencia | J41: AyC Colanta | K41: septiembre | L41: 2026 | M41: Gmail | N41: GMAIL:1a0d095b21a6f468|REF:804P222666 | O41: =IF(ISBLANK(A41), "", IF(AND(LOWER(TRIM(K41))=LOWER(TRIM(PANEL!$L$2)), L41=PANEL!$I$2), MAX($O$4:O40)+1, "")) | P41: =IF(ISBLANK(A41), "", IF(OR(B41="Q1", B41="Q2"), B41, IF(ISNUMBER(B41), IF(DAY(B41)<=15, "Q1", "Q2"), IF(MID(TRIM(B41),3,1)="/", IF(VALUE(LEFT(TRIM(B41),2))<=15, "Q1", "Q2"), IF(MID(TRIM(B41),5,1)="-", IF(VALUE(MID(TRIM(B41),9,2))<=15, "Q1", "Q2"), "Q1"))))) -> Q2
A42: M-0201 | B42: 46286 | C42: 04:45 PM | D42: Gasto | E42: Transporte | F42: Pago fijo | G42: Parqueadero Trabajo Semana - Abono parcial | H42: 8500 | I42: No especificado | J42: No especificada | K42: septiembre | L42: 2026 | M42: Telegram | N42: PAGO_FIJO|F-0095|septiembre|2026 | O42: =IF(ISBLANK(A42), "", IF(AND(LOWER(TRIM(K42))=LOWER(TRIM(PANEL!$L$2)), L42=PANEL!$I$2), MAX($O$4:O41)+1, "")) | P42: =IF(ISBLANK(A42), "", IF(OR(B42="Q1", B42="Q2"), B42, IF(ISNUMBER(B42), IF(DAY(B42)<=15, "Q1", "Q2"), IF(MID(TRIM(B42),3,1)="/", IF(VALUE(LEFT(TRIM(B42),2))<=15, "Q1", "Q2"), IF(MID(TRIM(B42),5,1)="-", IF(VALUE(MID(TRIM(B42),9,2))<=15, "Q1", "Q2"), "Q1"))))) -> Q2
A43: M-0200 | B43: 46286 | C43: 12:34 PM | D43: Gasto | E43: Alimentación | F43: Lácteos y Colanta | G43: Factura Electrónica DIAN COOPERATIVA COLANTA 454A263995 | H43: 11998 | I43: Transferencia | J43: AyC Colanta | K43: septiembre | L43: 2026 | M43: Gmail | N43: GMAIL:1a0c507a4abf1b35|REF:454A263995 | O43: =IF(ISBLANK(A43), "", IF(AND(LOWER(TRIM(K43))=LOWER(TRIM(PANEL!$L$2)), L43=PANEL!$I$2), MAX($O$4:O42)+1, "")) | P43: =IF(ISBLANK(A43), "", IF(OR(B43="Q1", B43="Q2"), B43, IF(ISNUMBER(B43), IF(DAY(B43)<=15, "Q1", "Q2"), IF(MID(TRIM(B43),3,1)="/", IF(VALUE(LEFT(TRIM(B43),2))<=15, "Q1", "Q2"), IF(MID(TRIM(B43),5,1)="-", IF(VALUE(MID(TRIM(B43),9,2))<=15, "Q1", "Q2"), "Q1"))))) -> Q2
A44: M-0199 | B44: 46285 | C44: 09:33 PM | D44: Gasto | E44: Servicios | F44: Pago fijo | G44: Google One - Pago mensual | H44: 20000 | I44: No especificado | J44: No especificada | K44: septiembre | L44: 2026 | M44: Telegram | N44: PAGO_FIJO|F-0102|septiembre|2026 | O44: =IF(ISBLANK(A44), "", IF(AND(LOWER(TRIM(K44))=LOWER(TRIM(PANEL!$L$2)), L44=PANEL!$I$2), MAX($O$4:O43)+1, "")) | P44: =IF(ISBLANK(A44), "", IF(OR(B44="Q1", B44="Q2"), B44, IF(ISNUMBER(B44), IF(DAY(B44)<=15, "Q1", "Q2"), IF(MID(TRIM(B44),3,1)="/", IF(VALUE(LEFT(TRIM(B44),2))<=15, "Q1", "Q2"), IF(MID(TRIM(B44),5,1)="-", IF(VALUE(MID(TRIM(B44),9,2))<=15, "Q1", "Q2"), "Q1"))))) -> Q2
A45: M-0198 | B45: 46285 | C45: 09:32 PM | D45: Gasto | E45: Servicios | F45: Pago fijo | G45: EPM ENERGIA - Pago mensual | H45: 120000 | I45: No especificado | J45: No especificada | K45: septiembre | L45: 2026 | M45: Telegram | N45: PAGO_FIJO|F-0092|septiembre|2026 | O45: =IF(ISBLANK(A45), "", IF(AND(LOWER(TRIM(K45))=LOWER(TRIM(PANEL!$L$2)), L45=PANEL!$I$2), MAX($O$4:O44)+1, "")) | P45: =IF(ISBLANK(A45), "", IF(OR(B45="Q1", B45="Q2"), B45, IF(ISNUMBER(B45), IF(DAY(B45)<=15, "Q1", "Q2"), IF(MID(TRIM(B45),3,1)="/", IF(VALUE(LEFT(TRIM(B45),2))<=15, "Q1", "Q2"), IF(MID(TRIM(B45),5,1)="-", IF(VALUE(MID(TRIM(B45),9,2))<=15, "Q1", "Q2"), "Q1"))))) -> Q2
A46: M-0197 | B46: 18/09/2026 | C46: 06:19 PM | D46: Gasto | E46: Alimentación | F46: Lácteos y Colanta | G46: Factura Electrónica DIAN COOPERATIVA COLANTA 454A262115 | H46: 12116 | I46: Factura Electrónica | J46: Nequi | K46: septiembre | L46: 2026 | M46: Gmail | O46: =IF(ISBLANK(A46), "", IF(AND(LOWER(TRIM(K46))=LOWER(TRIM(PANEL!$L$2)), L46=PANEL!$I$2), MAX($O$4:O45)+1, "")) | P46: =IF(ISBLANK(A46), "", IF(OR(B46="Q1", B46="Q2"), B46, IF(ISNUMBER(B46), IF(DAY(B46)<=15, "Q1", "Q2"), IF(MID(TRIM(B46),3,1)="/", IF(VALUE(LEFT(TRIM(B46),2))<=15, "Q1", "Q2"), IF(MID(TRIM(B46),5,1)="-", IF(VALUE(MID(TRIM(B46),9,2))<=15, "Q1", "Q2"), "Q1"))))) -> Q2
A47: M-0196 | B47: 17/09/2026 | C47: 10:15 AM | D47: Gasto | E47: Compras | F47: General | G47: Compre un teclado para el trabajo en 70 mil pesos | H47: 70000 | I47: No especificado | J47: No especificada | K47: septiembre | L47: 2026 | M47: Telegram | O47: =IF(ISBLANK(A47), "", IF(AND(LOWER(TRIM(K47))=LOWER(TRIM(PANEL!$L$2)), L47=PANEL!$I$2), MAX($O$4:O46)+1, "")) | P47: =IF(ISBLANK(A47), "", IF(OR(B47="Q1", B47="Q2"), B47, IF(ISNUMBER(B47), IF(DAY(B47)<=15, "Q1", "Q2"), IF(MID(TRIM(B47),3,1)="/", IF(VALUE(LEFT(TRIM(B47),2))<=15, "Q1", "Q2"), IF(MID(TRIM(B47),5,1)="-", IF(VALUE(MID(TRIM(B47),9,2))<=15, "Q1", "Q2"), "Q1"))))) -> Q2
A48: M-0189 | B48: 15/09/2026 | C48: 10:19 PM | D48: Gasto | E48: Alimentación | F48: Supermercado | G48: Pago PSE en P.A. ADDI Descripción | H48: 60000 | I48: PSE | J48: PSE | K48: septiembre | L48: 2026 | M48: Gmail | O48: =IF(ISBLANK(A48), "", IF(AND(LOWER(TRIM(K48))=LOWER(TRIM(PANEL!$L$2)), L48=PANEL!$I$2), MAX($O$4:O47)+1, "")) | P48: =IF(ISBLANK(A48), "", IF(OR(B48="Q1", B48="Q2"), B48, IF(ISNUMBER(B48), IF(DAY(B48)<=15, "Q1", "Q2"), IF(MID(TRIM(B48),3,1)="/", IF(VALUE(LEFT(TRIM(B48),2))<=15, "Q1", "Q2"), IF(MID(TRIM(B48),5,1)="-", IF(VALUE(MID(TRIM(B48),9,2))<=15, "Q1", "Q2"), "Q1"))))) -> Q1
A49: M-0188 | B49: 15/09/2026 | C49: 09:05 PM | D49: Ingreso | E49: Salario | F49: Nómina | G49: Nómina Colanta - 1ra Quincena de Septiembre 2026 (Periodo 17) | H49: 1702727 | I49: Transferencia / Nómina | J49: Bancolombia | K49: septiembre | L49: 2026 | M49: Colilla Nómina | O49: =IF(ISBLANK(A49), "", IF(AND(LOWER(TRIM(K49))=LOWER(TRIM(PANEL!$L$2)), L49=PANEL!$I$2), MAX($O$4:O48)+1, "")) | P49: =IF(ISBLANK(A49), "", IF(OR(B49="Q1", B49="Q2"), B49, IF(ISNUMBER(B49), IF(DAY(B49)<=15, "Q1", "Q2"), IF(MID(TRIM(B49),3,1)="/", IF(VALUE(LEFT(TRIM(B49),2))<=15, "Q1", "Q2"), IF(MID(TRIM(B49),5,1)="-", IF(VALUE(MID(TRIM(B49),9,2))<=15, "Q1", "Q2"), "Q1"))))) -> Q1
A50: M-0187 | B50: 15/09/2026 | C50: 04:15 PM | D50: Gasto | E50: Moto | F50: Pago fijo | G50: Parqueadero trabajo semana - abono | H50: 8500 | I50: No especificado | J50: No especificada | K50: septiembre | L50: 2026 | M50: Telegram | O50: =IF(ISBLANK(A50), "", IF(AND(LOWER(TRIM(K50))=LOWER(TRIM(PANEL!$L$2)), L50=PANEL!$I$2), MAX($O$4:O49)+1, "")) | P50: =IF(ISBLANK(A50), "", IF(OR(B50="Q1", B50="Q2"), B50, IF(ISNUMBER(B50), IF(DAY(B50)<=15, "Q1", "Q2"), IF(MID(TRIM(B50),3,1)="/", IF(VALUE(LEFT(TRIM(B50),2))<=15, "Q1", "Q2"), IF(MID(TRIM(B50),5,1)="-", IF(VALUE(MID(TRIM(B50),9,2))<=15, "Q1", "Q2"), "Q1"))))) -> Q1
A51: M-0186 | B51: 15/09/2026 | C51: 07:10 AM | D51: Gasto | E51: Entretenimiento | F51: Pago fijo | G51: Spotify | H51: 10000 | I51: No especificado | J51: No especificada | K51: septiembre | L51: 2026 | M51: Telegram | O51: =IF(ISBLANK(A51), "", IF(AND(LOWER(TRIM(K51))=LOWER(TRIM(PANEL!$L$2)), L51=PANEL!$I$2), MAX($O$4:O50)+1, "")) | P51: =IF(ISBLANK(A51), "", IF(OR(B51="Q1", B51="Q2"), B51, IF(ISNUMBER(B51), IF(DAY(B51)<=15, "Q1", "Q2"), IF(MID(TRIM(B51),3,1)="/", IF(VALUE(LEFT(TRIM(B51),2))<=15, "Q1", "Q2"), IF(MID(TRIM(B51),5,1)="-", IF(VALUE(MID(TRIM(B51),9,2))<=15, "Q1", "Q2"), "Q1"))))) -> Q1
A52: M-0185 | B52: 14/09/2026 | C52: 02:04 AM | D52: Gasto | E52: Compras | F52: Comercio electrónico | G52: Pago a DLOCAL COLOMBIA SAS por Nequi | H52: 5643 | I52: Transferencia | J52: Nequi | K52: septiembre | L52: 2026 | M52: Gmail | O52: =IF(ISBLANK(A52), "", IF(AND(LOWER(TRIM(K52))=LOWER(TRIM(PANEL!$L$2)), L52=PANEL!$I$2), MAX($O$4:O51)+1, "")) | P52: =IF(ISBLANK(A52), "", IF(OR(B52="Q1", B52="Q2"), B52, IF(ISNUMBER(B52), IF(DAY(B52)<=15, "Q1", "Q2"), IF(MID(TRIM(B52),3,1)="/", IF(VALUE(LEFT(TRIM(B52),2))<=15, "Q1", "Q2"), IF(MID(TRIM(B52),5,1)="-", IF(VALUE(MID(TRIM(B52),9,2))<=15, "Q1", "Q2"), "Q1"))))) -> Q1
A53: M-0182 | B53: 14/09/2026 | C53: 11:41 AM | D53: Gasto | E53: Alimentación | F53: General | G53: 50 mil comida rápida san felix | H53: 50000 | I53: No especificado | J53: No especificada | K53: septiembre | L53: 2026 | M53: Telegram | O53: =IF(ISBLANK(A53), "", IF(AND(LOWER(TRIM(K53))=LOWER(TRIM(PANEL!$L$2)), L53=PANEL!$I$2), MAX($O$4:O52)+1, "")) | P53: =IF(ISBLANK(A53), "", IF(OR(B53="Q1", B53="Q2"), B53, IF(ISNUMBER(B53), IF(DAY(B53)<=15, "Q1", "Q2"), IF(MID(TRIM(B53),3,1)="/", IF(VALUE(LEFT(TRIM(B53),2))<=15, "Q1", "Q2"), IF(MID(TRIM(B53),5,1)="-", IF(VALUE(MID(TRIM(B53),9,2))<=15, "Q1", "Q2"), "Q1"))))) -> Q1
A54: M-0181 | B54: 14/09/2026 | C54: 05:41 AM | D54: Gasto | E54: Otros | F54: General | G54: 105 mil flores salo | H54: 105000 | I54: No especificado | J54: No especificada | K54: septiembre | L54: 2026 | M54: Telegram | O54: =IF(ISBLANK(A54), "", IF(AND(LOWER(TRIM(K54))=LOWER(TRIM(PANEL!$L$2)), L54=PANEL!$I$2), MAX($O$4:O53)+1, "")) | P54: =IF(ISBLANK(A54), "", IF(OR(B54="Q1", B54="Q2"), B54, IF(ISNUMBER(B54), IF(DAY(B54)<=15, "Q1", "Q2"), IF(MID(TRIM(B54),3,1)="/", IF(VALUE(LEFT(TRIM(B54),2))<=15, "Q1", "Q2"), IF(MID(TRIM(B54),5,1)="-", IF(VALUE(MID(TRIM(B54),9,2))<=15, "Q1", "Q2"), "Q1"))))) -> Q1
A55: M-0180 | B55: 10/09/2026 | C55: 11:42 PM | D55: Gasto | E55: Otros | F55: General | G55: 62 mil granizados | H55: 62000 | I55: No especificado | J55: No especificada | K55: septiembre | L55: 2026 | M55: Telegram | O55: =IF(ISBLANK(A55), "", IF(AND(LOWER(TRIM(K55))=LOWER(TRIM(PANEL!$L$2)), L55=PANEL!$I$2), MAX($O$4:O54)+1, "")) | P55: =IF(ISBLANK(A55), "", IF(OR(B55="Q1", B55="Q2"), B55, IF(ISNUMBER(B55), IF(DAY(B55)<=15, "Q1", "Q2"), IF(MID(TRIM(B55),3,1)="/", IF(VALUE(LEFT(TRIM(B55),2))<=15, "Q1", "Q2"), IF(MID(TRIM(B55),5,1)="-", IF(VALUE(MID(TRIM(B55),9,2))<=15, "Q1", "Q2"), "Q1"))))) -> Q1
A56: M-0184 | B56: 09/09/2026 | C56: 03:04 PM | D56: Gasto | E56: Alimentación | F56: Lácteos y Colanta | G56: Factura Electrónica DIAN COOPERATIVA COLANTA 108P170676 | H56: 13537 | I56: Factura Electrónica | J56: Nequi | K56: septiembre | L56: 2026 | M56: Gmail | O56: =IF(ISBLANK(A56), "", IF(AND(LOWER(TRIM(K56))=LOWER(TRIM(PANEL!$L$2)), L56=PANEL!$I$2), MAX($O$4:O55)+1, "")) | P56: =IF(ISBLANK(A56), "", IF(OR(B56="Q1", B56="Q2"), B56, IF(ISNUMBER(B56), IF(DAY(B56)<=15, "Q1", "Q2"), IF(MID(TRIM(B56),3,1)="/", IF(VALUE(LEFT(TRIM(B56),2))<=15, "Q1", "Q2"), IF(MID(TRIM(B56),5,1)="-", IF(VALUE(MID(TRIM(B56),9,2))<=15, "Q1", "Q2"), "Q1"))))) -> Q1
A57: M-0179 | B57: 09/09/2026 | C57: 09:04 PM | D57: Gasto | E57: Moto | F57: Mantenimiento | G57: Arreglo de llanta ponchada de moto | H57: 20000 | I57: No especificado | J57: No especificada | K57: septiembre | L57: 2026 | M57: Telegram | O57: =IF(ISBLANK(A57), "", IF(AND(LOWER(TRIM(K57))=LOWER(TRIM(PANEL!$L$2)), L57=PANEL!$I$2), MAX($O$4:O56)+1, "")) | P57: =IF(ISBLANK(A57), "", IF(OR(B57="Q1", B57="Q2"), B57, IF(ISNUMBER(B57), IF(DAY(B57)<=15, "Q1", "Q2"), IF(MID(TRIM(B57),3,1)="/", IF(VALUE(LEFT(TRIM(B57),2))<=15, "Q1", "Q2"), IF(MID(TRIM(B57),5,1)="-", IF(VALUE(MID(TRIM(B57),9,2))<=15, "Q1", "Q2"), "Q1"))))) -> Q1
... A231: M-0144 | B231: 15/01/2026 | C231: 04:57 PM | D231: Ingreso | E231: Salario | F231: Nómina | G231: Nómina Colanta | H231: 2339862 | I231: Transferencia / Nómina | J231: AyC Colanta | K231: enero | L231: 2026 | M231: Telegram | O231: =IF(ISBLANK(A231), "", IF(AND(LOWER(TRIM(K231))=LOWER(TRIM(PANEL!$L$2)), L231=PANEL!$I$2), MAX($O$4:O230)+1, "")) | P231: =IF(ISBLANK(A231), "", IF(OR(B231="Q1", B231="Q2"), B231, IF(ISNUMBER(B231), IF(DAY(B231)<=15, "Q1", "Q2"), IF(MID(TRIM(B231),3,1)="/", IF(VALUE(LEFT(TRIM(B231),2))<=15, "Q1", "Q2"), IF(MID(TRIM(B231),5,1)="-", IF(VALUE(MID(TRIM(B231),9,2))<=15, "Q1", "Q2"), "Q1"))))) -> Q1
O232: =IF(ISBLANK(A232), "", IF(AND(LOWER(TRIM(K232))=LOWER(TRIM(PANEL!$L$2)), L232=PANEL!$I$2), MAX($O$4:O231)+1, "")) | P232: =IF(ISBLANK(A232), "", IF(OR(B232="Q1", B232="Q2"), B232, IF(ISNUMBER(B232), IF(DAY(B232)<=15, "Q1", "Q2"), IF(MID(TRIM(B232),3,1)="/", IF(VALUE(LEFT(TRIM(B232),2))<=15, "Q1", "Q2"), IF(MID(TRIM(B232),5,1)="-", IF(VALUE(MID(TRIM(B232),9,2))<=15, "Q1", "Q2"), "Q1")))))
O233: =IF(ISBLANK(A233), "", IF(AND(LOWER(TRIM(K233))=LOWER(TRIM(PANEL!$L$2)), L233=PANEL!$I$2), MAX($O$4:O232)+1, "")) | P233: =IF(ISBLANK(A233), "", IF(OR(B233="Q1", B233="Q2"), B233, IF(ISNUMBER(B233), IF(DAY(B233)<=15, "Q1", "Q2"), IF(MID(TRIM(B233),3,1)="/", IF(VALUE(LEFT(TRIM(B233),2))<=15, "Q1", "Q2"), IF(MID(TRIM(B233),5,1)="-", IF(VALUE(MID(TRIM(B233),9,2))<=15, "Q1", "Q2"), "Q1")))))
O234: =IF(ISBLANK(A234), "", IF(AND(LOWER(TRIM(K234))=LOWER(TRIM(PANEL!$L$2)), L234=PANEL!$I$2), MAX($O$4:O233)+1, "")) | P234: =IF(ISBLANK(A234), "", IF(OR(B234="Q1", B234="Q2"), B234, IF(ISNUMBER(B234), IF(DAY(B234)<=15, "Q1", "Q2"), IF(MID(TRIM(B234),3,1)="/", IF(VALUE(LEFT(TRIM(B234),2))<=15, "Q1", "Q2"), IF(MID(TRIM(B234),5,1)="-", IF(VALUE(MID(TRIM(B234),9,2))<=15, "Q1", "Q2"), "Q1")))))
O235: =IF(ISBLANK(A235), "", IF(AND(LOWER(TRIM(K235))=LOWER(TRIM(PANEL!$L$2)), L235=PANEL!$I$2), MAX($O$4:O234)+1, "")) | P235: =IF(ISBLANK(A235), "", IF(OR(B235="Q1", B235="Q2"), B235, IF(ISNUMBER(B235), IF(DAY(B235)<=15, "Q1", "Q2"), IF(MID(TRIM(B235),3,1)="/", IF(VALUE(LEFT(TRIM(B235),2))<=15, "Q1", "Q2"), IF(MID(TRIM(B235),5,1)="-", IF(VALUE(MID(TRIM(B235),9,2))<=15, "Q1", "Q2"), "Q1")))))
O236: =IF(ISBLANK(A236), "", IF(AND(LOWER(TRIM(K236))=LOWER(TRIM(PANEL!$L$2)), L236=PANEL!$I$2), MAX($O$4:O235)+1, "")) | P236: =IF(ISBLANK(A236), "", IF(OR(B236="Q1", B236="Q2"), B236, IF(ISNUMBER(B236), IF(DAY(B236)<=15, "Q1", "Q2"), IF(MID(TRIM(B236),3,1)="/", IF(VALUE(LEFT(TRIM(B236),2))<=15, "Q1", "Q2"), IF(MID(TRIM(B236),5,1)="-", IF(VALUE(MID(TRIM(B236),9,2))<=15, "Q1", "Q2"), "Q1")))))
O237: =IF(ISBLANK(A237), "", IF(AND(LOWER(TRIM(K237))=LOWER(TRIM(PANEL!$L$2)), L237=PANEL!$I$2), MAX($O$4:O236)+1, "")) | P237: =IF(ISBLANK(A237), "", IF(OR(B237="Q1", B237="Q2"), B237, IF(ISNUMBER(B237), IF(DAY(B237)<=15, "Q1", "Q2"), IF(MID(TRIM(B237),3,1)="/", IF(VALUE(LEFT(TRIM(B237),2))<=15, "Q1", "Q2"), IF(MID(TRIM(B237),5,1)="-", IF(VALUE(MID(TRIM(B237),9,2))<=15, "Q1", "Q2"), "Q1")))))
O238: =IF(ISBLANK(A238), "", IF(AND(LOWER(TRIM(K238))=LOWER(TRIM(PANEL!$L$2)), L238=PANEL!$I$2), MAX($O$4:O237)+1, "")) | P238: =IF(ISBLANK(A238), "", IF(OR(B238="Q1", B238="Q2"), B238, IF(ISNUMBER(B238), IF(DAY(B238)<=15, "Q1", "Q2"), IF(MID(TRIM(B238),3,1)="/", IF(VALUE(LEFT(TRIM(B238),2))<=15, "Q1", "Q2"), IF(MID(TRIM(B238),5,1)="-", IF(VALUE(MID(TRIM(B238),9,2))<=15, "Q1", "Q2"), "Q1")))))
O239: =IF(ISBLANK(A239), "", IF(AND(LOWER(TRIM(K239))=LOWER(TRIM(PANEL!$L$2)), L239=PANEL!$I$2), MAX($O$4:O238)+1, "")) | P239: =IF(ISBLANK(A239), "", IF(OR(B239="Q1", B239="Q2"), B239, IF(ISNUMBER(B239), IF(DAY(B239)<=15, "Q1", "Q2"), IF(MID(TRIM(B239),3,1)="/", IF(VALUE(LEFT(TRIM(B239),2))<=15, "Q1", "Q2"), IF(MID(TRIM(B239),5,1)="-", IF(VALUE(MID(TRIM(B239),9,2))<=15, "Q1", "Q2"), "Q1")))))
O240: =IF(ISBLANK(A240), "", IF(AND(LOWER(TRIM(K240))=LOWER(TRIM(PANEL!$L$2)), L240=PANEL!$I$2), MAX($O$4:O239)+1, "")) | P240: =IF(ISBLANK(A240), "", IF(OR(B240="Q1", B240="Q2"), B240, IF(ISNUMBER(B240), IF(DAY(B240)<=15, "Q1", "Q2"), IF(MID(TRIM(B240),3,1)="/", IF(VALUE(LEFT(TRIM(B240),2))<=15, "Q1", "Q2"), IF(MID(TRIM(B240),5,1)="-", IF(VALUE(MID(TRIM(B240),9,2))<=15, "Q1", "Q2"), "Q1")))))
O241: =IF(ISBLANK(A241), "", IF(AND(LOWER(TRIM(K241))=LOWER(TRIM(PANEL!$L$2)), L241=PANEL!$I$2), MAX($O$4:O240)+1, "")) | P241: =IF(ISBLANK(A241), "", IF(OR(B241="Q1", B241="Q2"), B241, IF(ISNUMBER(B241), IF(DAY(B241)<=15, "Q1", "Q2"), IF(MID(TRIM(B241),3,1)="/", IF(VALUE(LEFT(TRIM(B241),2))<=15, "Q1", "Q2"), IF(MID(TRIM(B241),5,1)="-", IF(VALUE(MID(TRIM(B241),9,2))<=15, "Q1", "Q2"), "Q1")))))
O242: =IF(ISBLANK(A242), "", IF(AND(LOWER(TRIM(K242))=LOWER(TRIM(PANEL!$L$2)), L242=PANEL!$I$2), MAX($O$4:O241)+1, "")) | P242: =IF(ISBLANK(A242), "", IF(OR(B242="Q1", B242="Q2"), B242, IF(ISNUMBER(B242), IF(DAY(B242)<=15, "Q1", "Q2"), IF(MID(TRIM(B242),3,1)="/", IF(VALUE(LEFT(TRIM(B242),2))<=15, "Q1", "Q2"), IF(MID(TRIM(B242),5,1)="-", IF(VALUE(MID(TRIM(B242),9,2))<=15, "Q1", "Q2"), "Q1")))))
O243: =IF(ISBLANK(A243), "", IF(AND(LOWER(TRIM(K243))=LOWER(TRIM(PANEL!$L$2)), L243=PANEL!$I$2), MAX($O$4:O242)+1, "")) | P243: =IF(ISBLANK(A243), "", IF(OR(B243="Q1", B243="Q2"), B243, IF(ISNUMBER(B243), IF(DAY(B243)<=15, "Q1", "Q2"), IF(MID(TRIM(B243),3,1)="/", IF(VALUE(LEFT(TRIM(B243),2))<=15, "Q1", "Q2"), IF(MID(TRIM(B243),5,1)="-", IF(VALUE(MID(TRIM(B243),9,2))<=15, "Q1", "Q2"), "Q1")))))
... O246: =IF(ISBLANK(A246), "", IF(AND(LOWER(TRIM(K246))=LOWER(TRIM(PANEL!$L$2)), L246=PANEL!$I$2), MAX($O$4:O245)+1, "")) | P246: =IF(ISBLANK(A246), "", IF(OR(B246="Q1", B246="Q2"), B246, IF(ISNUMBER(B246), IF(DAY(B246)<=15, "Q1", "Q2"), IF(MID(TRIM(B246),3,1)="/", IF(VALUE(LEFT(TRIM(B246),2))<=15, "Q1", "Q2"), IF(MID(TRIM(B246),5,1)="-", IF(VALUE(MID(TRIM(B246),9,2))<=15, "Q1", "Q2"), "Q1")))))

Sheet COLILLAS DE PAGO
A1: 📄 AUDITORÍA DE NÓMINA — COOPERATIVA COLANTA
A2: Registro histórico auditable de desprendibles quincenales y liquidación de prestaciones sociales Colanta
A4: ID Colilla | B4: Mes | C4: Año | D4: Quincena | E4: Período Liquidado | F4: Días | G4: Básico Quincenal ($) | H4: Extras y Recargos ($) | I4: Otros Devengados ($) | J4: TOTAL DEVENGADO ($) | K4: Salud EPS Sura ($) | L4: Pensión Porvenir ($) | M4: Fondo Empleados AyC ($) | N4: Otras Deducciones ($) | O4: NETO A COBRAR ($) | P4: Cuenta Consignación | Q4: Fecha Pago Real | R4: Estado | S4: Observaciones | T4: Ref. Documento
A5: CP-0018 | B5: septiembre | C5: 2026 | D5: Q2 | E5: 16/09/2026 al 30/09/2026 | F5: 15 | G5: 1627897 | H5: 572448 | I5: 95955 | J5: 2296300 | K5: 88014 | L5: 88014 | M5: 236121 | N5: 243873 | O5: 1640278 | P5: AyC Colanta | Q5: 46295 | R5: Pagado | S5: 2da Quincena Septiembre Periodo 18 | T5: Colilla_Pago_Periodo_18.pdf
A6: CP-0010 | B6: septiembre | C6: 2026 | D6: Q1 | E6: 01/09/2026 al 15/09/2026 | F6: 15 | G6: 1878342 | H6: 324238 | I6: 95956 | J6: 2298536 | K6: 88154 | L6: 88154 | M6: 236121 | N6: 183380 | O6: 1702727 | P6: AyC Colanta | Q6: 15/09/2026 | R6: Pagado | S6: 1ra Quincena Septiembre Periodo 17 | T6: Colilla_Pago_Periodo_17.pdf
A7: CP-0009 | B7: agosto | C7: 2026 | D7: Q2 | E7: 16/08/2026 al 31/08/2026 | F7: 15 | G7: 1878342 | H7: 420000 | I7: 402384 | J7: 2700726 | K7: 103935 | L7: 103935 | M7: 236121 | N7: 183380 | O7: 2073355 | P7: AyC Colanta | Q7: 31/08/2026 | R7: Pagado | S7: 2da Quincena Agosto Colanta | T7: Colilla_Agosto_Q2.pdf
A8: CP-0001 | B8: agosto | C8: 2026 | D8: Q1 | E8: 01/08/2026 al 15/08/2026 | F8: 15 | G8: 1878342 | H8: 220000 | I8: 197958 | J8: 2296300 | K8: 88037 | L8: 88037 | M8: 236121 | N8: 222067 | O8: 1662038 | P8: AyC Colanta | Q8: 15/08/2026 | R8: Pagado | S8: 1ra Quincena Agosto Colanta | T8: Colilla_Agosto_Q1.pdf
A9: CP-0008 | B9: julio | C9: 2026 | D9: Q2 | E9: 16/07/2026 al 31/07/2026 | F9: 15 | G9: 1878342 | H9: 120000 | I9: 107576 | J9: 2105918 | K9: 80143 | L9: 80143 | M9: 236121 | N9: 211709 | O9: 1497802 | P9: AyC Colanta | Q9: 31/07/2026 | R9: Pagado | S9: 2da Quincena Julio Colanta | T9: Colilla_Julio_Q2.pdf
A10: CP-0007 | B10: julio | C10: 2026 | D10: Q1 | E10: 01/07/2026 al 15/07/2026 | F10: 15 | G10: 1878342 | H10: 210000 | I10: 193461 | J10: 2281803 | K10: 87533 | L10: 87533 | M10: 236121 | N10: 196227 | O10: 1674389 | P10: AyC Colanta | Q10: 15/07/2026 | R10: Pagado | S10: 1ra Quincena Julio Colanta | T10: Colilla_Julio_Q1.pdf
A11: CP-0017 | B11: junio | C11: 2026 | D11: Q2 | E11: 16/06/2026 al 30/06/2026 | F11: 15 | G11: 1878342 | H11: 350000 | I11: 311658 | J11: 2540000 | K11: 90000 | L11: 90000 | M11: 236121 | N11: 184973 | O11: 1938906 | P11: AyC Colanta | Q11: 30/06/2026 | R11: Pagado | S11: 2da Quincena Junio Colanta | T11: Colilla_Junio_Q2.pdf
A12: CP-0016 | B12: junio | C12: 2026 | D12: Q1 | E12: 01/06/2026 al 15/06/2026 | F12: 15 | G12: 1878342 | H12: 450000 | I12: 1921658 | J12: 4250000 | K12: 110000 | L12: 110000 | M12: 236121 | N12: 274671 | O12: 3519208 | P12: AyC Colanta | Q12: 15/06/2026 | R12: Pagado | S12: 1ra Quincena Junio + Prima Colanta | T12: Colilla_Junio_Q1_Prima.pdf
A13: CP-0006 | B13: mayo | C13: 2026 | D13: Q2 | E13: 16/05/2026 al 31/05/2026 | F13: 15 | G13: 1878342 | H13: 120000 | I13: 107575 | J13: 2105917 | K13: 80143 | L13: 80143 | M13: 236121 | N13: 183380 | O13: 1526130 | P13: AyC Colanta | Q13: 31/05/2026 | R13: Pagado | S13: 2da Quincena Mayo Colanta | T13: Colilla_Mayo_Q2.pdf
A14: CP-0015 | B14: mayo | C14: 2026 | D14: Q1 | E14: 01/05/2026 al 15/05/2026 | F14: 15 | G14: 1878342 | H14: 180000 | I14: 181658 | J14: 2240000 | K14: 86000 | L14: 86000 | M14: 236121 | N14: 194256 | O14: 1637623 | P14: AyC Colanta | Q14: 15/05/2026 | R14: Pagado | S14: 1ra Quincena Mayo Colanta | T14: Colilla_Mayo_Q1.pdf
A15: CP-0014 | B15: abril | C15: 2026 | D15: Q2 | E15: 16/04/2026 al 30/04/2026 | F15: 15 | G15: 1878342 | H15: 150000 | I15: 151658 | J15: 2180000 | K15: 85000 | L15: 85000 | M15: 236121 | N15: 198389 | O15: 1575490 | P15: AyC Colanta | Q15: 30/04/2026 | R15: Pagado | S15: 2da Quincena Abril Colanta | T15: Colilla_Abril_Q2.pdf
A16: CP-0013 | B16: abril | C16: 2026 | D16: Q1 | E16: 01/04/2026 al 15/04/2026 | F16: 15 | G16: 1878342 | H16: 320000 | I16: 321658 | J16: 2520000 | K16: 92000 | L16: 92000 | M16: 236121 | N16: 181257 | O16: 1918622 | P16: AyC Colanta | Q16: 15/04/2026 | R16: Pagado | S16: 1ra Quincena Abril Colanta | T16: Colilla_Abril_Q1.pdf
A17: CP-0012 | B17: marzo | C17: 2026 | D17: Q2 | E17: 16/03/2026 al 31/03/2026 | F17: 15 | G17: 1878342 | H17: 240000 | I17: 241658 | J17: 2360000 | K17: 88000 | L17: 88000 | M17: 236121 | N17: 188963 | O17: 1758916 | P17: AyC Colanta | Q17: 31/03/2026 | R17: Pagado | S17: 2da Quincena Marzo Colanta | T17: Colilla_Marzo_Q2.pdf
... A22: CP-0003 | B22: enero | C22: 2026 | D22: Q1 | E22: 01/01/2026 al 15/01/2026 | F22: 15 | G22: 1878342 | H22: 550000 | I22: 558122 | J22: 2986464 | K22: 91518 | L22: 91518 | M22: 236121 | N22: 227445 | O22: 2339862 | P22: AyC Colanta | Q22: 15/01/2026 | R22: Pagado | S22: 1ra Quincena Enero Colanta | T22: Colilla_Enero_Q1.pdf
B23: PROYECCIÓN PRESTACIONAL LEGAL Y FONDOS ANUALES COLANTA
B24: Concepto Prestacional / Beneficio | E24: Base de Cálculo | G24: Fecha Legal Entrega | I24: Valor Proyectado ($) | K24: Destino Sugerido / Recomendación
B25: Prima Legal de Servicios (Junio) | E25: 50% Salario Promedio Semestre I | G25: 30 de Junio | I25: =AVERAGE(J4:J22) -> 2418909.1 | K25: Ahorro / Abono a compromisos
B26: Prima Legal de Servicios (Diciembre) | E26: 50% Salario Promedio Semestre II | G26: 20 de Diciembre | I26: =AVERAGE(J4:J22) -> 2418909.1 | K26: Fin de año y proyectos
B27: Ahorro Navideño Cooperativa Colanta | E27: $120.000 quincenal en nómina | G27: 01 de Diciembre | I27: =AHORROS!C9 -> 2160000 | K27: Entrega Fondo Colanta
B28: Cesantías Anuales de Ley | E28: 1 Mes de Salario Completo por Año | G28: 14 de Febrero (a Fondo) | I28: =AVERAGE(J4:J22)*2 -> 4837818.1 | K28: Consignación Fondo Porvenir
B29: Intereses a las Cesantías (12%) | E29: 12% Anual sobre Cesantías | G29: 31 de Enero (a Cuenta) | I29: =(AVERAGE(J4:J22)*2)*0.12 -> 580538.17 | K29: Nómina de enero
B30: TOTAL LIQUIDEZ EXTRA PRESTACIONAL Y FONDOS ESTIMADA (AÑO) | I30: =SUM(I25:I29) -> 12416174 | K30: Capital adicional para metas y patrimonio

Sheet AHORROS
A1: 🐷 FONDOS DE AHORRO Y APORTES — COOPERATIVA COLANTA
A2: Control de ahorros retenidos por nómina, fondo navideño y aportes cooperativos Colanta
A4: TOTAL ACUMULADO FONDOS COLANTA | C4: AHORRO MES SELECCIONADO (PANEL) | E4: FONDO NAVIDEÑO ACUMULADO
A5: =C12 -> 3931299 | C5: =B12 -> 0 | E5: =C9 -> 2160000
A7: Línea de Ahorro / Fondo | B7: Mes Seleccionado ($) | C7: Acumulado Total ($) | D7: % Participación | E7: Propósito / Destino
A8: Ahorro Ordinario | B8: =SUMIFS($E$14:$E$87, $D$14:$D$87, A8, $F$14:$F$87, PANEL!$L$2, $G$14:$G$87, PANEL!$I$2) -> 0 | C8: =SUMIF($D$14:$D$87, A8, $E$14:$E$87) -> 594000 | D8: =IFERROR(C8/$C$12, 0) -> 0.1510951 | E8: A la vista / Fondo de emergencia personal
A9: Ahorro Navideño | B9: =SUMIFS($E$14:$E$87, $D$14:$D$87, A9, $F$14:$F$87, PANEL!$L$2, $G$14:$G$87, PANEL!$I$2) -> 0 | C9: =SUMIF($D$14:$D$87, A9, $E$14:$E$87) -> 2160000 | D9: =IFERROR(C9/$C$12, 0) -> 0.54943671 | E9: Contractual / Entrega en diciembre Colanta
A10: Aportes Cooperativos | B10: =SUMIFS($E$14:$E$87, $D$14:$D$87, A10, $F$14:$F$87, PANEL!$L$2, $G$14:$G$87, PANEL!$I$2) -> 0 | C10: =SUMIF($D$14:$D$87, A10, $E$14:$E$87) -> 995083 | D10: =IFERROR(C10/$C$12, 0) -> 0.25311812 | E10: Capitalización obligatoria Colanta AyC
A11: Aporte Afiliación / Otros | B11: =SUMIFS($E$14:$E$87, $F$14:$F$87, PANEL!$L$2, $G$14:$G$87, PANEL!$I$2) - SUM(B8:B10) -> 0 | C11: =SUM($E$14:$E$87) - SUM(C8:C10) -> 182216 | D11: =IFERROR(C11/$C$12, 0) -> 0.046350074 | E11: Fondo y beneficios de asociado
A12: TOTAL FONDOS COLANTA | B12: =SUM(B8:B11) -> 0 | C12: =SUM(C8:C11) -> 3931299 | D12: =SUM(D8:D11) -> 1 | E12: Patrimonio acumulado Marlon Muñoz
A14: ID Descuento | B14: Fecha Nómina | C14: Colilla Ref | D14: Línea de Ahorro | E14: Monto Ahorrado ($) | F14: Mes | G14: Año | H14: Quincena | I14: Notas / Auditoría
A15: A-0001 | B15: 15/08/2026 | C15: Fondo de Empleados Colanta | D15: Ahorro Ordinario | E15: 33000 | F15: agosto | G15: 2026 | H15: Ref Colilla: CP-0001 | Ahorro Ordinario
A16: A-0002 | B16: 15/08/2026 | C16: Fondo de Empleados Colanta | D16: Ahorro Navideño | E16: 120000 | F16: agosto | G16: 2026 | H16: Ref Colilla: CP-0001 | Ahorro Navideño
A17: A-0003 | B17: 15/08/2026 | C17: Fondo de Empleados Colanta | D17: Aportes Cooperativos | E17: 37567 | F17: agosto | G17: 2026 | H17: Ref Colilla: CP-0001 | Aportes Cooperativos
A18: A-0004 | B18: 15/08/2026 | C18: Fondo de Empleados Colanta | D18: Otros Ahorros | E18: 45554 | F18: agosto | G18: 2026 | H18: Ref Colilla: CP-0001 | Otros Ahorros
A19: A-0005 | B19: 15/03/2026 | C19: Fondo de Empleados Colanta | D19: Ahorro Ordinario | E19: 33000 | F19: marzo | G19: 2026 | H19: IMPORT_HISTORICO_MARLON_2026-08-20
A20: A-0006 | B20: 15/03/2026 | C20: Fondo de Empleados Colanta | D20: Ahorro Navideño | E20: 120000 | F20: marzo | G20: 2026 | H20: IMPORT_HISTORICO_MARLON_2026-08-20
A21: A-0007 | B21: 15/03/2026 | C21: Fondo de Empleados Colanta | D21: Aportes Cooperativos | E21: 83121 | F21: marzo | G21: 2026 | H21: IMPORT_HISTORICO_MARLON_2026-08-20
A22: A-0008 | B22: 31/03/2026 | C22: Fondo de Empleados Colanta | D22: Ahorro Ordinario | E22: 33000 | F22: marzo | G22: 2026 | H22: IMPORT_HISTORICO_MARLON_2026-08-20
A23: A-0009 | B23: 31/03/2026 | C23: Fondo de Empleados Colanta | D23: Ahorro Navideño | E23: 120000 | F23: marzo | G23: 2026 | H23: IMPORT_HISTORICO_MARLON_2026-08-20
A24: A-0010 | B24: 31/03/2026 | C24: Fondo de Empleados Colanta | D24: Aportes Cooperativos | E24: 83121 | F24: marzo | G24: 2026 | H24: IMPORT_HISTORICO_MARLON_2026-08-20
A25: A-0011 | B25: 15/04/2026 | C25: Fondo de Empleados Colanta | D25: Ahorro Ordinario | E25: 33000 | F25: abril | G25: 2026 | H25: IMPORT_HISTORICO_MARLON_2026-08-20
A26: A-0012 | B26: 15/04/2026 | C26: Fondo de Empleados Colanta | D26: Ahorro Navideño | E26: 120000 | F26: abril | G26: 2026 | H26: IMPORT_HISTORICO_MARLON_2026-08-20
... A63: A-0049 | B63: 31/08/2026 | C63: Fondo de Empleados Colanta | D63: Aportes Cooperativos | E63: 37567 | F63: agosto | G63: 2026 | H63: ref colilla: cp-0009 | aportes cooperativos
A64: A-0050 | B64: 15/09/2026 | C64: Fondo de Empleados Colanta | D64: Ahorro Ordinario | E64: 33000 | F64: septiembre | G64: 2026 | H64: Ref Colilla: CP-0010 | Ahorro Ordinario | ⏰ 11:03 PM | I64: 11:03 PM
A65: A-0051 | B65: 15/09/2026 | C65: Fondo de Empleados Colanta | D65: Ahorro Navideño | E65: 120000 | F65: septiembre | G65: 2026 | H65: Ref Colilla: CP-0010 | Ahorro Navideño | ⏰ 11:03 PM | I65: 11:03 PM
A66: A-0052 | B66: 15/09/2026 | C66: Fondo de Empleados Colanta | D66: Aportes Cooperativos | E66: 37567 | F66: septiembre | G66: 2026 | H66: Ref Colilla: CP-0010 | Aportes Cooperativos | ⏰ 11:03 PM | I66: 11:03 PM
A67: A-0053 | B67: 15/09/2026 | C67: Fondo de Empleados Colanta | D67: Aporte Afiliación Cooperativa | E67: 45554 | F67: septiembre | G67: 2026 | H67: Ref Colilla: CP-0010 | Aporte Afiliación Cooperativa | ⏰ 11:03 PM | I67: 11:03 PM
A68: A-0056 | B68: 46295 | C68: Fondo de Empleados Colanta | D68: Aportes Cooperativos | E68: 37567 | F68: septiembre | G68: 2026 | H68: ref colilla: cp-0018 | aportes cooperativos
A69: A-0057 | B69: 46295 | C69: Fondo de Empleados Colanta | D69: Otros Ahorros | E69: 45554 | F69: septiembre | G69: 2026 | H69: ref colilla: cp-0018 | otros ahorros
A70: A-0058 | B70: 46295 | C70: Fondo de Empleados Colanta | D70: Ahorro Ordinario | E70: 33000 | F70: septiembre | G70: 2026 | H70: Ref Colilla: CP-0018 | Ahorro Ordinario
A71: A-0059 | B71: 46295 | C71: Fondo de Empleados Colanta | D71: Ahorro Navideño | E71: 120000 | F71: septiembre | G71: 2026 | H71: Ref Colilla: CP-0018 | Ahorro Navideño
A72: A-0060 | B72: 46295 | C72: Fondo de Empleados Colanta | D72: Aporte Afiliación Cooperativa | E72: 45554 | F72: septiembre | G72: 2026 | H72: Ref Colilla: CP-0018 | Aporte Afiliación Cooperativa

Sheet CONTROL FIJOS
A1: ="📌 CONTROL DE COMPROMISOS FIJOS — " & UPPER(PANEL!L2) & " " & PANEL!I2 -> 📌 CONTROL DE COMPROMISOS FIJOS — OCTUBRE 2026
A2: Sincronizado automáticamente con el mes y año seleccionados en el Panel Principal
A4: TOTAL CUOTAS MES | D4: TOTAL ABONADO / PAGADO | G4: SALDO PENDIENTE | J4: COMPROMISOS Q1 (DÍA <=15)
A5: =SUM(E10:E26) -> 2611000 | D5: =SUM(F10:F26) -> 54000 | G5: =SUM(I10:I26) -> 2557000 | J5: =SUMIFS(I10:I26, D10:D26, "<=15") -> 1332000
A9: ID | B9: Concepto / Servicio | C9: Categoría | D9: Día Cobro | E9: Cuota Base ($) | F9: Abonado Mes ($) | G9: Estado | H9: Fecha Último Pago | I9: Saldo Pendiente ($) | J9: Prioridad | K9: Medio de Pago | L9: Notas / Referencia
A10: {=IFERROR(INDEX('HISTORICO FIJOS'!$A$3:$A$204, MATCH(1, 'HISTORICO FIJOS'!$P$3:$P$204, 0)), "")} -> F-0107 | B10: {=IFERROR(INDEX('HISTORICO FIJOS'!$B$3:$B$204, MATCH(1, 'HISTORICO FIJOS'!$P$3:$P$204, 0)), "")} -> EPM ENERGIA | C10: {=IFERROR(INDEX('HISTORICO FIJOS'!$C$3:$C$204, MATCH(1, 'HISTORICO FIJOS'!$P$3:$P$204, 0)), "")} -> Servicios | D10: {=IFERROR(INDEX('HISTORICO FIJOS'!$D$3:$D$204, MATCH(1, 'HISTORICO FIJOS'!$P$3:$P$204, 0)), "")} -> 15 | E10: {=IFERROR(INDEX('HISTORICO FIJOS'!$E$4:$E$250, MATCH(1, 'HISTORICO FIJOS'!$P$4:$P$250, 0)), "")} -> 177000 | F10: {=IFERROR(INDEX('HISTORICO FIJOS'!$F$4:$F$250, MATCH(1, 'HISTORICO FIJOS'!$P$4:$P$250, 0)), "")} -> 0 | G10: =IF(A10="","",IF(N(F10)>=E10,"🟢 Pagado",IF(N(F10)>0,"🟡 Abono Parcial","🔴 Pendiente"))) -> 🔴 Pendiente | H10: {=IFERROR(INDEX('HISTORICO FIJOS'!$G$4:$G$250, MATCH(1, 'HISTORICO FIJOS'!$P$4:$P$250, 0)), "")} | I10: =IF(A10="","",MAX(0, E10-N(F10))) -> 177000 | J10: {=IFERROR(INDEX('HISTORICO FIJOS'!$L$3:$L$204, MATCH(1, 'HISTORICO FIJOS'!$P$3:$P$204, 0)), "")} -> Media | K10: {=IFERROR(INDEX('HISTORICO FIJOS'!$M$3:$M$204, MATCH(1, 'HISTORICO FIJOS'!$P$3:$P$204, 0)), "")} -> Transferencia | L10: {=IFERROR(INDEX('HISTORICO FIJOS'!$O$3:$O$204, MATCH(1, 'HISTORICO FIJOS'!$P$3:$P$204, 0)), "")}
A11: {=IFERROR(INDEX('HISTORICO FIJOS'!$A$3:$A$204, MATCH(2, 'HISTORICO FIJOS'!$P$3:$P$204, 0)), "")} -> F-0108 | B11: {=IFERROR(INDEX('HISTORICO FIJOS'!$B$3:$B$204, MATCH(2, 'HISTORICO FIJOS'!$P$3:$P$204, 0)), "")} -> COMIDA | C11: {=IFERROR(INDEX('HISTORICO FIJOS'!$C$3:$C$204, MATCH(2, 'HISTORICO FIJOS'!$P$3:$P$204, 0)), "")} -> Alimentación | D11: {=IFERROR(INDEX('HISTORICO FIJOS'!$D$3:$D$204, MATCH(2, 'HISTORICO FIJOS'!$P$3:$P$204, 0)), "")} -> 15 | E11: {=IFERROR(INDEX('HISTORICO FIJOS'!$E$3:$E$204, MATCH(2, 'HISTORICO FIJOS'!$P$3:$P$204, 0)), "")} -> 850000 | F11: {=IFERROR(INDEX('HISTORICO FIJOS'!$F$3:$F$204, MATCH(2, 'HISTORICO FIJOS'!$P$3:$P$204, 0)), "")} -> 0 | G11: =IF(A11="","",IF(N(F11)>=E11,"🟢 Pagado",IF(N(F11)>0,"🟡 Abono Parcial","🔴 Pendiente"))) -> 🔴 Pendiente | H11: {=IFERROR(INDEX('HISTORICO FIJOS'!$G$3:$G$204, MATCH(2, 'HISTORICO FIJOS'!$P$3:$P$204, 0)), "")} | I11: =IF(A11="","",MAX(0, E11-N(F11))) -> 850000 | J11: {=IFERROR(INDEX('HISTORICO FIJOS'!$L$3:$L$204, MATCH(2, 'HISTORICO FIJOS'!$P$3:$P$204, 0)), "")} -> Media | K11: {=IFERROR(INDEX('HISTORICO FIJOS'!$M$3:$M$204, MATCH(2, 'HISTORICO FIJOS'!$P$3:$P$204, 0)), "")} -> Transferencia | L11: {=IFERROR(INDEX('HISTORICO FIJOS'!$O$3:$O$204, MATCH(2, 'HISTORICO FIJOS'!$P$3:$P$204, 0)), "")}
A12: {=IFERROR(INDEX('HISTORICO FIJOS'!$A$3:$A$204, MATCH(3, 'HISTORICO FIJOS'!$P$3:$P$204, 0)), "")} -> F-0109 | B12: {=IFERROR(INDEX('HISTORICO FIJOS'!$B$3:$B$204, MATCH(3, 'HISTORICO FIJOS'!$P$3:$P$204, 0)), "")} -> Internet Tigo | C12: {=IFERROR(INDEX('HISTORICO FIJOS'!$C$3:$C$204, MATCH(3, 'HISTORICO FIJOS'!$P$3:$P$204, 0)), "")} -> Servicios | D12: {=IFERROR(INDEX('HISTORICO FIJOS'!$D$3:$D$204, MATCH(3, 'HISTORICO FIJOS'!$P$3:$P$204, 0)), "")} -> 15 | E12: {=IFERROR(INDEX('HISTORICO FIJOS'!$E$3:$E$204, MATCH(3, 'HISTORICO FIJOS'!$P$3:$P$204, 0)), "")} -> 120000 | F12: {=IFERROR(INDEX('HISTORICO FIJOS'!$F$3:$F$204, MATCH(3, 'HISTORICO FIJOS'!$P$3:$P$204, 0)), "")} -> 0 | G12: =IF(A12="","",IF(N(F12)>=E12,"🟢 Pagado",IF(N(F12)>0,"🟡 Abono Parcial","🔴 Pendiente"))) -> 🔴 Pendiente | H12: {=IFERROR(INDEX('HISTORICO FIJOS'!$G$3:$G$204, MATCH(3, 'HISTORICO FIJOS'!$P$3:$P$204, 0)), "")} | I12: =IF(A12="","",MAX(0, E12-N(F12))) -> 120000 | J12: {=IFERROR(INDEX('HISTORICO FIJOS'!$L$3:$L$204, MATCH(3, 'HISTORICO FIJOS'!$P$3:$P$204, 0)), "")} -> Media | K12: {=IFERROR(INDEX('HISTORICO FIJOS'!$M$3:$M$204, MATCH(3, 'HISTORICO FIJOS'!$P$3:$P$204, 0)), "")} -> Transferencia | L12: {=IFERROR(INDEX('HISTORICO FIJOS'!$O$3:$O$204, MATCH(3, 'HISTORICO FIJOS'!$P$3:$P$204, 0)), "")}
A13: {=IFERROR(INDEX('HISTORICO FIJOS'!$A$3:$A$204, MATCH(4, 'HISTORICO FIJOS'!$P$3:$P$204, 0)), "")} -> F-0110 | B13: {=IFERROR(INDEX('HISTORICO FIJOS'!$B$3:$B$204, MATCH(4, 'HISTORICO FIJOS'!$P$3:$P$204, 0)), "")} -> Parqueadero Trabajo Semana | C13: {=IFERROR(INDEX('HISTORICO FIJOS'!$C$3:$C$204, MATCH(4, 'HISTORICO FIJOS'!$P$3:$P$204, 0)), "")} -> Transporte | D13: {=IFERROR(INDEX('HISTORICO FIJOS'!$D$3:$D$204, MATCH(4, 'HISTORICO FIJOS'!$P$3:$P$204, 0)), "")} -> 15 | E13: {=IFERROR(INDEX('HISTORICO FIJOS'!$E$3:$E$204, MATCH(4, 'HISTORICO FIJOS'!$P$3:$P$204, 0)), "")} -> 40000 | F13: {=IFERROR(INDEX('HISTORICO FIJOS'!$F$3:$F$204, MATCH(4, 'HISTORICO FIJOS'!$P$3:$P$204, 0)), "")} -> 0 | G13: =IF(A13="","",IF(N(F13)>=E13,"🟢 Pagado",IF(N(F13)>0,"🟡 Abono Parcial","🔴 Pendiente"))) -> 🔴 Pendiente | H13: {=IFERROR(INDEX('HISTORICO FIJOS'!$G$3:$G$204, MATCH(4, 'HISTORICO FIJOS'!$P$3:$P$204, 0)), "")} | I13: =IF(A13="","",MAX(0, E13-N(F13))) -> 40000 | J13: {=IFERROR(INDEX('HISTORICO FIJOS'!$L$3:$L$204, MATCH(4, 'HISTORICO FIJOS'!$P$3:$P$204, 0)), "")} -> Media | K13: {=IFERROR(INDEX('HISTORICO FIJOS'!$M$3:$M$204, MATCH(4, 'HISTORICO FIJOS'!$P$3:$P$204, 0)), "")} -> Transferencia | L13: {=IFERROR(INDEX('HISTORICO FIJOS'!$O$3:$O$204, MATCH(4, 'HISTORICO FIJOS'!$P$3:$P$204, 0)), "")}
A14: {=IFERROR(INDEX('HISTORICO FIJOS'!$A$3:$A$204, MATCH(5, 'HISTORICO FIJOS'!$P$3:$P$204, 0)), "")} -> F-0111 | B14: {=IFERROR(INDEX('HISTORICO FIJOS'!$B$3:$B$204, MATCH(5, 'HISTORICO FIJOS'!$P$3:$P$204, 0)), "")} -> Cuota Audifonos Samsung | C14: {=IFERROR(INDEX('HISTORICO FIJOS'!$C$3:$C$204, MATCH(5, 'HISTORICO FIJOS'!$P$3:$P$204, 0)), "")} -> Otros | D14: {=IFERROR(INDEX('HISTORICO FIJOS'!$D$3:$D$204, MATCH(5, 'HISTORICO FIJOS'!$P$3:$P$204, 0)), "")} -> 15 | E14: {=IFERROR(INDEX('HISTORICO FIJOS'!$E$3:$E$204, MATCH(5, 'HISTORICO FIJOS'!$P$3:$P$204, 0)), "")} -> 50000 | F14: {=IFERROR(INDEX('HISTORICO FIJOS'!$F$3:$F$204, MATCH(5, 'HISTORICO FIJOS'!$P$3:$P$204, 0)), "")} -> 0 | G14: =IF(A14="","",IF(N(F14)>=E14,"🟢 Pagado",IF(N(F14)>0,"🟡 Abono Parcial","🔴 Pendiente"))) -> 🔴 Pendiente | H14: {=IFERROR(INDEX('HISTORICO FIJOS'!$G$3:$G$204, MATCH(5, 'HISTORICO FIJOS'!$P$3:$P$204, 0)), "")} | I14: =IF(A14="","",MAX(0, E14-N(F14))) -> 50000 | J14: {=IFERROR(INDEX('HISTORICO FIJOS'!$L$3:$L$204, MATCH(5, 'HISTORICO FIJOS'!$P$3:$P$204, 0)), "")} -> Media | K14: {=IFERROR(INDEX('HISTORICO FIJOS'!$M$3:$M$204, MATCH(5, 'HISTORICO FIJOS'!$P$3:$P$204, 0)), "")} -> Transferencia | L14: {=IFERROR(INDEX('HISTORICO FIJOS'!$O$3:$O$204, MATCH(5, 'HISTORICO FIJOS'!$P$3:$P$204, 0)), "")}
A15: {=IFERROR(INDEX('HISTORICO FIJOS'!$A$3:$A$204, MATCH(6, 'HISTORICO FIJOS'!$P$3:$P$204, 0)), "")} -> F-0112 | B15: {=IFERROR(INDEX('HISTORICO FIJOS'!$B$3:$B$204, MATCH(6, 'HISTORICO FIJOS'!$P$3:$P$204, 0)), "")} -> PARQUEADERO MOTO | C15: {=IFERROR(INDEX('HISTORICO FIJOS'!$C$3:$C$204, MATCH(6, 'HISTORICO FIJOS'!$P$3:$P$204, 0)), "")} -> Moto | D15: {=IFERROR(INDEX('HISTORICO FIJOS'!$D$3:$D$204, MATCH(6, 'HISTORICO FIJOS'!$P$3:$P$204, 0)), "")} -> 15 | E15: {=IFERROR(INDEX('HISTORICO FIJOS'!$E$3:$E$204, MATCH(6, 'HISTORICO FIJOS'!$P$3:$P$204, 0)), "")} -> 60000 | F15: {=IFERROR(INDEX('HISTORICO FIJOS'!$F$3:$F$204, MATCH(6, 'HISTORICO FIJOS'!$P$3:$P$204, 0)), "")} -> 0 | G15: =IF(A15="","",IF(N(F15)>=E15,"🟢 Pagado",IF(N(F15)>0,"🟡 Abono Parcial","🔴 Pendiente"))) -> 🔴 Pendiente | H15: {=IFERROR(INDEX('HISTORICO FIJOS'!$G$3:$G$204, MATCH(6, 'HISTORICO FIJOS'!$P$3:$P$204, 0)), "")} | I15: =IF(A15="","",MAX(0, E15-N(F15))) -> 60000 | J15: {=IFERROR(INDEX('HISTORICO FIJOS'!$L$3:$L$204, MATCH(6, 'HISTORICO FIJOS'!$P$3:$P$204, 0)), "")} -> Media | K15: {=IFERROR(INDEX('HISTORICO FIJOS'!$M$3:$M$204, MATCH(6, 'HISTORICO FIJOS'!$P$3:$P$204, 0)), "")} -> Efectivo | L15: {=IFERROR(INDEX('HISTORICO FIJOS'!$O$3:$O$204, MATCH(6, 'HISTORICO FIJOS'!$P$3:$P$204, 0)), "")}
A16: {=IFERROR(INDEX('HISTORICO FIJOS'!$A$3:$A$204, MATCH(7, 'HISTORICO FIJOS'!$P$3:$P$204, 0)), "")} -> F-0113 | B16: {=IFERROR(INDEX('HISTORICO FIJOS'!$B$3:$B$204, MATCH(7, 'HISTORICO FIJOS'!$P$3:$P$204, 0)), "")} -> Gasolina Moto | C16: {=IFERROR(INDEX('HISTORICO FIJOS'!$C$3:$C$204, MATCH(7, 'HISTORICO FIJOS'!$P$3:$P$204, 0)), "")} -> Moto | D16: {=IFERROR(INDEX('HISTORICO FIJOS'!$D$3:$D$204, MATCH(7, 'HISTORICO FIJOS'!$P$3:$P$204, 0)), "")} -> 15 | E16: {=IFERROR(INDEX('HISTORICO FIJOS'!$E$3:$E$204, MATCH(7, 'HISTORICO FIJOS'!$P$3:$P$204, 0)), "")} -> 35000 | F16: {=IFERROR(INDEX('HISTORICO FIJOS'!$F$3:$F$204, MATCH(7, 'HISTORICO FIJOS'!$P$3:$P$204, 0)), "")} -> 0 | G16: =IF(A16="","",IF(N(F16)>=E16,"🟢 Pagado",IF(N(F16)>0,"🟡 Abono Parcial","🔴 Pendiente"))) -> 🔴 Pendiente | H16: {=IFERROR(INDEX('HISTORICO FIJOS'!$G$3:$G$204, MATCH(7, 'HISTORICO FIJOS'!$P$3:$P$204, 0)), "")} | I16: =IF(A16="","",MAX(0, E16-N(F16))) -> 35000 | J16: {=IFERROR(INDEX('HISTORICO FIJOS'!$L$3:$L$204, MATCH(7, 'HISTORICO FIJOS'!$P$3:$P$204, 0)), "")} -> Media | K16: {=IFERROR(INDEX('HISTORICO FIJOS'!$M$3:$M$204, MATCH(7, 'HISTORICO FIJOS'!$P$3:$P$204, 0)), "")} -> Transferencia | L16: {=IFERROR(INDEX('HISTORICO FIJOS'!$O$3:$O$204, MATCH(7, 'HISTORICO FIJOS'!$P$3:$P$204, 0)), "")}
A17: {=IFERROR(INDEX('HISTORICO FIJOS'!$A$3:$A$204, MATCH(8, 'HISTORICO FIJOS'!$P$3:$P$204, 0)), "")} -> F-0114 | B17: {=IFERROR(INDEX('HISTORICO FIJOS'!$B$3:$B$204, MATCH(8, 'HISTORICO FIJOS'!$P$3:$P$204, 0)), "")} -> Spotify | C17: {=IFERROR(INDEX('HISTORICO FIJOS'!$C$3:$C$204, MATCH(8, 'HISTORICO FIJOS'!$P$3:$P$204, 0)), "")} -> Entretenimiento | D17: {=IFERROR(INDEX('HISTORICO FIJOS'!$D$3:$D$204, MATCH(8, 'HISTORICO FIJOS'!$P$3:$P$204, 0)), "")} -> 15 | E17: {=IFERROR(INDEX('HISTORICO FIJOS'!$E$3:$E$204, MATCH(8, 'HISTORICO FIJOS'!$P$3:$P$204, 0)), "")} -> 10100 | F17: {=IFERROR(INDEX('HISTORICO FIJOS'!$F$3:$F$204, MATCH(8, 'HISTORICO FIJOS'!$P$3:$P$204, 0)), "")} -> 10100 | G17: =IF(A17="","",IF(N(F17)>=E17,"🟢 Pagado",IF(N(F17)>0,"🟡 Abono Parcial","🔴 Pendiente"))) -> 🟢 Pagado | H17: {=IFERROR(INDEX('HISTORICO FIJOS'!$G$3:$G$204, MATCH(8, 'HISTORICO FIJOS'!$P$3:$P$204, 0)), "")} -> 46310 | I17: =IF(A17="","",MAX(0, E17-N(F17))) -> 0 | J17: {=IFERROR(INDEX('HISTORICO FIJOS'!$L$3:$L$204, MATCH(8, 'HISTORICO FIJOS'!$P$3:$P$204, 0)), "")} -> Media | K17: {=IFERROR(INDEX('HISTORICO FIJOS'!$M$3:$M$204, MATCH(8, 'HISTORICO FIJOS'!$P$3:$P$204, 0)), "")} -> Tarjeta Nequi | L17: {=IFERROR(INDEX('HISTORICO FIJOS'!$O$3:$O$204, MATCH(8, 'HISTORICO FIJOS'!$P$3:$P$204, 0)), "")} -> Renovación automática Google Play GPA.3333-4099-9556-15284..13
A18: {=IFERROR(INDEX('HISTORICO FIJOS'!$A$3:$A$204, MATCH(9, 'HISTORICO FIJOS'!$P$3:$P$204, 0)), "")} -> F-0115 | B18: {=IFERROR(INDEX('HISTORICO FIJOS'!$B$3:$B$204, MATCH(9, 'HISTORICO FIJOS'!$P$3:$P$204, 0)), "")} -> CUOTA DATOS CELULAR | C18: {=IFERROR(INDEX('HISTORICO FIJOS'!$C$3:$C$204, MATCH(9, 'HISTORICO FIJOS'!$P$3:$P$204, 0)), "")} -> Servicios | D18: {=IFERROR(INDEX('HISTORICO FIJOS'!$D$3:$D$204, MATCH(9, 'HISTORICO FIJOS'!$P$3:$P$204, 0)), "")} -> 15 | E18: {=IFERROR(INDEX('HISTORICO FIJOS'!$E$3:$E$204, MATCH(9, 'HISTORICO FIJOS'!$P$3:$P$204, 0)), "")} -> 43900 | F18: {=IFERROR(INDEX('HISTORICO FIJOS'!$F$3:$F$204, MATCH(9, 'HISTORICO FIJOS'!$P$3:$P$204, 0)), "")} -> 43900 | G18: =IF(A18="","",IF(N(F18)>=E18,"🟢 Pagado",IF(N(F18)>0,"🟡 Abono Parcial","🔴 Pendiente"))) -> 🟢 Pagado | H18: {=IFERROR(INDEX('HISTORICO FIJOS'!$G$3:$G$204, MATCH(9, 'HISTORICO FIJOS'!$P$3:$P$204, 0)), "")} -> 46297 | I18: =IF(A18="","",MAX(0, E18-N(F18))) -> 0 | J18: {=IFERROR(INDEX('HISTORICO FIJOS'!$L$3:$L$204, MATCH(9, 'HISTORICO FIJOS'!$P$3:$P$204, 0)), "")} -> Media | K18: {=IFERROR(INDEX('HISTORICO FIJOS'!$M$3:$M$204, MATCH(9, 'HISTORICO FIJOS'!$P$3:$P$204, 0)), "")} -> Efectivo | L18: {=IFERROR(INDEX('HISTORICO FIJOS'!$O$3:$O$204, MATCH(9, 'HISTORICO FIJOS'!$P$3:$P$204, 0)), "")}
A19: {=IFERROR(INDEX('HISTORICO FIJOS'!$A$3:$A$204, MATCH(10, 'HISTORICO FIJOS'!$P$3:$P$204, 0)), "")} -> F-0116 | B19: {=IFERROR(INDEX('HISTORICO FIJOS'!$B$3:$B$204, MATCH(10, 'HISTORICO FIJOS'!$P$3:$P$204, 0)), "")} -> ARRIENDO CASA | C19: {=IFERROR(INDEX('HISTORICO FIJOS'!$C$3:$C$204, MATCH(10, 'HISTORICO FIJOS'!$P$3:$P$204, 0)), "")} -> Vivienda | D19: {=IFERROR(INDEX('HISTORICO FIJOS'!$D$3:$D$204, MATCH(10, 'HISTORICO FIJOS'!$P$3:$P$204, 0)), "")} -> 30 | E19: {=IFERROR(INDEX('HISTORICO FIJOS'!$E$3:$E$204, MATCH(10, 'HISTORICO FIJOS'!$P$3:$P$204, 0)), "")} -> 900000 | F19: {=IFERROR(INDEX('HISTORICO FIJOS'!$F$3:$F$204, MATCH(10, 'HISTORICO FIJOS'!$P$3:$P$204, 0)), "")} -> 0 | G19: =IF(A19="","",IF(N(F19)>=E19,"🟢 Pagado",IF(N(F19)>0,"🟡 Abono Parcial","🔴 Pendiente"))) -> 🔴 Pendiente | H19: {=IFERROR(INDEX('HISTORICO FIJOS'!$G$3:$G$204, MATCH(10, 'HISTORICO FIJOS'!$P$3:$P$204, 0)), "")} | I19: =IF(A19="","",MAX(0, E19-N(F19))) -> 900000 | J19: {=IFERROR(INDEX('HISTORICO FIJOS'!$L$3:$L$204, MATCH(10, 'HISTORICO FIJOS'!$P$3:$P$204, 0)), "")} -> Media | K19: {=IFERROR(INDEX('HISTORICO FIJOS'!$M$3:$M$204, MATCH(10, 'HISTORICO FIJOS'!$P$3:$P$204, 0)), "")} -> Efectivo | L19: {=IFERROR(INDEX('HISTORICO FIJOS'!$O$3:$O$204, MATCH(10, 'HISTORICO FIJOS'!$P$3:$P$204, 0)), "")}
A20: {=IFERROR(INDEX('HISTORICO FIJOS'!$A$3:$A$204, MATCH(11, 'HISTORICO FIJOS'!$P$3:$P$204, 0)), "")} -> F-0117 | B20: {=IFERROR(INDEX('HISTORICO FIJOS'!$B$3:$B$204, MATCH(11, 'HISTORICO FIJOS'!$P$3:$P$204, 0)), "")} -> Google One | C20: {=IFERROR(INDEX('HISTORICO FIJOS'!$C$3:$C$204, MATCH(11, 'HISTORICO FIJOS'!$P$3:$P$204, 0)), "")} -> Servicios | D20: {=IFERROR(INDEX('HISTORICO FIJOS'!$D$3:$D$204, MATCH(11, 'HISTORICO FIJOS'!$P$3:$P$204, 0)), "")} -> 30 | E20: {=IFERROR(INDEX('HISTORICO FIJOS'!$E$3:$E$204, MATCH(11, 'HISTORICO FIJOS'!$P$3:$P$204, 0)), "")} -> 20000 | F20: {=IFERROR(INDEX('HISTORICO FIJOS'!$F$3:$F$204, MATCH(11, 'HISTORICO FIJOS'!$P$3:$P$204, 0)), "")} -> 0 | G20: =IF(A20="","",IF(N(F20)>=E20,"🟢 Pagado",IF(N(F20)>0,"🟡 Abono Parcial","🔴 Pendiente"))) -> 🔴 Pendiente | H20: {=IFERROR(INDEX('HISTORICO FIJOS'!$G$3:$G$204, MATCH(11, 'HISTORICO FIJOS'!$P$3:$P$204, 0)), "")} | I20: =IF(A20="","",MAX(0, E20-N(F20))) -> 20000 | J20: {=IFERROR(INDEX('HISTORICO FIJOS'!$L$3:$L$204, MATCH(11, 'HISTORICO FIJOS'!$P$3:$P$204, 0)), "")} -> Media | K20: {=IFERROR(INDEX('HISTORICO FIJOS'!$M$3:$M$204, MATCH(11, 'HISTORICO FIJOS'!$P$3:$P$204, 0)), "")} -> Efectivo | L20: {=IFERROR(INDEX('HISTORICO FIJOS'!$O$3:$O$204, MATCH(11, 'HISTORICO FIJOS'!$P$3:$P$204, 0)), "")}
A21: {=IFERROR(INDEX('HISTORICO FIJOS'!$A$3:$A$204, MATCH(12, 'HISTORICO FIJOS'!$P$3:$P$204, 0)), "")} -> F-0118 | B21: {=IFERROR(INDEX('HISTORICO FIJOS'!$B$3:$B$204, MATCH(12, 'HISTORICO FIJOS'!$P$3:$P$204, 0)), "")} -> Gasolina Moto | C21: {=IFERROR(INDEX('HISTORICO FIJOS'!$C$3:$C$204, MATCH(12, 'HISTORICO FIJOS'!$P$3:$P$204, 0)), "")} -> Moto | D21: {=IFERROR(INDEX('HISTORICO FIJOS'!$D$3:$D$204, MATCH(12, 'HISTORICO FIJOS'!$P$3:$P$204, 0)), "")} -> 30 | E21: {=IFERROR(INDEX('HISTORICO FIJOS'!$E$3:$E$204, MATCH(12, 'HISTORICO FIJOS'!$P$3:$P$204, 0)), "")} -> 25000 | F21: {=IFERROR(INDEX('HISTORICO FIJOS'!$F$3:$F$204, MATCH(12, 'HISTORICO FIJOS'!$P$3:$P$204, 0)), "")} -> 0 | G21: =IF(A21="","",IF(N(F21)>=E21,"🟢 Pagado",IF(N(F21)>0,"🟡 Abono Parcial","🔴 Pendiente"))) -> 🔴 Pendiente | H21: {=IFERROR(INDEX('HISTORICO FIJOS'!$G$3:$G$204, MATCH(12, 'HISTORICO FIJOS'!$P$3:$P$204, 0)), "")} | I21: =IF(A21="","",MAX(0, E21-N(F21))) -> 25000 | J21: {=IFERROR(INDEX('HISTORICO FIJOS'!$L$3:$L$204, MATCH(12, 'HISTORICO FIJOS'!$P$3:$P$204, 0)), "")} -> Media | K21: {=IFERROR(INDEX('HISTORICO FIJOS'!$M$3:$M$204, MATCH(12, 'HISTORICO FIJOS'!$P$3:$P$204, 0)), "")} -> Efectivo | L21: {=IFERROR(INDEX('HISTORICO FIJOS'!$O$3:$O$204, MATCH(12, 'HISTORICO FIJOS'!$P$3:$P$204, 0)), "")}
A22: {=IFERROR(INDEX('HISTORICO FIJOS'!$A$3:$A$204, MATCH(13, 'HISTORICO FIJOS'!$P$3:$P$204, 0)), "")} -> F-0119 | B22: {=IFERROR(INDEX('HISTORICO FIJOS'!$B$3:$B$204, MATCH(13, 'HISTORICO FIJOS'!$P$3:$P$204, 0)), "")} -> Parqueadero Trabajo Semana | C22: {=IFERROR(INDEX('HISTORICO FIJOS'!$C$3:$C$204, MATCH(13, 'HISTORICO FIJOS'!$P$3:$P$204, 0)), "")} -> Transporte | D22: {=IFERROR(INDEX('HISTORICO FIJOS'!$D$3:$D$204, MATCH(13, 'HISTORICO FIJOS'!$P$3:$P$204, 0)), "")} -> 30 | E22: {=IFERROR(INDEX('HISTORICO FIJOS'!$E$3:$E$204, MATCH(13, 'HISTORICO FIJOS'!$P$3:$P$204, 0)), "")} -> 40000 | F22: {=IFERROR(INDEX('HISTORICO FIJOS'!$F$3:$F$204, MATCH(13, 'HISTORICO FIJOS'!$P$3:$P$204, 0)), "")} -> 0 | G22: =IF(A22="","",IF(N(F22)>=E22,"🟢 Pagado",IF(N(F22)>0,"🟡 Abono Parcial","🔴 Pendiente"))) -> 🔴 Pendiente | H22: {=IFERROR(INDEX('HISTORICO FIJOS'!$G$3:$G$204, MATCH(13, 'HISTORICO FIJOS'!$P$3:$P$204, 0)), "")} | I22: =IF(A22="","",MAX(0, E22-N(F22))) -> 40000 | J22: {=IFERROR(INDEX('HISTORICO FIJOS'!$L$3:$L$204, MATCH(13, 'HISTORICO FIJOS'!$P$3:$P$204, 0)), "")} -> Media | K22: {=IFERROR(INDEX('HISTORICO FIJOS'!$M$3:$M$204, MATCH(13, 'HISTORICO FIJOS'!$P$3:$P$204, 0)), "")} -> Efectivo | L22: {=IFERROR(INDEX('HISTORICO FIJOS'!$O$3:$O$204, MATCH(13, 'HISTORICO FIJOS'!$P$3:$P$204, 0)), "")}
A23: {=IFERROR(INDEX('HISTORICO FIJOS'!$A$3:$A$204, MATCH(14, 'HISTORICO FIJOS'!$P$3:$P$204, 0)), "")} -> F-0120 | B23: {=IFERROR(INDEX('HISTORICO FIJOS'!$B$3:$B$204, MATCH(14, 'HISTORICO FIJOS'!$P$3:$P$204, 0)), "")} -> COMIDA | C23: {=IFERROR(INDEX('HISTORICO FIJOS'!$C$3:$C$204, MATCH(14, 'HISTORICO FIJOS'!$P$3:$P$204, 0)), "")} -> Alimentación | D23: {=IFERROR(INDEX('HISTORICO FIJOS'!$D$3:$D$204, MATCH(14, 'HISTORICO FIJOS'!$P$3:$P$204, 0)), "")} -> 30 | E23: {=IFERROR(INDEX('HISTORICO FIJOS'!$E$3:$E$204, MATCH(14, 'HISTORICO FIJOS'!$P$3:$P$204, 0)), "")} -> 200000 | F23: {=IFERROR(INDEX('HISTORICO FIJOS'!$F$3:$F$204, MATCH(14, 'HISTORICO FIJOS'!$P$3:$P$204, 0)), "")} -> 0 | G23: =IF(A23="","",IF(N(F23)>=E23,"🟢 Pagado",IF(N(F23)>0,"🟡 Abono Parcial","🔴 Pendiente"))) -> 🔴 Pendiente | H23: {=IFERROR(INDEX('HISTORICO FIJOS'!$G$3:$G$204, MATCH(14, 'HISTORICO FIJOS'!$P$3:$P$204, 0)), "")} | I23: =IF(A23="","",MAX(0, E23-N(F23))) -> 200000 | J23: {=IFERROR(INDEX('HISTORICO FIJOS'!$L$3:$L$204, MATCH(14, 'HISTORICO FIJOS'!$P$3:$P$204, 0)), "")} -> Media | K23: {=IFERROR(INDEX('HISTORICO FIJOS'!$M$3:$M$204, MATCH(14, 'HISTORICO FIJOS'!$P$3:$P$204, 0)), "")} -> Efectivo | L23: {=IFERROR(INDEX('HISTORICO FIJOS'!$O$3:$O$204, MATCH(14, 'HISTORICO FIJOS'!$P$3:$P$204, 0)), "")}
A24: {=IFERROR(INDEX('HISTORICO FIJOS'!$A$3:$A$204, MATCH(15, 'HISTORICO FIJOS'!$P$3:$P$204, 0)), "")} -> F-0121 | B24: {=IFERROR(INDEX('HISTORICO FIJOS'!$B$3:$B$204, MATCH(15, 'HISTORICO FIJOS'!$P$3:$P$204, 0)), "")} -> PARQUEADERO MOTO | C24: {=IFERROR(INDEX('HISTORICO FIJOS'!$C$3:$C$204, MATCH(15, 'HISTORICO FIJOS'!$P$3:$P$204, 0)), "")} -> Moto | D24: {=IFERROR(INDEX('HISTORICO FIJOS'!$D$3:$D$204, MATCH(15, 'HISTORICO FIJOS'!$P$3:$P$204, 0)), "")} -> 30 | E24: {=IFERROR(INDEX('HISTORICO FIJOS'!$E$3:$E$204, MATCH(15, 'HISTORICO FIJOS'!$P$3:$P$204, 0)), "")} -> 40000 | F24: {=IFERROR(INDEX('HISTORICO FIJOS'!$F$3:$F$204, MATCH(15, 'HISTORICO FIJOS'!$P$3:$P$204, 0)), "")} -> 0 | G24: =IF(A24="","",IF(N(F24)>=E24,"🟢 Pagado",IF(N(F24)>0,"🟡 Abono Parcial","🔴 Pendiente"))) -> 🔴 Pendiente | H24: {=IFERROR(INDEX('HISTORICO FIJOS'!$G$3:$G$204, MATCH(15, 'HISTORICO FIJOS'!$P$3:$P$204, 0)), "")} | I24: =IF(A24="","",MAX(0, E24-N(F24))) -> 40000 | J24: {=IFERROR(INDEX('HISTORICO FIJOS'!$L$3:$L$204, MATCH(15, 'HISTORICO FIJOS'!$P$3:$P$204, 0)), "")} -> Media | K24: {=IFERROR(INDEX('HISTORICO FIJOS'!$M$3:$M$204, MATCH(15, 'HISTORICO FIJOS'!$P$3:$P$204, 0)), "")} -> Efectivo | L24: {=IFERROR(INDEX('HISTORICO FIJOS'!$O$3:$O$204, MATCH(15, 'HISTORICO FIJOS'!$P$3:$P$204, 0)), "")}
A25: {=IFERROR(INDEX('HISTORICO FIJOS'!$A$3:$A$204, MATCH(16, 'HISTORICO FIJOS'!$P$3:$P$204, 0)), "")} | B25: {=IFERROR(INDEX('HISTORICO FIJOS'!$B$3:$B$204, MATCH(16, 'HISTORICO FIJOS'!$P$3:$P$204, 0)), "")} | C25: {=IFERROR(INDEX('HISTORICO FIJOS'!$C$3:$C$204, MATCH(16, 'HISTORICO FIJOS'!$P$3:$P$204, 0)), "")} | D25: {=IFERROR(INDEX('HISTORICO FIJOS'!$D$3:$D$204, MATCH(16, 'HISTORICO FIJOS'!$P$3:$P$204, 0)), "")} | E25: {=IFERROR(INDEX('HISTORICO FIJOS'!$E$3:$E$204, MATCH(16, 'HISTORICO FIJOS'!$P$3:$P$204, 0)), "")} | F25: {=IFERROR(INDEX('HISTORICO FIJOS'!$F$3:$F$204, MATCH(16, 'HISTORICO FIJOS'!$P$3:$P$204, 0)), "")} | G25: =IF(A25="","",IF(N(F25)>=E25,"🟢 Pagado",IF(N(F25)>0,"🟡 Abono Parcial","🔴 Pendiente"))) | H25: {=IFERROR(INDEX('HISTORICO FIJOS'!$G$3:$G$204, MATCH(16, 'HISTORICO FIJOS'!$P$3:$P$204, 0)), "")} | I25: =IF(A25="","",MAX(0, E25-N(F25))) | J25: {=IFERROR(INDEX('HISTORICO FIJOS'!$L$3:$L$204, MATCH(16, 'HISTORICO FIJOS'!$P$3:$P$204, 0)), "")} | K25: {=IFERROR(INDEX('HISTORICO FIJOS'!$M$3:$M$204, MATCH(16, 'HISTORICO FIJOS'!$P$3:$P$204, 0)), "")} | L25: {=IFERROR(INDEX('HISTORICO FIJOS'!$O$3:$O$204, MATCH(16, 'HISTORICO FIJOS'!$P$3:$P$204, 0)), "")}
A26: {=IFERROR(INDEX('HISTORICO FIJOS'!$A$3:$A$204, MATCH(17, 'HISTORICO FIJOS'!$P$3:$P$204, 0)), "")} | B26: {=IFERROR(INDEX('HISTORICO FIJOS'!$B$3:$B$204, MATCH(17, 'HISTORICO FIJOS'!$P$3:$P$204, 0)), "")} | C26: {=IFERROR(INDEX('HISTORICO FIJOS'!$C$3:$C$204, MATCH(17, 'HISTORICO FIJOS'!$P$3:$P$204, 0)), "")} | D26: {=IFERROR(INDEX('HISTORICO FIJOS'!$D$3:$D$204, MATCH(17, 'HISTORICO FIJOS'!$P$3:$P$204, 0)), "")} | E26: {=IFERROR(INDEX('HISTORICO FIJOS'!$E$3:$E$204, MATCH(17, 'HISTORICO FIJOS'!$P$3:$P$204, 0)), "")} | F26: {=IFERROR(INDEX('HISTORICO FIJOS'!$F$3:$F$204, MATCH(17, 'HISTORICO FIJOS'!$P$3:$P$204, 0)), "")} | G26: =IF(A26="","",IF(N(F26)>=E26,"🟢 Pagado",IF(N(F26)>0,"🟡 Abono Parcial","🔴 Pendiente"))) | H26: {=IFERROR(INDEX('HISTORICO FIJOS'!$G$3:$G$204, MATCH(17, 'HISTORICO FIJOS'!$P$3:$P$204, 0)), "")} | I26: =IF(A26="","",MAX(0, E26-N(F26))) | J26: {=IFERROR(INDEX('HISTORICO FIJOS'!$L$3:$L$204, MATCH(17, 'HISTORICO FIJOS'!$P$3:$P$204, 0)), "")} | K26: {=IFERROR(INDEX('HISTORICO FIJOS'!$M$3:$M$204, MATCH(17, 'HISTORICO FIJOS'!$P$3:$P$204, 0)), "")} | L26: {=IFERROR(INDEX('HISTORICO FIJOS'!$O$3:$O$204, MATCH(17, 'HISTORICO FIJOS'!$P$3:$P$204, 0)), "")}

Sheet PRESUPUESTO Y ALERTAS
A1: ="🎯 CONTROL PRESUPUESTAL Y LÍMITES — " & UPPER(PANEL!L2) & " " & PANEL!I2 -> 🎯 CONTROL PRESUPUESTAL Y LÍMITES — OCTUBRE 2026
A2: Monitoreo automático de topes mensuales de gasto, porcentaje consumido y semáforos de alerta
A4: Categoría Presupuestal | B4: Límite Asignado ($) | C4: Gasto Ejecutado ($) | D4: Saldo Disponible ($) | E4: % Consumo | F4: Barra de Progreso | G4: Estado / Alerta | H4: Acción Recomendada
A5: Alimentación | B5: 800000 | C5: =PANEL!C20 -> 0 | D5: =IF(B5=0, 0, B5-C5) -> 800000 | E5: =IF(B5=0, 0, C5/B5) -> 0 | F5: =IF(B5=0, "░░░░░░░░░░ (Libre)", REPT("█", MIN(10, ROUND(E5*10, 0))) & REPT("░", MAX(0, 10-MIN(10, ROUND(E5*10, 0))))) -> ░░░░░░░░░░ | G5: =IF(B5=0, "⚪ Sin límite", IF(E5<=0.8, "🟢 En regla", IF(E5<=1, "🟡 Al Límite", "🔴 Excedido"))) -> 🟢 En regla | H5: =IF(B5=0, "Monitorear sin restricción", IF(E5>1, "Frenar gastos de inmediato", IF(E5>0.8, "Gastar solo en lo indispensable", "Consumo en rango normal"))) -> Consumo en rango normal
A6: ARRIENDO CASA | B6: 900000 | C6: =PANEL!C21 -> 0 | D6: =IF(B6=0, 0, B6-C6) -> 900000 | E6: =IF(B6=0, 0, C6/B6) -> 0 | F6: =IF(B6=0, "░░░░░░░░░░ (Libre)", REPT("█", MIN(10, ROUND(E6*10, 0))) & REPT("░", MAX(0, 10-MIN(10, ROUND(E6*10, 0))))) -> ░░░░░░░░░░ | G6: =IF(B6=0, "⚪ Sin límite", IF(E6<=0.8, "🟢 En regla", IF(E6<=1, "🟡 Al Límite", "🔴 Excedido"))) -> 🟢 En regla | H6: =IF(B6=0, "Monitorear sin restricción", IF(E6>1, "Frenar gastos de inmediato", IF(E6>0.8, "Gastar solo en lo indispensable", "Consumo en rango normal"))) -> Consumo en rango normal
A7: Servicios Públicos | B7: 300000 | C7: =PANEL!C22 -> 0 | D7: =IF(B7=0, 0, B7-C7) -> 300000 | E7: =IF(B7=0, 0, C7/B7) -> 0 | F7: =IF(B7=0, "░░░░░░░░░░ (Libre)", REPT("█", MIN(10, ROUND(E7*10, 0))) & REPT("░", MAX(0, 10-MIN(10, ROUND(E7*10, 0))))) -> ░░░░░░░░░░ | G7: =IF(B7=0, "⚪ Sin límite", IF(E7<=0.8, "🟢 En regla", IF(E7<=1, "🟡 Al Límite", "🔴 Excedido"))) -> 🟢 En regla | H7: =IF(B7=0, "Monitorear sin restricción", IF(E7>1, "Frenar gastos de inmediato", IF(E7>0.8, "Gastar solo en lo indispensable", "Consumo en rango normal"))) -> Consumo en rango normal
A8: Transporte y Moto | B8: 240000 | C8: =PANEL!C23 -> 116000 | D8: =IF(B8=0, 0, B8-C8) -> 124000 | E8: =IF(B8=0, 0, C8/B8) -> 0.48333333 | F8: =IF(B8=0, "░░░░░░░░░░ (Libre)", REPT("█", MIN(10, ROUND(E8*10, 0))) & REPT("░", MAX(0, 10-MIN(10, ROUND(E8*10, 0))))) -> █████░░░░░ | G8: =IF(B8=0, "⚪ Sin límite", IF(E8<=0.8, "🟢 En regla", IF(E8<=1, "🟡 Al Límite", "🔴 Excedido"))) -> 🟢 En regla | H8: =IF(B8=0, "Monitorear sin restricción", IF(E8>1, "Frenar gastos de inmediato", IF(E8>0.8, "Gastar solo en lo indispensable", "Consumo en rango normal"))) -> Consumo en rango normal
A9: Gastos Hormiga / Dulces | B9: 50000 | C9: =PANEL!C24 -> 67000 | D9: =IF(B9=0, 0, B9-C9) -> -17000 | E9: =IF(B9=0, 0, C9/B9) -> 1.34 | F9: =IF(B9=0, "░░░░░░░░░░ (Libre)", REPT("█", MIN(10, ROUND(E9*10, 0))) & REPT("░", MAX(0, 10-MIN(10, ROUND(E9*10, 0))))) -> ██████████ | G9: =IF(B9=0, "⚪ Sin límite", IF(E9<=0.8, "🟢 En regla", IF(E9<=1, "🟡 Al Límite", "🔴 Excedido"))) -> 🔴 Excedido | H9: =IF(B9=0, "Monitorear sin restricción", IF(E9>1, "Frenar gastos de inmediato", IF(E9>0.8, "Gastar solo en lo indispensable", "Consumo en rango normal"))) -> Frenar gastos de inmediato
A10: Ocio y Entretenimiento | B10: 100000 | C10: =PANEL!C25 -> 14023 | D10: =IF(B10=0, 0, B10-C10) -> 85977 | E10: =IF(B10=0, 0, C10/B10) -> 0.14023 | F10: =IF(B10=0, "░░░░░░░░░░ (Libre)", REPT("█", MIN(10, ROUND(E10*10, 0))) & REPT("░", MAX(0, 10-MIN(10, ROUND(E10*10, 0))))) -> █░░░░░░░░░ | G10: =IF(B10=0, "⚪ Sin límite", IF(E10<=0.8, "🟢 En regla", IF(E10<=1, "🟡 Al Límite", "🔴 Excedido"))) -> 🟢 En regla | H10: =IF(B10=0, "Monitorear sin restricción", IF(E10>1, "Frenar gastos de inmediato", IF(E10>0.8, "Gastar solo en lo indispensable", "Consumo en rango normal"))) -> Consumo en rango normal
A11: Suscripciones | B11: 0 | C11: =PANEL!C26 -> 10100 | D11: =IF(B11=0, 0, B11-C11) -> 0 | E11: =IF(B11=0, 0, C11/B11) -> 0 | F11: =IF(B11=0, "░░░░░░░░░░ (Libre)", REPT("█", MIN(10, ROUND(E11*10, 0))) & REPT("░", MAX(0, 10-MIN(10, ROUND(E11*10, 0))))) -> ░░░░░░░░░░ (Libre) | G11: =IF(B11=0, "⚪ Sin límite", IF(E11<=0.8, "🟢 En regla", IF(E11<=1, "🟡 Al Límite", "🔴 Excedido"))) -> ⚪ Sin límite | H11: =IF(B11=0, "Monitorear sin restricción", IF(E11>1, "Frenar gastos de inmediato", IF(E11>0.8, "Gastar solo en lo indispensable", "Consumo en rango normal"))) -> Monitorear sin restricción
A12: Compras | B12: 0 | C12: =PANEL!C27 -> 0 | D12: =IF(B12=0, 0, B12-C12) -> 0 | E12: =IF(B12=0, 0, C12/B12) -> 0 | F12: =IF(B12=0, "░░░░░░░░░░ (Libre)", REPT("█", MIN(10, ROUND(E12*10, 0))) & REPT("░", MAX(0, 10-MIN(10, ROUND(E12*10, 0))))) -> ░░░░░░░░░░ (Libre) | G12: =IF(B12=0, "⚪ Sin límite", IF(E12<=0.8, "🟢 En regla", IF(E12<=1, "🟡 Al Límite", "🔴 Excedido"))) -> ⚪ Sin límite | H12: =IF(B12=0, "Monitorear sin restricción", IF(E12>1, "Frenar gastos de inmediato", IF(E12>0.8, "Gastar solo en lo indispensable", "Consumo en rango normal"))) -> Monitorear sin restricción
A13: Otras categorías sin presupuesto | B13: 0 | C13: =PANEL!C28 -> 0 | D13: =IF(B13=0, 0, B13-C13) -> 0 | E13: =IF(B13=0, 0, C13/B13) -> 0 | F13: =IF(B13=0, "░░░░░░░░░░ (Libre)", REPT("█", MIN(10, ROUND(E13*10, 0))) & REPT("░", MAX(0, 10-MIN(10, ROUND(E13*10, 0))))) -> ░░░░░░░░░░ (Libre) | G13: =IF(B13=0, "⚪ Sin límite", IF(E13<=0.8, "🟢 En regla", IF(E13<=1, "🟡 Al Límite", "🔴 Excedido"))) -> ⚪ Sin límite | H13: =IF(B13=0, "Monitorear sin restricción", IF(E13>1, "Frenar gastos de inmediato", IF(E13>0.8, "Gastar solo en lo indispensable", "Consumo en rango normal"))) -> Monitorear sin restricción
A14: TOTAL PRESUPUESTO MENSUAL | B14: =SUM(B5:B13) -> 2390000 | C14: =SUM(C5:C13) -> 207123 | D14: =IF(B14=0, 0, B14-C14) -> 2182877 | E14: =IF(B14=0, 0, C14/B14) -> 0.086662343 | F14: =IF(B14=0, "░░░░░░░░░░", REPT("█", MIN(10, ROUND(E14*10, 0))) & REPT("░", MAX(0, 10-MIN(10, ROUND(E14*10, 0))))) -> █░░░░░░░░░ | G14: =IF(B14=0, "⚪ Sin límite", IF(E14<=0.8, "🟢 En regla", IF(E14<=1, "🟡 Al Límite", "🔴 Excedido"))) -> 🟢 En regla | H14: Consolidado de categorías con límite

Sheet ANÁLISIS
A1: 📊 TABLERO DE INTELIGENCIA FINANCIERA Y TENDENCIAS
A2: Consolidado comparativo mensual de ingresos, gastos, ahorro cooperativo y flujo neto anual
A4: Mes / Período | B4: Ingresos ($) | C4: Gastos ($) | D4: Ahorro ($) | E4: Balance Neto ($) | F4: Tasa Ahorro (%) | G4: Salud
A5: Enero 2026 | B5: =IFERROR(SUMIFS('COLILLAS DE PAGO'!$O$4:$O$22, 'COLILLAS DE PAGO'!$B$4:$B$22, "enero", 'COLILLAS DE PAGO'!$C$4:$C$22, PANEL!$I$2) + SUMIFS(MOVIMIENTOS!$H$4:$H$246, MOVIMIENTOS!$D$4:$D$246, "Ingreso", MOVIMIENTOS!$E$4:$E$246, "<>Salario", MOVIMIENTOS!$K$4:$K$246, "enero", MOVIMIENTOS!$L$4:$L$246, PANEL!$I$2), 0) -> 3842222 | C5: =IFERROR(SUMIFS(MOVIMIENTOS!$H$4:$H$246, MOVIMIENTOS!$D$4:$D$246, "Gasto", MOVIMIENTOS!$K$4:$K$246, "enero", MOVIMIENTOS!$L$4:$L$246, PANEL!$I$2), 0) -> 1359128 | D5: =IFERROR(SUMIFS(AHORROS!$E$14:$E$87, AHORROS!$F$14:$F$87, "enero", AHORROS!$G$14:$G$87, PANEL!$I$2), 0) -> 381133 | E5: =B5-C5 -> 2483094 | F5: =IF(B5=0, 0, D5/B5) -> 0.099195986 | G5: =IF(AND(B5=0, C5=0), "⚪ Proyectado", IF(E5>0, "🟢 Superávit", "🔴 Déficit")) -> 🟢 Superávit
A6: Febrero 2026 | B6: =IFERROR(SUMIFS('COLILLAS DE PAGO'!$O$4:$O$22, 'COLILLAS DE PAGO'!$B$4:$B$22, "febrero", 'COLILLAS DE PAGO'!$C$4:$C$22, PANEL!$I$2) + SUMIFS(MOVIMIENTOS!$H$4:$H$246, MOVIMIENTOS!$D$4:$D$246, "Ingreso", MOVIMIENTOS!$E$4:$E$246, "<>Salario", MOVIMIENTOS!$K$4:$K$246, "febrero", MOVIMIENTOS!$L$4:$L$246, PANEL!$I$2), 0) -> 2733672 | C6: =IFERROR(SUMIFS(MOVIMIENTOS!$H$4:$H$246, MOVIMIENTOS!$D$4:$D$246, "Gasto", MOVIMIENTOS!$K$4:$K$246, "febrero", MOVIMIENTOS!$L$4:$L$246, PANEL!$I$2), 0) -> 2296000 | D6: =IFERROR(SUMIFS(AHORROS!$E$14:$E$87, AHORROS!$F$14:$F$87, "febrero", AHORROS!$G$14:$G$87, PANEL!$I$2), 0) -> 381134 | E6: =B6-C6 -> 437672 | F6: =IF(B6=0, 0, D6/B6) -> 0.13942199 | G6: =IF(AND(B6=0, C6=0), "⚪ Proyectado", IF(E6>0, "🟢 Superávit", "🔴 Déficit")) -> 🟢 Superávit
A7: Marzo 2026 | B7: =IFERROR(SUMIFS('COLILLAS DE PAGO'!$O$4:$O$22, 'COLILLAS DE PAGO'!$B$4:$B$22, "marzo", 'COLILLAS DE PAGO'!$C$4:$C$22, PANEL!$I$2) + SUMIFS(MOVIMIENTOS!$H$4:$H$246, MOVIMIENTOS!$D$4:$D$246, "Ingreso", MOVIMIENTOS!$E$4:$E$246, "<>Salario", MOVIMIENTOS!$K$4:$K$246, "marzo", MOVIMIENTOS!$L$4:$L$246, PANEL!$I$2), 0) -> 3509411 | C7: =IFERROR(SUMIFS(MOVIMIENTOS!$H$4:$H$246, MOVIMIENTOS!$D$4:$D$246, "Gasto", MOVIMIENTOS!$K$4:$K$246, "marzo", MOVIMIENTOS!$L$4:$L$246, PANEL!$I$2), 0) -> 2814000 | D7: =IFERROR(SUMIFS(AHORROS!$E$14:$E$87, AHORROS!$F$14:$F$87, "marzo", AHORROS!$G$14:$G$87, PANEL!$I$2), 0) -> 472242 | E7: =B7-C7 -> 695411 | F7: =IF(B7=0, 0, D7/B7) -> 0.13456446 | G7: =IF(AND(B7=0, C7=0), "⚪ Proyectado", IF(E7>0, "🟢 Superávit", "🔴 Déficit")) -> 🟢 Superávit
A8: Abril 2026 | B8: =IFERROR(SUMIFS('COLILLAS DE PAGO'!$O$4:$O$22, 'COLILLAS DE PAGO'!$B$4:$B$22, "abril", 'COLILLAS DE PAGO'!$C$4:$C$22, PANEL!$I$2) + SUMIFS(MOVIMIENTOS!$H$4:$H$246, MOVIMIENTOS!$D$4:$D$246, "Ingreso", MOVIMIENTOS!$E$4:$E$246, "<>Salario", MOVIMIENTOS!$K$4:$K$246, "abril", MOVIMIENTOS!$L$4:$L$246, PANEL!$I$2), 0) -> 3494112 | C8: =IFERROR(SUMIFS(MOVIMIENTOS!$H$4:$H$246, MOVIMIENTOS!$D$4:$D$246, "Gasto", MOVIMIENTOS!$K$4:$K$246, "abril", MOVIMIENTOS!$L$4:$L$246, PANEL!$I$2), 0) -> 3129946 | D8: =IFERROR(SUMIFS(AHORROS!$E$14:$E$87, AHORROS!$F$14:$F$87, "abril", AHORROS!$G$14:$G$87, PANEL!$I$2), 0) -> 472242 | E8: =B8-C8 -> 364166 | F8: =IF(B8=0, 0, D8/B8) -> 0.13515365 | G8: =IF(AND(B8=0, C8=0), "⚪ Proyectado", IF(E8>0, "🟢 Superávit", "🔴 Déficit")) -> 🟢 Superávit
A9: Mayo 2026 | B9: =IFERROR(SUMIFS('COLILLAS DE PAGO'!$O$4:$O$22, 'COLILLAS DE PAGO'!$B$4:$B$22, "mayo", 'COLILLAS DE PAGO'!$C$4:$C$22, PANEL!$I$2) + SUMIFS(MOVIMIENTOS!$H$4:$H$246, MOVIMIENTOS!$D$4:$D$246, "Ingreso", MOVIMIENTOS!$E$4:$E$246, "<>Salario", MOVIMIENTOS!$K$4:$K$246, "mayo", MOVIMIENTOS!$L$4:$L$246, PANEL!$I$2), 0) -> 3163753 | C9: =IFERROR(SUMIFS(MOVIMIENTOS!$H$4:$H$246, MOVIMIENTOS!$D$4:$D$246, "Gasto", MOVIMIENTOS!$K$4:$K$246, "mayo", MOVIMIENTOS!$L$4:$L$246, PANEL!$I$2), 0) -> 2829200 | D9: =IFERROR(SUMIFS(AHORROS!$E$14:$E$87, AHORROS!$F$14:$F$87, "mayo", AHORROS!$G$14:$G$87, PANEL!$I$2), 0) -> 426688 | E9: =B9-C9 -> 334553 | F9: =IF(B9=0, 0, D9/B9) -> 0.13486767 | G9: =IF(AND(B9=0, C9=0), "⚪ Proyectado", IF(E9>0, "🟢 Superávit", "🔴 Déficit")) -> 🟢 Superávit
A10: Junio 2026 | B10: =IFERROR(SUMIFS('COLILLAS DE PAGO'!$O$4:$O$22, 'COLILLAS DE PAGO'!$B$4:$B$22, "junio", 'COLILLAS DE PAGO'!$C$4:$C$22, PANEL!$I$2) + SUMIFS(MOVIMIENTOS!$H$4:$H$246, MOVIMIENTOS!$D$4:$D$246, "Ingreso", MOVIMIENTOS!$E$4:$E$246, "<>Salario", MOVIMIENTOS!$K$4:$K$246, "junio", MOVIMIENTOS!$L$4:$L$246, PANEL!$I$2), 0) -> 5458114 | C10: =IFERROR(SUMIFS(MOVIMIENTOS!$H$4:$H$246, MOVIMIENTOS!$D$4:$D$246, "Gasto", MOVIMIENTOS!$K$4:$K$246, "junio", MOVIMIENTOS!$L$4:$L$246, PANEL!$I$2), 0) -> 3892812 | D10: =IFERROR(SUMIFS(AHORROS!$E$14:$E$87, AHORROS!$F$14:$F$87, "junio", AHORROS!$G$14:$G$87, PANEL!$I$2), 0) -> 472242 | E10: =B10-C10 -> 1565302 | F10: =IF(B10=0, 0, D10/B10) -> 0.086521095 | G10: =IF(AND(B10=0, C10=0), "⚪ Proyectado", IF(E10>0, "🟢 Superávit", "🔴 Déficit")) -> 🟢 Superávit
A11: Julio 2026 | B11: =IFERROR(SUMIFS('COLILLAS DE PAGO'!$O$4:$O$22, 'COLILLAS DE PAGO'!$B$4:$B$22, "julio", 'COLILLAS DE PAGO'!$C$4:$C$22, PANEL!$I$2) + SUMIFS(MOVIMIENTOS!$H$4:$H$246, MOVIMIENTOS!$D$4:$D$246, "Ingreso", MOVIMIENTOS!$E$4:$E$246, "<>Salario", MOVIMIENTOS!$K$4:$K$246, "julio", MOVIMIENTOS!$L$4:$L$246, PANEL!$I$2), 0) -> 3172191 | C11: =IFERROR(SUMIFS(MOVIMIENTOS!$H$4:$H$246, MOVIMIENTOS!$D$4:$D$246, "Gasto", MOVIMIENTOS!$K$4:$K$246, "julio", MOVIMIENTOS!$L$4:$L$246, PANEL!$I$2), 0) -> 2546900 | D11: =IFERROR(SUMIFS(AHORROS!$E$14:$E$87, AHORROS!$F$14:$F$87, "julio", AHORROS!$G$14:$G$87, PANEL!$I$2), 0) -> 381134 | E11: =B11-C11 -> 625291 | F11: =IF(B11=0, 0, D11/B11) -> 0.1201485 | G11: =IF(AND(B11=0, C11=0), "⚪ Proyectado", IF(E11>0, "🟢 Superávit", "🔴 Déficit")) -> 🟢 Superávit
A12: Agosto 2026 | B12: =IFERROR(SUMIFS('COLILLAS DE PAGO'!$O$4:$O$22, 'COLILLAS DE PAGO'!$B$4:$B$22, "agosto", 'COLILLAS DE PAGO'!$C$4:$C$22, PANEL!$I$2) + SUMIFS(MOVIMIENTOS!$H$4:$H$246, MOVIMIENTOS!$D$4:$D$246, "Ingreso", MOVIMIENTOS!$E$4:$E$246, "<>Salario", MOVIMIENTOS!$K$4:$K$246, "agosto", MOVIMIENTOS!$L$4:$L$246, PANEL!$I$2), 0) -> 3735393 | C12: =IFERROR(SUMIFS(MOVIMIENTOS!$H$4:$H$246, MOVIMIENTOS!$D$4:$D$246, "Gasto", MOVIMIENTOS!$K$4:$K$246, "agosto", MOVIMIENTOS!$L$4:$L$246, PANEL!$I$2), 0) -> 1668936 | D12: =IFERROR(SUMIFS(AHORROS!$E$14:$E$87, AHORROS!$F$14:$F$87, "agosto", AHORROS!$G$14:$G$87, PANEL!$I$2), 0) -> 426688 | E12: =B12-C12 -> 2066457 | F12: =IF(B12=0, 0, D12/B12) -> 0.11422841 | G12: =IF(AND(B12=0, C12=0), "⚪ Proyectado", IF(E12>0, "🟢 Superávit", "🔴 Déficit")) -> 🟢 Superávit
A13: Septiembre 2026 | B13: =IFERROR(SUMIFS('COLILLAS DE PAGO'!$O$4:$O$22, 'COLILLAS DE PAGO'!$B$4:$B$22, "septiembre", 'COLILLAS DE PAGO'!$C$4:$C$22, PANEL!$I$2) + SUMIFS(MOVIMIENTOS!$H$4:$H$246, MOVIMIENTOS!$D$4:$D$246, "Ingreso", MOVIMIENTOS!$E$4:$E$246, "<>Salario", MOVIMIENTOS!$K$4:$K$246, "septiembre", MOVIMIENTOS!$L$4:$L$246, PANEL!$I$2), 0) -> 3343005 | C13: =IFERROR(SUMIFS(MOVIMIENTOS!$H$4:$H$246, MOVIMIENTOS!$D$4:$D$246, "Gasto", MOVIMIENTOS!$K$4:$K$246, "septiembre", MOVIMIENTOS!$L$4:$L$246, PANEL!$I$2), 0) -> 2206444 | D13: =IFERROR(SUMIFS(AHORROS!$E$14:$E$87, AHORROS!$F$14:$F$87, "septiembre", AHORROS!$G$14:$G$87, PANEL!$I$2), 0) -> 517796 | E13: =B13-C13 -> 1136561 | F13: =IF(B13=0, 0, D13/B13) -> 0.15488939 | G13: =IF(AND(B13=0, C13=0), "⚪ Proyectado", IF(E13>0, "🟢 Superávit", "🔴 Déficit")) -> 🟢 Superávit
A14: Octubre 2026 | B14: =IFERROR(SUMIFS('COLILLAS DE PAGO'!$O$4:$O$22, 'COLILLAS DE PAGO'!$B$4:$B$22, "octubre", 'COLILLAS DE PAGO'!$C$4:$C$22, PANEL!$I$2) + SUMIFS(MOVIMIENTOS!$H$4:$H$246, MOVIMIENTOS!$D$4:$D$246, "Ingreso", MOVIMIENTOS!$E$4:$E$246, "<>Salario", MOVIMIENTOS!$K$4:$K$246, "octubre", MOVIMIENTOS!$L$4:$L$246, PANEL!$I$2), 0) -> 0 | C14: =IFERROR(SUMIFS(MOVIMIENTOS!$H$4:$H$246, MOVIMIENTOS!$D$4:$D$246, "Gasto", MOVIMIENTOS!$K$4:$K$246, "octubre", MOVIMIENTOS!$L$4:$L$246, PANEL!$I$2), 0) -> 207123 | D14: =IFERROR(SUMIFS(AHORROS!$E$14:$E$87, AHORROS!$F$14:$F$87, "octubre", AHORROS!$G$14:$G$87, PANEL!$I$2), 0) -> 0 | E14: =B14-C14 -> -207123 | F14: =IF(B14=0, 0, D14/B14) -> 0 | G14: =IF(AND(B14=0, C14=0), "⚪ Proyectado", IF(E14>0, "🟢 Superávit", "🔴 Déficit")) -> 🔴 Déficit
A15: Noviembre 2026 | B15: =IFERROR(SUMIFS('COLILLAS DE PAGO'!$O$4:$O$22, 'COLILLAS DE PAGO'!$B$4:$B$22, "noviembre", 'COLILLAS DE PAGO'!$C$4:$C$22, PANEL!$I$2) + SUMIFS(MOVIMIENTOS!$H$4:$H$246, MOVIMIENTOS!$D$4:$D$246, "Ingreso", MOVIMIENTOS!$E$4:$E$246, "<>Salario", MOVIMIENTOS!$K$4:$K$246, "noviembre", MOVIMIENTOS!$L$4:$L$246, PANEL!$I$2), 0) -> 0 | C15: =IFERROR(SUMIFS(MOVIMIENTOS!$H$4:$H$246, MOVIMIENTOS!$D$4:$D$246, "Gasto", MOVIMIENTOS!$K$4:$K$246, "noviembre", MOVIMIENTOS!$L$4:$L$246, PANEL!$I$2), 0) -> 0 | D15: =IFERROR(SUMIFS(AHORROS!$E$14:$E$87, AHORROS!$F$14:$F$87, "noviembre", AHORROS!$G$14:$G$87, PANEL!$I$2), 0) -> 0 | E15: =B15-C15 -> 0 | F15: =IF(B15=0, 0, D15/B15) -> 0 | G15: =IF(AND(B15=0, C15=0), "⚪ Proyectado", IF(E15>0, "🟢 Superávit", "🔴 Déficit")) -> ⚪ Proyectado
A16: Diciembre 2026 | B16: =IFERROR(SUMIFS('COLILLAS DE PAGO'!$O$4:$O$22, 'COLILLAS DE PAGO'!$B$4:$B$22, "diciembre", 'COLILLAS DE PAGO'!$C$4:$C$22, PANEL!$I$2) + SUMIFS(MOVIMIENTOS!$H$4:$H$246, MOVIMIENTOS!$D$4:$D$246, "Ingreso", MOVIMIENTOS!$E$4:$E$246, "<>Salario", MOVIMIENTOS!$K$4:$K$246, "diciembre", MOVIMIENTOS!$L$4:$L$246, PANEL!$I$2), 0) -> 0 | C16: =IFERROR(SUMIFS(MOVIMIENTOS!$H$4:$H$246, MOVIMIENTOS!$D$4:$D$246, "Gasto", MOVIMIENTOS!$K$4:$K$246, "diciembre", MOVIMIENTOS!$L$4:$L$246, PANEL!$I$2), 0) -> 0 | D16: =IFERROR(SUMIFS(AHORROS!$E$14:$E$87, AHORROS!$F$14:$F$87, "diciembre", AHORROS!$G$14:$G$87, PANEL!$I$2), 0) -> 0 | E16: =B16-C16 -> 0 | F16: =IF(B16=0, 0, D16/B16) -> 0 | G16: =IF(AND(B16=0, C16=0), "⚪ Proyectado", IF(E16>0, "🟢 Superávit", "🔴 Déficit")) -> ⚪ Proyectado
A17: TOTAL ANUAL CONSOLIDADO | B17: =SUM(B5:B16) -> 32451873 | C17: =SUM(C5:C16) -> 22950489 | D17: =SUM(D5:D16) -> 3931299 | E17: =SUM(E5:E16) -> 9501384 | F17: =IF(B17=0, 0, D17/B17) -> 0.12114244 | G17: =IF(E17>0, "🟢 SUPERÁVIT ANUAL", "🔴 DÉFICIT ANUAL") -> 🟢 SUPERÁVIT ANUAL
A19: COMPOSICIÓN DE GASTOS DEL MES ACTIVO
A20: Categoría | B20: Gasto Mes ($)
A21: Alimentación | B21: ='PRESUPUESTO Y ALERTAS'!C5 -> 0
A22: ARRIENDO CASA | B22: ='PRESUPUESTO Y ALERTAS'!C6 -> 0
A23: Servicios Públicos | B23: ='PRESUPUESTO Y ALERTAS'!C7 -> 0
A24: Transporte y Moto | B24: ='PRESUPUESTO Y ALERTAS'!C8 -> 116000
A25: Gastos Hormiga / Dulces | B25: ='PRESUPUESTO Y ALERTAS'!C9 -> 67000
A26: Ocio y Entretenimiento | B26: ='PRESUPUESTO Y ALERTAS'!C10 -> 14023
A27: Suscripciones | B27: ='PRESUPUESTO Y ALERTAS'!C11 -> 10100
A28: Compras | B28: ='PRESUPUESTO Y ALERTAS'!C12 -> 0

Sheet PATRIMONIO NETO
A1: 🏛️ BALANCE GENERAL Y PATRIMONIO NETO — MARLON MUÑOZ PARDO
A2: Estado de situación financiera personal: Activos líquidos, ahorros cooperativos y pasivos del mes
B4: TOTAL ACTIVOS | E4: TOTAL PASIVOS | H4: PATRIMONIO NETO REAL | K4: MESES DE COBERTURA
B5: =E15 -> 14822156 | E5: =J15 -> 2557000 | H5: =B5-E5 -> 12265156 | K5: =IF(PANEL!E6=0, 0, B5/PANEL!E6) -> 71.562096
B7: DETALLE DE ACTIVOS (RECURSOS Y DERECHOS) | G7: DETALLE DE PASIVOS (OBLIGACIONES Y DEUDAS)
B8: Clase de Activo | C8: Concepto / Detalle | D8: Entidad / Ubicación | E8: Valor Estimado ($) | G8: Clase de Pasivo | H8: Concepto / Detalle | I8: Acreedor / Medio | J8: Monto Pendiente ($)
B9: Líquido | C9: Cuenta de Ahorros Principal | D9: AyC Colanta (Nómina) | E9: =PANEL!J39 -> 3319057 | G9: Corriente | H9: Compromisos Fijos Abiertos Mes | I9: Control Fijos Colanta | J9: ='CONTROL FIJOS'!G5 -> 2557000
B10: Líquido | C10: Depósito de Bajo Monto | D10: Nequi Marlon | E10: =PANEL!J40 -> 0 | G10: Crédito | H10: Tarjeta de Crédito / Cupo Usado | I10: Bancolombia | J10: 0
B11: Líquido | C11: Efectivo Disponible en Mano | D11: Billetera Física | E11: =PANEL!J41 -> 71800 | G11: Préstamo | H11: Obligaciones Bancarias / Terceros | I11: Entidad Financiera | J11: 0
B12: Inversión / Ahorro | C12: Fondos de Ahorro Acumulados | D12: Cooperativa Colanta | E12: =AHORROS!C12 -> 3931299 | G12: Otros | H12: Otras Deudas Pendientes | I12: Varios | J12: 0
B13: Por Cobrar | C13: Cartera de Préstamos Activa | D13: Cuentas por Cobrar | E13: ='CUENTAS POR COBRAR'!E5 -> 0 | G13: - | H13: Sin pasivos adicionales | I13: - | J13: 0
B14: Bien Físico | C14: Motocicleta (Valor Comercial) | D14: Propiedad Marlon | E14: 7500000 | G14: - | H14: Sin pasivos adicionales | I14: - | J14: 0
B15: TOTAL ACTIVOS CONSOLIDADOS | E15: =SUM(E9:E14) -> 14822156 | G15: TOTAL PASIVOS CONSOLIDADOS | J15: =SUM(J9:J14) -> 2557000

Sheet HISTORICO FIJOS
A1: 📅 HISTÓRICO Y PROYECCIÓN DE COMPROMISOS FIJOS — MARLON MUÑOZ
A2: Base maestra mensual de obligaciones fijas, suscripciones y servicios públicos
A3: ID Fijo | B3: Concepto / Servicio | C3: Categoría | D3: Día Cobro | E3: Cuota Base ($) | F3: Abonado ($) | G3: Fecha Pago | H3: Estado | I3: Período (YYYY-MM) | J3: Mes | K3: Año | L3: Prioridad | M3: Medio de Pago | N3: Saldo Pendiente ($) | O3: Notas | P3: _IndexFiltro
A4: F-0332 | B4: EPM Energía | C4: Servicios | D4: 15 | E4: 124000 | F4: 124000 | G4: 2026-01-15 | H4: =IF(ISBLANK(A4),"",IF(N(F4)>=E4,"🟢 Pagado",IF(N(F4)>0,"🟡 Abono Parcial","🔴 Pendiente"))) -> 🟢 Pagado | I4: 2026-01-01 | J4: enero | K4: 2026 | L4: Media | M4: No especificado | N4: =IF(ISBLANK(A4),"",MAX(0, E4-N(F4))) -> 0 | O4: Copiado de abril 2026; obligación sin movimiento real | PAGADO_CON_MOVIMIENTO_ENERO_2026 | P4: =IF(ISBLANK(A4), "", IF(AND(LOWER(TRIM(J4))=LOWER(TRIM(PANEL!$L$2)), K4=PANEL!$I$2), MAX($P$3:P3)+1, ""))
A5: F-0333 | B5: Servicios Agua | C5: Servicios | D5: 15 | E5: 60000 | F5: 60000 | G5: 2026-01-15 | H5: =IF(ISBLANK(A5),"",IF(N(F5)>=E5,"🟢 Pagado",IF(N(F5)>0,"🟡 Abono Parcial","🔴 Pendiente"))) -> 🟢 Pagado | I5: 2026-01-01 | J5: enero | K5: 2026 | L5: Media | M5: No especificado | N5: =IF(ISBLANK(A5),"",MAX(0, E5-N(F5))) -> 0 | O5: Copiado de abril 2026; obligación sin movimiento real | PAGADO_CON_MOVIMIENTO_ENERO_2026 | P5: =IF(ISBLANK(A5), "", IF(AND(LOWER(TRIM(J5))=LOWER(TRIM(PANEL!$L$2)), K5=PANEL!$I$2), MAX($P$3:P4)+1, ""))
A6: F-0334 | B6: Internet Tigo | C6: Servicios | D6: 15 | E6: 62128 | F6: 62128 | G6: 2026-01-15 | H6: =IF(ISBLANK(A6),"",IF(N(F6)>=E6,"🟢 Pagado",IF(N(F6)>0,"🟡 Abono Parcial","🔴 Pendiente"))) -> 🟢 Pagado | I6: 2026-01-01 | J6: enero | K6: 2026 | L6: Media | M6: No especificado | N6: =IF(ISBLANK(A6),"",MAX(0, E6-N(F6))) -> 0 | O6: Copiado de abril 2026; obligación sin movimiento real | PAGADO_CON_MOVIMIENTO_ENERO_2026 | P6: =IF(ISBLANK(A6), "", IF(AND(LOWER(TRIM(J6))=LOWER(TRIM(PANEL!$L$2)), K6=PANEL!$I$2), MAX($P$3:P5)+1, ""))
A7: F-0335 | B7: Gasolina Moto Quincena | C7: Moto | D7: 15 | E7: 20000 | F7: 20000 | G7: 2026-01-15 | H7: =IF(ISBLANK(A7),"",IF(N(F7)>=E7,"🟢 Pagado",IF(N(F7)>0,"🟡 Abono Parcial","🔴 Pendiente"))) -> 🟢 Pagado | I7: 2026-01-01 | J7: enero | K7: 2026 | L7: Media | M7: No especificado | N7: =IF(ISBLANK(A7),"",MAX(0, E7-N(F7))) -> 0 | O7: Copiado de abril 2026; obligación sin movimiento real | PAGADO_CON_MOVIMIENTO_ENERO_2026 | P7: =IF(ISBLANK(A7), "", IF(AND(LOWER(TRIM(J7))=LOWER(TRIM(PANEL!$L$2)), K7=PANEL!$I$2), MAX($P$3:P6)+1, ""))
A8: F-0336 | B8: Spotify | C8: Entretenimiento | D8: 15 | E8: 10000 | F8: 10000 | G8: 2026-01-15 | H8: =IF(ISBLANK(A8),"",IF(N(F8)>=E8,"🟢 Pagado",IF(N(F8)>0,"🟡 Abono Parcial","🔴 Pendiente"))) -> 🟢 Pagado | I8: 2026-01-01 | J8: enero | K8: 2026 | L8: Media | M8: No especificado | N8: =IF(ISBLANK(A8),"",MAX(0, E8-N(F8))) -> 0 | O8: Copiado de abril 2026; obligación sin movimiento real | PAGADO_CON_MOVIMIENTO_ENERO_2026 | P8: =IF(ISBLANK(A8), "", IF(AND(LOWER(TRIM(J8))=LOWER(TRIM(PANEL!$L$2)), K8=PANEL!$I$2), MAX($P$3:P7)+1, ""))
A9: F-0337 | B9: Arriendo Casa | C9: Vivienda | D9: 30 | E9: 900000 | F9: 900000 | G9: 2026-01-31 | H9: =IF(ISBLANK(A9),"",IF(N(F9)>=E9,"🟢 Pagado",IF(N(F9)>0,"🟡 Abono Parcial","🔴 Pendiente"))) -> 🟢 Pagado | I9: 2026-01-01 | J9: enero | K9: 2026 | L9: Media | M9: No especificado | N9: =IF(ISBLANK(A9),"",MAX(0, E9-N(F9))) -> 0 | O9: Copiado de abril 2026; obligación sin movimiento real | PAGADO_CON_MOVIMIENTO_ENERO_2026 | P9: =IF(ISBLANK(A9), "", IF(AND(LOWER(TRIM(J9))=LOWER(TRIM(PANEL!$L$2)), K9=PANEL!$I$2), MAX($P$3:P8)+1, ""))
A10: F-0338 | B10: Cuota Datos Celular | C10: Servicios | D10: 30 | E10: 48000 | F10: 48000 | G10: 2026-01-31 | H10: =IF(ISBLANK(A10),"",IF(N(F10)>=E10,"🟢 Pagado",IF(N(F10)>0,"🟡 Abono Parcial","🔴 Pendiente"))) -> 🟢 Pagado | I10: 2026-01-01 | J10: enero | K10: 2026 | L10: Media | M10: No especificado | N10: =IF(ISBLANK(A10),"",MAX(0, E10-N(F10))) -> 0 | O10: Copiado de abril 2026; obligación sin movimiento real | PAGADO_CON_MOVIMIENTO_ENERO_2026 | P10: =IF(ISBLANK(A10), "", IF(AND(LOWER(TRIM(J10))=LOWER(TRIM(PANEL!$L$2)), K10=PANEL!$I$2), MAX($P$3:P9)+1, ""))
A11: F-0339 | B11: Gasolina Moto Fin de Mes | C11: Moto | D11: 30 | E11: 35000 | F11: 35000 | G11: 2026-01-31 | H11: =IF(ISBLANK(A11),"",IF(N(F11)>=E11,"🟢 Pagado",IF(N(F11)>0,"🟡 Abono Parcial","🔴 Pendiente"))) -> 🟢 Pagado | I11: 2026-01-01 | J11: enero | K11: 2026 | L11: Media | M11: No especificado | N11: =IF(ISBLANK(A11),"",MAX(0, E11-N(F11))) -> 0 | O11: Copiado de abril 2026; obligación sin movimiento real | PAGADO_CON_MOVIMIENTO_ENERO_2026 | P11: =IF(ISBLANK(A11), "", IF(AND(LOWER(TRIM(J11))=LOWER(TRIM(PANEL!$L$2)), K11=PANEL!$I$2), MAX($P$3:P10)+1, ""))
A12: F-0340 | B12: Parqueadero Trabajo Fin de Mes | C12: Transporte | D12: 30 | E12: 40000 | F12: 40000 | G12: 2026-01-31 | H12: =IF(ISBLANK(A12),"",IF(N(F12)>=E12,"🟢 Pagado",IF(N(F12)>0,"🟡 Abono Parcial","🔴 Pendiente"))) -> 🟢 Pagado | I12: 2026-01-01 | J12: enero | K12: 2026 | L12: Media | M12: No especificado | N12: =IF(ISBLANK(A12),"",MAX(0, E12-N(F12))) -> 0 | O12: Copiado de abril 2026; obligación sin movimiento real | PAGADO_CON_MOVIMIENTO_ENERO_2026 | P12: =IF(ISBLANK(A12), "", IF(AND(LOWER(TRIM(J12))=LOWER(TRIM(PANEL!$L$2)), K12=PANEL!$I$2), MAX($P$3:P11)+1, ""))
A13: F-0341 | B13: Parqueadero Moto Fin de Mes | C13: Moto | D13: 30 | E13: 60000 | F13: 60000 | G13: 2026-01-31 | H13: =IF(ISBLANK(A13),"",IF(N(F13)>=E13,"🟢 Pagado",IF(N(F13)>0,"🟡 Abono Parcial","🔴 Pendiente"))) -> 🟢 Pagado | I13: 2026-01-01 | J13: enero | K13: 2026 | L13: Media | M13: No especificado | N13: =IF(ISBLANK(A13),"",MAX(0, E13-N(F13))) -> 0 | O13: Copiado de abril 2026; obligación sin movimiento real | PAGADO_CON_MOVIMIENTO_ENERO_2026 | P13: =IF(ISBLANK(A13), "", IF(AND(LOWER(TRIM(J13))=LOWER(TRIM(PANEL!$L$2)), K13=PANEL!$I$2), MAX($P$3:P12)+1, ""))
A14: F-0026 | B14: EPM Energía | C14: Servicios | D14: 15 | E14: 110000 | F14: 110000 | G14: 2026-02-15 | H14: =IF(ISBLANK(A14),"",IF(N(F14)>=E14,"🟢 Pagado",IF(N(F14)>0,"🟡 Abono Parcial","🔴 Pendiente"))) -> 🟢 Pagado | I14: 2026-02-01 | J14: febrero | K14: 2026 | L14: Media | M14: No especificado | N14: =IF(ISBLANK(A14),"",MAX(0, E14-N(F14))) -> 0 | O14: HIST_FIJOS_2026-08-22 | P14: =IF(ISBLANK(A14), "", IF(AND(LOWER(TRIM(J14))=LOWER(TRIM(PANEL!$L$2)), K14=PANEL!$I$2), MAX($P$3:P13)+1, ""))
A15: F-0027 | B15: Internet Tigo | C15: Servicios | D15: 15 | E15: 120000 | F15: 120000 | G15: 2026-02-15 | H15: =IF(ISBLANK(A15),"",IF(N(F15)>=E15,"🟢 Pagado",IF(N(F15)>0,"🟡 Abono Parcial","🔴 Pendiente"))) -> 🟢 Pagado | I15: 2026-02-01 | J15: febrero | K15: 2026 | L15: Media | M15: No especificado | N15: =IF(ISBLANK(A15),"",MAX(0, E15-N(F15))) -> 0 | O15: HIST_FIJOS_2026-08-22 | P15: =IF(ISBLANK(A15), "", IF(AND(LOWER(TRIM(J15))=LOWER(TRIM(PANEL!$L$2)), K15=PANEL!$I$2), MAX($P$3:P14)+1, ""))
... A64: F-0091 | B64: Parqueadero Moto Fin de Mes | C64: Moto | D64: 31 | E64: 40000 | F64: 40000 | G64: 2026-07-31 | H64: =IF(ISBLANK(A64),"",IF(N(F64)>=E64,"🟢 Pagado",IF(N(F64)>0,"🟡 Abono Parcial","🔴 Pendiente"))) -> 🟢 Pagado | I64: 2026-07-01 | J64: julio | K64: 2026 | L64: Media | M64: No especificado | N64: =IF(ISBLANK(A64),"",MAX(0, E64-N(F64))) -> 0 | O64: HIST_FIJOS_2026-08-22 | P64: =IF(ISBLANK(A64), "", IF(AND(LOWER(TRIM(J64))=LOWER(TRIM(PANEL!$L$2)), K64=PANEL!$I$2), MAX($P$3:P63)+1, ""))
A65: F-0002 | B65: EPM ENERGIA | C65: Servicios | D65: 15 | E65: 177000 | F65: 177000 | G65: 2026-08-16 | H65: =IF(ISBLANK(A65),"",IF(N(F65)>=E65,"🟢 Pagado",IF(N(F65)>0,"🟡 Abono Parcial","🔴 Pendiente"))) -> 🟢 Pagado | I65: 2026-08-01 | J65: agosto | K65: 2026 | L65: Media | M65: Transferencia | N65: =IF(ISBLANK(A65),"",MAX(0, E65-N(F65))) -> 0 | P65: =IF(ISBLANK(A65), "", IF(AND(LOWER(TRIM(J65))=LOWER(TRIM(PANEL!$L$2)), K65=PANEL!$I$2), MAX($P$3:P64)+1, ""))
A66: F-0003 | B66: COMIDA | C66: Alimentación | D66: 15 | E66: 850000 | F66: 850000 | G66: 2026-08-17 | H66: =IF(ISBLANK(A66),"",IF(N(F66)>=E66,"🟢 Pagado",IF(N(F66)>0,"🟡 Abono Parcial","🔴 Pendiente"))) -> 🟢 Pagado | I66: 2026-08-01 | J66: agosto | K66: 2026 | L66: Media | M66: Transferencia | N66: =IF(ISBLANK(A66),"",MAX(0, E66-N(F66))) -> 0 | P66: =IF(ISBLANK(A66), "", IF(AND(LOWER(TRIM(J66))=LOWER(TRIM(PANEL!$L$2)), K66=PANEL!$I$2), MAX($P$3:P65)+1, ""))
A67: F-0004 | B67: Internet Tigo | C67: Servicios | D67: 15 | E67: 120000 | F67: 62136 | G67: 2026-09-01 | H67: =IF(ISBLANK(A67),"",IF(N(F67)>=E67,"🟢 Pagado",IF(N(F67)>0,"🟡 Abono Parcial","🔴 Pendiente"))) -> 🟡 Abono Parcial | I67: 2026-08-01 | J67: agosto | K67: 2026 | L67: Media | M67: Transferencia | N67: =IF(ISBLANK(A67),"",MAX(0, E67-N(F67))) -> 57864 | P67: =IF(ISBLANK(A67), "", IF(AND(LOWER(TRIM(J67))=LOWER(TRIM(PANEL!$L$2)), K67=PANEL!$I$2), MAX($P$3:P66)+1, ""))
A68: F-0005 | B68: Parqueadero Trabajo Semana | C68: Transporte | D68: 15 | E68: 40000 | F68: 17000 | G68: 2026-08-28 | H68: =IF(ISBLANK(A68),"",IF(N(F68)>=E68,"🟢 Pagado",IF(N(F68)>0,"🟡 Abono Parcial","🔴 Pendiente"))) -> 🟡 Abono Parcial | I68: 2026-08-01 | J68: agosto | K68: 2026 | L68: Media | M68: Transferencia | N68: =IF(ISBLANK(A68),"",MAX(0, E68-N(F68))) -> 23000 | P68: =IF(ISBLANK(A68), "", IF(AND(LOWER(TRIM(J68))=LOWER(TRIM(PANEL!$L$2)), K68=PANEL!$I$2), MAX($P$3:P67)+1, ""))
A69: F-0006 | B69: PARQUEADERO MOTO | C69: Moto | D69: 15 | E69: 60000 | F69: 60000 | G69: 2026-08-21 | H69: =IF(ISBLANK(A69),"",IF(N(F69)>=E69,"🟢 Pagado",IF(N(F69)>0,"🟡 Abono Parcial","🔴 Pendiente"))) -> 🟢 Pagado | I69: 2026-08-01 | J69: agosto | K69: 2026 | L69: Media | M69: Efectivo | N69: =IF(ISBLANK(A69),"",MAX(0, E69-N(F69))) -> 0 | P69: =IF(ISBLANK(A69), "", IF(AND(LOWER(TRIM(J69))=LOWER(TRIM(PANEL!$L$2)), K69=PANEL!$I$2), MAX($P$3:P68)+1, ""))
A70: F-0007 | B70: Gasolina Moto | C70: Moto | D70: 15 | E70: 35000 | F70: 35000 | G70: 2026-08-28 | H70: =IF(ISBLANK(A70),"",IF(N(F70)>=E70,"🟢 Pagado",IF(N(F70)>0,"🟡 Abono Parcial","🔴 Pendiente"))) -> 🟢 Pagado | I70: 2026-08-01 | J70: agosto | K70: 2026 | L70: Media | M70: Transferencia | N70: =IF(ISBLANK(A70),"",MAX(0, E70-N(F70))) -> 0 | P70: =IF(ISBLANK(A70), "", IF(AND(LOWER(TRIM(J70))=LOWER(TRIM(PANEL!$L$2)), K70=PANEL!$I$2), MAX($P$3:P69)+1, ""))
A71: F-0008 | B71: Spotify | C71: Entretenimiento | D71: 15 | E71: 10000 | F71: 10000 | G71: 2026-08-15 | H71: =IF(ISBLANK(A71),"",IF(N(F71)>=E71,"🟢 Pagado",IF(N(F71)>0,"🟡 Abono Parcial","🔴 Pendiente"))) -> 🟢 Pagado | I71: 2026-08-01 | J71: agosto | K71: 2026 | L71: Media | M71: Transferencia | N71: =IF(ISBLANK(A71),"",MAX(0, E71-N(F71))) -> 0 | P71: =IF(ISBLANK(A71), "", IF(AND(LOWER(TRIM(J71))=LOWER(TRIM(PANEL!$L$2)), K71=PANEL!$I$2), MAX($P$3:P70)+1, ""))
A72: F-0009 | B72: CUOTA DATOS CELULAR | C72: Servicios | D72: 15 | E72: 39000 | F72: 43900 | G72: 2026-08-31 | H72: =IF(ISBLANK(A72),"",IF(N(F72)>=E72,"🟢 Pagado",IF(N(F72)>0,"🟡 Abono Parcial","🔴 Pendiente"))) -> 🟢 Pagado | I72: 2026-08-01 | J72: agosto | K72: 2026 | L72: Media | M72: Efectivo | N72: =IF(ISBLANK(A72),"",MAX(0, E72-N(F72))) -> 0 | P72: =IF(ISBLANK(A72), "", IF(AND(LOWER(TRIM(J72))=LOWER(TRIM(PANEL!$L$2)), K72=PANEL!$I$2), MAX($P$3:P71)+1, ""))
A73: F-0010 | B73: ARRIENDO CASA | C73: Vivienda | D73: 30 | E73: 900000 | F73: 0 | H73: =IF(ISBLANK(A73),"",IF(N(F73)>=E73,"🟢 Pagado",IF(N(F73)>0,"🟡 Abono Parcial","🔴 Pendiente"))) -> 🔴 Pendiente | I73: 2026-08-01 | J73: agosto | K73: 2026 | L73: Media | M73: Efectivo | N73: =IF(ISBLANK(A73),"",MAX(0, E73-N(F73))) -> 900000 | P73: =IF(ISBLANK(A73), "", IF(AND(LOWER(TRIM(J73))=LOWER(TRIM(PANEL!$L$2)), K73=PANEL!$I$2), MAX($P$3:P72)+1, ""))
A74: F-0011 | B74: Google One | C74: Servicios | D74: 30 | E74: 20000 | F74: 20000 | G74: 2026-08-31 | H74: =IF(ISBLANK(A74),"",IF(N(F74)>=E74,"🟢 Pagado",IF(N(F74)>0,"🟡 Abono Parcial","🔴 Pendiente"))) -> 🟢 Pagado | I74: 2026-08-01 | J74: agosto | K74: 2026 | L74: Media | M74: Efectivo | N74: =IF(ISBLANK(A74),"",MAX(0, E74-N(F74))) -> 0 | P74: =IF(ISBLANK(A74), "", IF(AND(LOWER(TRIM(J74))=LOWER(TRIM(PANEL!$L$2)), K74=PANEL!$I$2), MAX($P$3:P73)+1, ""))
A75: F-0012 | B75: Gasolina Moto | C75: Moto | D75: 30 | E75: 25000 | F75: 0 | H75: =IF(ISBLANK(A75),"",IF(N(F75)>=E75,"🟢 Pagado",IF(N(F75)>0,"🟡 Abono Parcial","🔴 Pendiente"))) -> 🔴 Pendiente | I75: 2026-08-01 | J75: agosto | K75: 2026 | L75: Media | M75: Efectivo | N75: =IF(ISBLANK(A75),"",MAX(0, E75-N(F75))) -> 25000 | P75: =IF(ISBLANK(A75), "", IF(AND(LOWER(TRIM(J75))=LOWER(TRIM(PANEL!$L$2)), K75=PANEL!$I$2), MAX($P$3:P74)+1, ""))
A76: F-0013 | B76: Parqueadero Trabajo Semana | C76: Transporte | D76: 30 | E76: 40000 | F76: 0 | H76: =IF(ISBLANK(A76),"",IF(N(F76)>=E76,"🟢 Pagado",IF(N(F76)>0,"🟡 Abono Parcial","🔴 Pendiente"))) -> 🔴 Pendiente | I76: 2026-08-01 | J76: agosto | K76: 2026 | L76: Media | M76: Efectivo | N76: =IF(ISBLANK(A76),"",MAX(0, E76-N(F76))) -> 40000 | P76: =IF(ISBLANK(A76), "", IF(AND(LOWER(TRIM(J76))=LOWER(TRIM(PANEL!$L$2)), K76=PANEL!$I$2), MAX($P$3:P75)+1, ""))
A77: F-0014 | B77: COMIDA | C77: Alimentación | D77: 30 | E77: 200000 | F77: 0 | H77: =IF(ISBLANK(A77),"",IF(N(F77)>=E77,"🟢 Pagado",IF(N(F77)>0,"🟡 Abono Parcial","🔴 Pendiente"))) -> 🔴 Pendiente | I77: 2026-08-01 | J77: agosto | K77: 2026 | L77: Media | M77: Efectivo | N77: =IF(ISBLANK(A77),"",MAX(0, E77-N(F77))) -> 200000 | P77: =IF(ISBLANK(A77), "", IF(AND(LOWER(TRIM(J77))=LOWER(TRIM(PANEL!$L$2)), K77=PANEL!$I$2), MAX($P$3:P76)+1, ""))
A78: F-0015 | B78: PARQUEADERO MOTO | C78: Moto | D78: 30 | E78: 40000 | F78: 0 | H78: =IF(ISBLANK(A78),"",IF(N(F78)>=E78,"🟢 Pagado",IF(N(F78)>0,"🟡 Abono Parcial","🔴 Pendiente"))) -> 🔴 Pendiente | I78: 2026-08-01 | J78: agosto | K78: 2026 | L78: Media | M78: Efectivo | N78: =IF(ISBLANK(A78),"",MAX(0, E78-N(F78))) -> 40000 | P78: =IF(ISBLANK(A78), "", IF(AND(LOWER(TRIM(J78))=LOWER(TRIM(PANEL!$L$2)), K78=PANEL!$I$2), MAX($P$3:P77)+1, ""))
A79: F-0025 | B79: Cuota Audifonos Samsung | C79: Otros | D79: 15 | E79: 50000 | F79: 50000 | G79: 2026-08-16 | H79: =IF(ISBLANK(A79),"",IF(N(F79)>=E79,"🟢 Pagado",IF(N(F79)>0,"🟡 Abono Parcial","🔴 Pendiente"))) -> 🟢 Pagado | I79: 2026-08-01 | J79: agosto | K79: 2026 | L79: Media | M79: Transferencia | N79: =IF(ISBLANK(A79),"",MAX(0, E79-N(F79))) -> 0 | P79: =IF(ISBLANK(A79), "", IF(AND(LOWER(TRIM(J79))=LOWER(TRIM(PANEL!$L$2)), K79=PANEL!$I$2), MAX($P$3:P78)+1, ""))
A80: F-0092 | B80: EPM ENERGIA | C80: Servicios | D80: 15 | E80: 120000 | F80: 120000 | G80: 46285 | H80: =IF(ISBLANK(A80),"",IF(N(F80)>=E80,"🟢 Pagado",IF(N(F80)>0,"🟡 Abono Parcial","🔴 Pendiente"))) -> 🟢 Pagado | I80: 2026-09-01 | J80: septiembre | K80: 2026 | L80: Media | M80: Transferencia | N80: =IF(ISBLANK(A80),"",MAX(0, E80-N(F80))) -> 0 | P80: =IF(ISBLANK(A80), "", IF(AND(LOWER(TRIM(J80))=LOWER(TRIM(PANEL!$L$2)), K80=PANEL!$I$2), MAX($P$3:P79)+1, ""))
A81: F-0093 | B81: COMIDA | C81: Alimentación | D81: 15 | E81: 850000 | F81: 650000 | G81: 15/09/2026 | H81: =IF(ISBLANK(A81),"",IF(N(F81)>=E81,"🟢 Pagado",IF(N(F81)>0,"🟡 Abono Parcial","🔴 Pendiente"))) -> 🟡 Abono Parcial | I81: 2026-09-01 | J81: septiembre | K81: 2026 | L81: Media | M81: Transferencia | N81: =IF(ISBLANK(A81),"",MAX(0, E81-N(F81))) -> 200000 | P81: =IF(ISBLANK(A81), "", IF(AND(LOWER(TRIM(J81))=LOWER(TRIM(PANEL!$L$2)), K81=PANEL!$I$2), MAX($P$3:P80)+1, ""))
A82: F-0094 | B82: Internet Tigo | C82: Servicios | D82: 15 | E82: 120000 | F82: 0 | H82: =IF(ISBLANK(A82),"",IF(N(F82)>=E82,"🟢 Pagado",IF(N(F82)>0,"🟡 Abono Parcial","🔴 Pendiente"))) -> 🔴 Pendiente | I82: 2026-09-01 | J82: septiembre | K82: 2026 | L82: Media | M82: Transferencia | N82: =IF(ISBLANK(A82),"",MAX(0, E82-N(F82))) -> 120000 | P82: =IF(ISBLANK(A82), "", IF(AND(LOWER(TRIM(J82))=LOWER(TRIM(PANEL!$L$2)), K82=PANEL!$I$2), MAX($P$3:P81)+1, ""))
A83: F-0095 | B83: Parqueadero Trabajo Semana | C83: Transporte | D83: 15 | E83: 40000 | F83: 8500 | G83: 46286 | H83: =IF(ISBLANK(A83),"",IF(N(F83)>=E83,"🟢 Pagado",IF(N(F83)>0,"🟡 Abono Parcial","🔴 Pendiente"))) -> 🟡 Abono Parcial | I83: 2026-09-01 | J83: septiembre | K83: 2026 | L83: Media | M83: Transferencia | N83: =IF(ISBLANK(A83),"",MAX(0, E83-N(F83))) -> 31500 | P83: =IF(ISBLANK(A83), "", IF(AND(LOWER(TRIM(J83))=LOWER(TRIM(PANEL!$L$2)), K83=PANEL!$I$2), MAX($P$3:P82)+1, ""))
A84: F-0096 | B84: Cuota Audifonos Samsung | C84: Otros | D84: 15 | E84: 50000 | F84: 60000 | G84: 15/09/2026 | H84: =IF(ISBLANK(A84),"",IF(N(F84)>=E84,"🟢 Pagado",IF(N(F84)>0,"🟡 Abono Parcial","🔴 Pendiente"))) -> 🟢 Pagado | I84: 2026-09-01 | J84: septiembre | K84: 2026 | L84: Media | M84: Transferencia | N84: =IF(ISBLANK(A84),"",MAX(0, E84-N(F84))) -> 0 | P84: =IF(ISBLANK(A84), "", IF(AND(LOWER(TRIM(J84))=LOWER(TRIM(PANEL!$L$2)), K84=PANEL!$I$2), MAX($P$3:P83)+1, ""))
A85: F-0097 | B85: PARQUEADERO MOTO | C85: Moto | D85: 15 | E85: 60000 | F85: 0 | H85: =IF(ISBLANK(A85),"",IF(N(F85)>=E85,"🟢 Pagado",IF(N(F85)>0,"🟡 Abono Parcial","🔴 Pendiente"))) -> 🔴 Pendiente | I85: 2026-09-01 | J85: septiembre | K85: 2026 | L85: Media | M85: Efectivo | N85: =IF(ISBLANK(A85),"",MAX(0, E85-N(F85))) -> 60000 | P85: =IF(ISBLANK(A85), "", IF(AND(LOWER(TRIM(J85))=LOWER(TRIM(PANEL!$L$2)), K85=PANEL!$I$2), MAX($P$3:P84)+1, ""))
A86: F-0098 | B86: Gasolina Moto | C86: Moto | D86: 15 | E86: 35000 | F86: 0 | H86: =IF(ISBLANK(A86),"",IF(N(F86)>=E86,"🟢 Pagado",IF(N(F86)>0,"🟡 Abono Parcial","🔴 Pendiente"))) -> 🔴 Pendiente | I86: 2026-09-01 | J86: septiembre | K86: 2026 | L86: Media | M86: Transferencia | N86: =IF(ISBLANK(A86),"",MAX(0, E86-N(F86))) -> 35000 | P86: =IF(ISBLANK(A86), "", IF(AND(LOWER(TRIM(J86))=LOWER(TRIM(PANEL!$L$2)), K86=PANEL!$I$2), MAX($P$3:P85)+1, ""))
A87: F-0099 | B87: Spotify | C87: Entretenimiento | D87: 15 | E87: 10000 | F87: 10000 | G87: 15/09/2026 | H87: =IF(ISBLANK(A87),"",IF(N(F87)>=E87,"🟢 Pagado",IF(N(F87)>0,"🟡 Abono Parcial","🔴 Pendiente"))) -> 🟢 Pagado | I87: 2026-09-01 | J87: septiembre | K87: 2026 | L87: Media | M87: Transferencia | N87: =IF(ISBLANK(A87),"",MAX(0, E87-N(F87))) -> 0 | P87: =IF(ISBLANK(A87), "", IF(AND(LOWER(TRIM(J87))=LOWER(TRIM(PANEL!$L$2)), K87=PANEL!$I$2), MAX($P$3:P86)+1, ""))
A88: F-0100 | B88: CUOTA DATOS CELULAR | C88: Servicios | D88: 15 | E88: 43900 | F88: 43900 | G88: 46297 | H88: =IF(ISBLANK(A88),"",IF(N(F88)>=E88,"🟢 Pagado",IF(N(F88)>0,"🟡 Abono Parcial","🔴 Pendiente"))) -> 🟢 Pagado | I88: 2026-09-01 | J88: septiembre | K88: 2026 | L88: Media | M88: Efectivo | N88: =IF(ISBLANK(A88),"",MAX(0, E88-N(F88))) -> 0 | P88: =IF(ISBLANK(A88), "", IF(AND(LOWER(TRIM(J88))=LOWER(TRIM(PANEL!$L$2)), K88=PANEL!$I$2), MAX($P$3:P87)+1, ""))
A89: F-0101 | B89: ARRIENDO CASA | C89: Vivienda | D89: 30 | E89: 900000 | F89: 900000 | G89: 46297 | H89: =IF(ISBLANK(A89),"",IF(N(F89)>=E89,"🟢 Pagado",IF(N(F89)>0,"🟡 Abono Parcial","🔴 Pendiente"))) -> 🟢 Pagado | I89: 2026-09-01 | J89: septiembre | K89: 2026 | L89: Media | M89: Efectivo | N89: =IF(ISBLANK(A89),"",MAX(0, E89-N(F89))) -> 0 | P89: =IF(ISBLANK(A89), "", IF(AND(LOWER(TRIM(J89))=LOWER(TRIM(PANEL!$L$2)), K89=PANEL!$I$2), MAX($P$3:P88)+1, ""))
A90: F-0102 | B90: Google One | C90: Servicios | D90: 30 | E90: 20000 | F90: 20000 | G90: 46285 | H90: =IF(ISBLANK(A90),"",IF(N(F90)>=E90,"🟢 Pagado",IF(N(F90)>0,"🟡 Abono Parcial","🔴 Pendiente"))) -> 🟢 Pagado | I90: 2026-09-01 | J90: septiembre | K90: 2026 | L90: Media | M90: Efectivo | N90: =IF(ISBLANK(A90),"",MAX(0, E90-N(F90))) -> 0 | P90: =IF(ISBLANK(A90), "", IF(AND(LOWER(TRIM(J90))=LOWER(TRIM(PANEL!$L$2)), K90=PANEL!$I$2), MAX($P$3:P89)+1, ""))
A91: F-0103 | B91: Gasolina Moto | C91: Moto | D91: 30 | E91: 25000 | F91: 0 | H91: =IF(ISBLANK(A91),"",IF(N(F91)>=E91,"🟢 Pagado",IF(N(F91)>0,"🟡 Abono Parcial","🔴 Pendiente"))) -> 🔴 Pendiente | I91: 2026-09-01 | J91: septiembre | K91: 2026 | L91: Media | M91: Efectivo | N91: =IF(ISBLANK(A91),"",MAX(0, E91-N(F91))) -> 25000 | P91: =IF(ISBLANK(A91), "", IF(AND(LOWER(TRIM(J91))=LOWER(TRIM(PANEL!$L$2)), K91=PANEL!$I$2), MAX($P$3:P90)+1, ""))
A92: F-0104 | B92: Parqueadero Trabajo Semana | C92: Transporte | D92: 30 | E92: 40000 | F92: 0 | H92: =IF(ISBLANK(A92),"",IF(N(F92)>=E92,"🟢 Pagado",IF(N(F92)>0,"🟡 Abono Parcial","🔴 Pendiente"))) -> 🔴 Pendiente | I92: 2026-09-01 | J92: septiembre | K92: 2026 | L92: Media | M92: Efectivo | N92: =IF(ISBLANK(A92),"",MAX(0, E92-N(F92))) -> 40000 | P92: =IF(ISBLANK(A92), "", IF(AND(LOWER(TRIM(J92))=LOWER(TRIM(PANEL!$L$2)), K92=PANEL!$I$2), MAX($P$3:P91)+1, ""))
A93: F-0105 | B93: COMIDA | C93: Alimentación | D93: 30 | E93: 200000 | F93: 0 | H93: =IF(ISBLANK(A93),"",IF(N(F93)>=E93,"🟢 Pagado",IF(N(F93)>0,"🟡 Abono Parcial","🔴 Pendiente"))) -> 🔴 Pendiente | I93: 2026-09-01 | J93: septiembre | K93: 2026 | L93: Media | M93: Efectivo | N93: =IF(ISBLANK(A93),"",MAX(0, E93-N(F93))) -> 200000 | P93: =IF(ISBLANK(A93), "", IF(AND(LOWER(TRIM(J93))=LOWER(TRIM(PANEL!$L$2)), K93=PANEL!$I$2), MAX($P$3:P92)+1, ""))
A94: F-0106 | B94: PARQUEADERO MOTO | C94: Moto | D94: 30 | E94: 40000 | F94: 0 | H94: =IF(ISBLANK(A94),"",IF(N(F94)>=E94,"🟢 Pagado",IF(N(F94)>0,"🟡 Abono Parcial","🔴 Pendiente"))) -> 🔴 Pendiente | I94: 2026-09-01 | J94: septiembre | K94: 2026 | L94: Media | M94: Efectivo | N94: =IF(ISBLANK(A94),"",MAX(0, E94-N(F94))) -> 40000 | P94: =IF(ISBLANK(A94), "", IF(AND(LOWER(TRIM(J94))=LOWER(TRIM(PANEL!$L$2)), K94=PANEL!$I$2), MAX($P$3:P93)+1, ""))
A95: F-0107 | B95: EPM ENERGIA | C95: Servicios | D95: 15 | E95: 177000 | F95: 0 | H95: =IF(ISBLANK(A95),"",IF(N(F95)>=E95,"🟢 Pagado",IF(N(F95)>0,"🟡 Abono Parcial","🔴 Pendiente"))) -> 🔴 Pendiente | I95: 2026-10-01 | J95: octubre | K95: 2026 | L95: Media | M95: Transferencia | N95: =IF(ISBLANK(A95),"",MAX(0, E95-N(F95))) -> 177000 | P95: =IF(ISBLANK(A95), "", IF(AND(LOWER(TRIM(J95))=LOWER(TRIM(PANEL!$L$2)), K95=PANEL!$I$2), MAX($P$3:P94)+1, "")) -> 1
A96: F-0108 | B96: COMIDA | C96: Alimentación | D96: 15 | E96: 850000 | F96: 0 | H96: =IF(ISBLANK(A96),"",IF(N(F96)>=E96,"🟢 Pagado",IF(N(F96)>0,"🟡 Abono Parcial","🔴 Pendiente"))) -> 🔴 Pendiente | I96: 2026-10-01 | J96: octubre | K96: 2026 | L96: Media | M96: Transferencia | N96: =IF(ISBLANK(A96),"",MAX(0, E96-N(F96))) -> 850000 | P96: =IF(ISBLANK(A96), "", IF(AND(LOWER(TRIM(J96))=LOWER(TRIM(PANEL!$L$2)), K96=PANEL!$I$2), MAX($P$3:P95)+1, "")) -> 2
A97: F-0109 | B97: Internet Tigo | C97: Servicios | D97: 15 | E97: 120000 | F97: 0 | H97: =IF(ISBLANK(A97),"",IF(N(F97)>=E97,"🟢 Pagado",IF(N(F97)>0,"🟡 Abono Parcial","🔴 Pendiente"))) -> 🔴 Pendiente | I97: 2026-10-01 | J97: octubre | K97: 2026 | L97: Media | M97: Transferencia | N97: =IF(ISBLANK(A97),"",MAX(0, E97-N(F97))) -> 120000 | P97: =IF(ISBLANK(A97), "", IF(AND(LOWER(TRIM(J97))=LOWER(TRIM(PANEL!$L$2)), K97=PANEL!$I$2), MAX($P$3:P96)+1, "")) -> 3
A98: F-0110 | B98: Parqueadero Trabajo Semana | C98: Transporte | D98: 15 | E98: 40000 | F98: 0 | H98: =IF(ISBLANK(A98),"",IF(N(F98)>=E98,"🟢 Pagado",IF(N(F98)>0,"🟡 Abono Parcial","🔴 Pendiente"))) -> 🔴 Pendiente | I98: 2026-10-01 | J98: octubre | K98: 2026 | L98: Media | M98: Transferencia | N98: =IF(ISBLANK(A98),"",MAX(0, E98-N(F98))) -> 40000 | P98: =IF(ISBLANK(A98), "", IF(AND(LOWER(TRIM(J98))=LOWER(TRIM(PANEL!$L$2)), K98=PANEL!$I$2), MAX($P$3:P97)+1, "")) -> 4
A99: F-0111 | B99: Cuota Audifonos Samsung | C99: Otros | D99: 15 | E99: 50000 | F99: 0 | H99: =IF(ISBLANK(A99),"",IF(N(F99)>=E99,"🟢 Pagado",IF(N(F99)>0,"🟡 Abono Parcial","🔴 Pendiente"))) -> 🔴 Pendiente | I99: 2026-10-01 | J99: octubre | K99: 2026 | L99: Media | M99: Transferencia | N99: =IF(ISBLANK(A99),"",MAX(0, E99-N(F99))) -> 50000 | P99: =IF(ISBLANK(A99), "", IF(AND(LOWER(TRIM(J99))=LOWER(TRIM(PANEL!$L$2)), K99=PANEL!$I$2), MAX($P$3:P98)+1, "")) -> 5
A100: F-0112 | B100: PARQUEADERO MOTO | C100: Moto | D100: 15 | E100: 60000 | F100: 0 | H100: =IF(ISBLANK(A100),"",IF(N(F100)>=E100,"🟢 Pagado",IF(N(F100)>0,"🟡 Abono Parcial","🔴 Pendiente"))) -> 🔴 Pendiente | I100: 2026-10-01 | J100: octubre | K100: 2026 | L100: Media | M100: Efectivo | N100: =IF(ISBLANK(A100),"",MAX(0, E100-N(F100))) -> 60000 | P100: =IF(ISBLANK(A100), "", IF(AND(LOWER(TRIM(J100))=LOWER(TRIM(PANEL!$L$2)), K100=PANEL!$I$2), MAX($P$3:P99)+1, "")) -> 6
A101: F-0113 | B101: Gasolina Moto | C101: Moto | D101: 15 | E101: 35000 | F101: 0 | H101: =IF(ISBLANK(A101),"",IF(N(F101)>=E101,"🟢 Pagado",IF(N(F101)>0,"🟡 Abono Parcial","🔴 Pendiente"))) -> 🔴 Pendiente | I101: 2026-10-01 | J101: octubre | K101: 2026 | L101: Media | M101: Transferencia | N101: =IF(ISBLANK(A101),"",MAX(0, E101-N(F101))) -> 35000 | P101: =IF(ISBLANK(A101), "", IF(AND(LOWER(TRIM(J101))=LOWER(TRIM(PANEL!$L$2)), K101=PANEL!$I$2), MAX($P$3:P100)+1, "")) -> 7
A102: F-0114 | B102: Spotify | C102: Entretenimiento | D102: 15 | E102: 10100 | F102: 10100 | G102: 46310 | H102: =IF(ISBLANK(A102),"",IF(N(F102)>=E102,"🟢 Pagado",IF(N(F102)>0,"🟡 Abono Parcial","🔴 Pendiente"))) -> 🟢 Pagado | I102: 2026-10-01 | J102: octubre | K102: 2026 | L102: Media | M102: Tarjeta Nequi | N102: =IF(ISBLANK(A102),"",MAX(0, E102-N(F102))) -> 0 | O102: Renovación automática Google Play GPA.3333-4099-9556-15284..13 | P102: =IF(ISBLANK(A102), "", IF(AND(LOWER(TRIM(J102))=LOWER(TRIM(PANEL!$L$2)), K102=PANEL!$I$2), MAX($P$3:P101)+1, "")) -> 8
A103: F-0115 | B103: CUOTA DATOS CELULAR | C103: Servicios | D103: 15 | E103: 43900 | F103: 43900 | G103: 46297 | H103: =IF(ISBLANK(A103),"",IF(N(F103)>=E103,"🟢 Pagado",IF(N(F103)>0,"🟡 Abono Parcial","🔴 Pendiente"))) -> 🟢 Pagado | I103: 2026-10-01 | J103: octubre | K103: 2026 | L103: Media | M103: Efectivo | N103: =IF(ISBLANK(A103),"",MAX(0, E103-N(F103))) -> 0 | P103: =IF(ISBLANK(A103), "", IF(AND(LOWER(TRIM(J103))=LOWER(TRIM(PANEL!$L$2)), K103=PANEL!$I$2), MAX($P$3:P102)+1, "")) -> 9
A104: F-0116 | B104: ARRIENDO CASA | C104: Vivienda | D104: 30 | E104: 900000 | F104: 0 | H104: =IF(ISBLANK(A104),"",IF(N(F104)>=E104,"🟢 Pagado",IF(N(F104)>0,"🟡 Abono Parcial","🔴 Pendiente"))) -> 🔴 Pendiente | I104: 2026-10-01 | J104: octubre | K104: 2026 | L104: Media | M104: Efectivo | N104: =IF(ISBLANK(A104),"",MAX(0, E104-N(F104))) -> 900000 | P104: =IF(ISBLANK(A104), "", IF(AND(LOWER(TRIM(J104))=LOWER(TRIM(PANEL!$L$2)), K104=PANEL!$I$2), MAX($P$3:P103)+1, "")) -> 10
A105: F-0117 | B105: Google One | C105: Servicios | D105: 30 | E105: 20000 | F105: 0 | H105: =IF(ISBLANK(A105),"",IF(N(F105)>=E105,"🟢 Pagado",IF(N(F105)>0,"🟡 Abono Parcial","🔴 Pendiente"))) -> 🔴 Pendiente | I105: 2026-10-01 | J105: octubre | K105: 2026 | L105: Media | M105: Efectivo | N105: =IF(ISBLANK(A105),"",MAX(0, E105-N(F105))) -> 20000 | P105: =IF(ISBLANK(A105), "", IF(AND(LOWER(TRIM(J105))=LOWER(TRIM(PANEL!$L$2)), K105=PANEL!$I$2), MAX($P$3:P104)+1, "")) -> 11
A106: F-0118 | B106: Gasolina Moto | C106: Moto | D106: 30 | E106: 25000 | F106: 0 | H106: =IF(ISBLANK(A106),"",IF(N(F106)>=E106,"🟢 Pagado",IF(N(F106)>0,"🟡 Abono Parcial","🔴 Pendiente"))) -> 🔴 Pendiente | I106: 2026-10-01 | J106: octubre | K106: 2026 | L106: Media | M106: Efectivo | N106: =IF(ISBLANK(A106),"",MAX(0, E106-N(F106))) -> 25000 | P106: =IF(ISBLANK(A106), "", IF(AND(LOWER(TRIM(J106))=LOWER(TRIM(PANEL!$L$2)), K106=PANEL!$I$2), MAX($P$3:P105)+1, "")) -> 12
A107: F-0119 | B107: Parqueadero Trabajo Semana | C107: Transporte | D107: 30 | E107: 40000 | F107: 0 | H107: =IF(ISBLANK(A107),"",IF(N(F107)>=E107,"🟢 Pagado",IF(N(F107)>0,"🟡 Abono Parcial","🔴 Pendiente"))) -> 🔴 Pendiente | I107: 2026-10-01 | J107: octubre | K107: 2026 | L107: Media | M107: Efectivo | N107: =IF(ISBLANK(A107),"",MAX(0, E107-N(F107))) -> 40000 | P107: =IF(ISBLANK(A107), "", IF(AND(LOWER(TRIM(J107))=LOWER(TRIM(PANEL!$L$2)), K107=PANEL!$I$2), MAX($P$3:P106)+1, "")) -> 13
A108: F-0120 | B108: COMIDA | C108: Alimentación | D108: 30 | E108: 200000 | F108: 0 | H108: =IF(ISBLANK(A108),"",IF(N(F108)>=E108,"🟢 Pagado",IF(N(F108)>0,"🟡 Abono Parcial","🔴 Pendiente"))) -> 🔴 Pendiente | I108: 2026-10-01 | J108: octubre | K108: 2026 | L108: Media | M108: Efectivo | N108: =IF(ISBLANK(A108),"",MAX(0, E108-N(F108))) -> 200000 | P108: =IF(ISBLANK(A108), "", IF(AND(LOWER(TRIM(J108))=LOWER(TRIM(PANEL!$L$2)), K108=PANEL!$I$2), MAX($P$3:P107)+1, "")) -> 14
A109: F-0121 | B109: PARQUEADERO MOTO | C109: Moto | D109: 30 | E109: 40000 | F109: 0 | H109: =IF(ISBLANK(A109),"",IF(N(F109)>=E109,"🟢 Pagado",IF(N(F109)>0,"🟡 Abono Parcial","🔴 Pendiente"))) -> 🔴 Pendiente | I109: 2026-10-01 | J109: octubre | K109: 2026 | L109: Media | M109: Efectivo | N109: =IF(ISBLANK(A109),"",MAX(0, E109-N(F109))) -> 40000 | P109: =IF(ISBLANK(A109), "", IF(AND(LOWER(TRIM(J109))=LOWER(TRIM(PANEL!$L$2)), K109=PANEL!$I$2), MAX($P$3:P108)+1, "")) -> 15
A110: F-0122 | B110: EPM ENERGIA | C110: Servicios | D110: 15 | E110: 177000 | F110: 0 | H110: =IF(ISBLANK(A110),"",IF(N(F110)>=E110,"🟢 Pagado",IF(N(F110)>0,"🟡 Abono Parcial","🔴 Pendiente"))) -> 🔴 Pendiente | I110: 2026-11-01 | J110: noviembre | K110: 2026 | L110: Media | M110: Transferencia | N110: =IF(ISBLANK(A110),"",MAX(0, E110-N(F110))) -> 177000 | P110: =IF(ISBLANK(A110), "", IF(AND(LOWER(TRIM(J110))=LOWER(TRIM(PANEL!$L$2)), K110=PANEL!$I$2), MAX($P$3:P109)+1, ""))
A111: F-0123 | B111: COMIDA | C111: Alimentación | D111: 15 | E111: 850000 | F111: 0 | H111: =IF(ISBLANK(A111),"",IF(N(F111)>=E111,"🟢 Pagado",IF(N(F111)>0,"🟡 Abono Parcial","🔴 Pendiente"))) -> 🔴 Pendiente | I111: 2026-11-01 | J111: noviembre | K111: 2026 | L111: Media | M111: Transferencia | N111: =IF(ISBLANK(A111),"",MAX(0, E111-N(F111))) -> 850000 | P111: =IF(ISBLANK(A111), "", IF(AND(LOWER(TRIM(J111))=LOWER(TRIM(PANEL!$L$2)), K111=PANEL!$I$2), MAX($P$3:P110)+1, ""))
A112: F-0124 | B112: Internet Tigo | C112: Servicios | D112: 15 | E112: 120000 | F112: 0 | H112: =IF(ISBLANK(A112),"",IF(N(F112)>=E112,"🟢 Pagado",IF(N(F112)>0,"🟡 Abono Parcial","🔴 Pendiente"))) -> 🔴 Pendiente | I112: 2026-11-01 | J112: noviembre | K112: 2026 | L112: Media | M112: Transferencia | N112: =IF(ISBLANK(A112),"",MAX(0, E112-N(F112))) -> 120000 | P112: =IF(ISBLANK(A112), "", IF(AND(LOWER(TRIM(J112))=LOWER(TRIM(PANEL!$L$2)), K112=PANEL!$I$2), MAX($P$3:P111)+1, ""))
A113: F-0125 | B113: Parqueadero Trabajo Semana | C113: Transporte | D113: 15 | E113: 40000 | F113: 0 | H113: =IF(ISBLANK(A113),"",IF(N(F113)>=E113,"🟢 Pagado",IF(N(F113)>0,"🟡 Abono Parcial","🔴 Pendiente"))) -> 🔴 Pendiente | I113: 2026-11-01 | J113: noviembre | K113: 2026 | L113: Media | M113: Transferencia | N113: =IF(ISBLANK(A113),"",MAX(0, E113-N(F113))) -> 40000 | P113: =IF(ISBLANK(A113), "", IF(AND(LOWER(TRIM(J113))=LOWER(TRIM(PANEL!$L$2)), K113=PANEL!$I$2), MAX($P$3:P112)+1, ""))
A114: F-0126 | B114: Cuota Audifonos Samsung | C114: Otros | D114: 15 | E114: 50000 | F114: 0 | H114: =IF(ISBLANK(A114),"",IF(N(F114)>=E114,"🟢 Pagado",IF(N(F114)>0,"🟡 Abono Parcial","🔴 Pendiente"))) -> 🔴 Pendiente | I114: 2026-11-01 | J114: noviembre | K114: 2026 | L114: Media | M114: Transferencia | N114: =IF(ISBLANK(A114),"",MAX(0, E114-N(F114))) -> 50000 | P114: =IF(ISBLANK(A114), "", IF(AND(LOWER(TRIM(J114))=LOWER(TRIM(PANEL!$L$2)), K114=PANEL!$I$2), MAX($P$3:P113)+1, ""))
A115: F-0127 | B115: PARQUEADERO MOTO | C115: Moto | D115: 15 | E115: 60000 | F115: 0 | H115: =IF(ISBLANK(A115),"",IF(N(F115)>=E115,"🟢 Pagado",IF(N(F115)>0,"🟡 Abono Parcial","🔴 Pendiente"))) -> 🔴 Pendiente | I115: 2026-11-01 | J115: noviembre | K115: 2026 | L115: Media | M115: Efectivo | N115: =IF(ISBLANK(A115),"",MAX(0, E115-N(F115))) -> 60000 | P115: =IF(ISBLANK(A115), "", IF(AND(LOWER(TRIM(J115))=LOWER(TRIM(PANEL!$L$2)), K115=PANEL!$I$2), MAX($P$3:P114)+1, ""))
... A189: F-0201 | B189: Cuota Audifonos Samsung | C189: Otros | D189: 15 | E189: 50000 | F189: 0 | H189: =IF(ISBLANK(A189),"",IF(N(F189)>=E189,"🟢 Pagado",IF(N(F189)>0,"🟡 Abono Parcial","🔴 Pendiente"))) -> 🔴 Pendiente | I189: 2027-04-01 | J189: abril | K189: 2027 | L189: Media | M189: Transferencia | N189: =IF(ISBLANK(A189),"",MAX(0, E189-N(F189))) -> 50000 | P189: =IF(ISBLANK(A189), "", IF(AND(LOWER(TRIM(J189))=LOWER(TRIM(PANEL!$L$2)), K189=PANEL!$I$2), MAX($P$3:P188)+1, ""))
H190: =IF(ISBLANK(A190),"",IF(N(F190)>=E190,"🟢 Pagado",IF(N(F190)>0,"🟡 Abono Parcial","🔴 Pendiente"))) | N190: =IF(ISBLANK(A190),"",MAX(0, E190-N(F190))) | P190: =IF(ISBLANK(A190), "", IF(AND(LOWER(TRIM(J190))=LOWER(TRIM(PANEL!$L$2)), K190=PANEL!$I$2), MAX($P$3:P189)+1, ""))
H191: =IF(ISBLANK(A191),"",IF(N(F191)>=E191,"🟢 Pagado",IF(N(F191)>0,"🟡 Abono Parcial","🔴 Pendiente"))) | N191: =IF(ISBLANK(A191),"",MAX(0, E191-N(F191))) | P191: =IF(ISBLANK(A191), "", IF(AND(LOWER(TRIM(J191))=LOWER(TRIM(PANEL!$L$2)), K191=PANEL!$I$2), MAX($P$3:P190)+1, ""))
H192: =IF(ISBLANK(A192),"",IF(N(F192)>=E192,"🟢 Pagado",IF(N(F192)>0,"🟡 Abono Parcial","🔴 Pendiente"))) | N192: =IF(ISBLANK(A192),"",MAX(0, E192-N(F192))) | P192: =IF(ISBLANK(A192), "", IF(AND(LOWER(TRIM(J192))=LOWER(TRIM(PANEL!$L$2)), K192=PANEL!$I$2), MAX($P$3:P191)+1, ""))
H193: =IF(ISBLANK(A193),"",IF(N(F193)>=E193,"🟢 Pagado",IF(N(F193)>0,"🟡 Abono Parcial","🔴 Pendiente"))) | N193: =IF(ISBLANK(A193),"",MAX(0, E193-N(F193))) | P193: =IF(ISBLANK(A193), "", IF(AND(LOWER(TRIM(J193))=LOWER(TRIM(PANEL!$L$2)), K193=PANEL!$I$2), MAX($P$3:P192)+1, ""))
H194: =IF(ISBLANK(A194),"",IF(N(F194)>=E194,"🟢 Pagado",IF(N(F194)>0,"🟡 Abono Parcial","🔴 Pendiente"))) | N194: =IF(ISBLANK(A194),"",MAX(0, E194-N(F194))) | P194: =IF(ISBLANK(A194), "", IF(AND(LOWER(TRIM(J194))=LOWER(TRIM(PANEL!$L$2)), K194=PANEL!$I$2), MAX($P$3:P193)+1, ""))
H195: =IF(ISBLANK(A195),"",IF(N(F195)>=E195,"🟢 Pagado",IF(N(F195)>0,"🟡 Abono Parcial","🔴 Pendiente"))) | N195: =IF(ISBLANK(A195),"",MAX(0, E195-N(F195))) | P195: =IF(ISBLANK(A195), "", IF(AND(LOWER(TRIM(J195))=LOWER(TRIM(PANEL!$L$2)), K195=PANEL!$I$2), MAX($P$3:P194)+1, ""))
H196: =IF(ISBLANK(A196),"",IF(N(F196)>=E196,"🟢 Pagado",IF(N(F196)>0,"🟡 Abono Parcial","🔴 Pendiente"))) | N196: =IF(ISBLANK(A196),"",MAX(0, E196-N(F196))) | P196: =IF(ISBLANK(A196), "", IF(AND(LOWER(TRIM(J196))=LOWER(TRIM(PANEL!$L$2)), K196=PANEL!$I$2), MAX($P$3:P195)+1, ""))
H197: =IF(ISBLANK(A197),"",IF(N(F197)>=E197,"🟢 Pagado",IF(N(F197)>0,"🟡 Abono Parcial","🔴 Pendiente"))) | N197: =IF(ISBLANK(A197),"",MAX(0, E197-N(F197))) | P197: =IF(ISBLANK(A197), "", IF(AND(LOWER(TRIM(J197))=LOWER(TRIM(PANEL!$L$2)), K197=PANEL!$I$2), MAX($P$3:P196)+1, ""))
H198: =IF(ISBLANK(A198),"",IF(N(F198)>=E198,"🟢 Pagado",IF(N(F198)>0,"🟡 Abono Parcial","🔴 Pendiente"))) | N198: =IF(ISBLANK(A198),"",MAX(0, E198-N(F198))) | P198: =IF(ISBLANK(A198), "", IF(AND(LOWER(TRIM(J198))=LOWER(TRIM(PANEL!$L$2)), K198=PANEL!$I$2), MAX($P$3:P197)+1, ""))
H199: =IF(ISBLANK(A199),"",IF(N(F199)>=E199,"🟢 Pagado",IF(N(F199)>0,"🟡 Abono Parcial","🔴 Pendiente"))) | N199: =IF(ISBLANK(A199),"",MAX(0, E199-N(F199))) | P199: =IF(ISBLANK(A199), "", IF(AND(LOWER(TRIM(J199))=LOWER(TRIM(PANEL!$L$2)), K199=PANEL!$I$2), MAX($P$3:P198)+1, ""))
H200: =IF(ISBLANK(A200),"",IF(N(F200)>=E200,"🟢 Pagado",IF(N(F200)>0,"🟡 Abono Parcial","🔴 Pendiente"))) | N200: =IF(ISBLANK(A200),"",MAX(0, E200-N(F200))) | P200: =IF(ISBLANK(A200), "", IF(AND(LOWER(TRIM(J200))=LOWER(TRIM(PANEL!$L$2)), K200=PANEL!$I$2), MAX($P$3:P199)+1, ""))
H201: =IF(ISBLANK(A201),"",IF(N(F201)>=E201,"🟢 Pagado",IF(N(F201)>0,"🟡 Abono Parcial","🔴 Pendiente"))) | N201: =IF(ISBLANK(A201),"",MAX(0, E201-N(F201))) | P201: =IF(ISBLANK(A201), "", IF(AND(LOWER(TRIM(J201))=LOWER(TRIM(PANEL!$L$2)), K201=PANEL!$I$2), MAX($P$3:P200)+1, ""))
... H204: =IF(ISBLANK(A204),"",IF(N(F204)>=E204,"🟢 Pagado",IF(N(F204)>0,"🟡 Abono Parcial","🔴 Pendiente"))) | N204: =IF(ISBLANK(A204),"",MAX(0, E204-N(F204))) | P204: =IF(ISBLANK(A204), "", IF(AND(LOWER(TRIM(J204))=LOWER(TRIM(PANEL!$L$2)), K204=PANEL!$I$2), MAX($P$3:P203)+1, ""))

Sheet METAS AHORRO
A1: 🎯 GESTOR DE METAS DE AHORRO Y PROYECTOS FINANCIEROS
A2: Seguimiento de objetivos financieros, capital abonado, saldo restante y progreso porcentual
A4: META CONSOLIDADA ($) | C4: AHORRO ACUMULADO ($) | E4: FALTANTE TOTAL ($) | G4: % AVANCE GLOBAL
A5: =SUM(C10:C25) -> 0 | C5: =SUM(D10:D25) -> 0 | E5: =SUM(E10:E25) -> 0 | G5: =IF(A5=0, 0, C5/A5) -> 0
A9: ID | B9: Objetivo / Proyecto | C9: Meta Financiera ($) | D9: Ahorro Actual ($) | E9: Faltante ($) | F9: % Avance | G9: Barra Progreso | H9: Estado | I9: Fecha Estimada | J9: Origen / Cuenta
E10: =IF(A10="", "", MAX(0, C10-D10)) | F10: =IF(OR(A10="", C10=0), "", MIN(1, D10/C10)) | G10: =IF(A10="", "", REPT("█", ROUND(N(F10)*10, 0)) & REPT("░", 10-ROUND(N(F10)*10, 0))) | H10: =IF(A10="", "", IF(D10>=C10, "🟢 Cumplida", IF(D10>0, "🟡 En Progreso", "🔴 No Iniciada")))
E11: =IF(A11="", "", MAX(0, C11-D11)) | F11: =IF(OR(A11="", C11=0), "", MIN(1, D11/C11)) | G11: =IF(A11="", "", REPT("█", ROUND(N(F11)*10, 0)) & REPT("░", 10-ROUND(N(F11)*10, 0))) | H11: =IF(A11="", "", IF(D11>=C11, "🟢 Cumplida", IF(D11>0, "🟡 En Progreso", "🔴 No Iniciada")))
E12: =IF(A12="", "", MAX(0, C12-D12)) | F12: =IF(OR(A12="", C12=0), "", MIN(1, D12/C12)) | G12: =IF(A12="", "", REPT("█", ROUND(N(F12)*10, 0)) & REPT("░", 10-ROUND(N(F12)*10, 0))) | H12: =IF(A12="", "", IF(D12>=C12, "🟢 Cumplida", IF(D12>0, "🟡 En Progreso", "🔴 No Iniciada")))
E13: =IF(A13="", "", MAX(0, C13-D13)) | F13: =IF(OR(A13="", C13=0), "", MIN(1, D13/C13)) | G13: =IF(A13="", "", REPT("█", ROUND(N(F13)*10, 0)) & REPT("░", 10-ROUND(N(F13)*10, 0))) | H13: =IF(A13="", "", IF(D13>=C13, "🟢 Cumplida", IF(D13>0, "🟡 En Progreso", "🔴 No Iniciada")))
E14: =IF(A14="", "", MAX(0, C14-D14)) | F14: =IF(OR(A14="", C14=0), "", MIN(1, D14/C14)) | G14: =IF(A14="", "", REPT("█", ROUND(N(F14)*10, 0)) & REPT("░", 10-ROUND(N(F14)*10, 0))) | H14: =IF(A14="", "", IF(D14>=C14, "🟢 Cumplida", IF(D14>0, "🟡 En Progreso", "🔴 No Iniciada")))
E15: =IF(A15="", "", MAX(0, C15-D15)) | F15: =IF(OR(A15="", C15=0), "", MIN(1, D15/C15)) | G15: =IF(A15="", "", REPT("█", ROUND(N(F15)*10, 0)) & REPT("░", 10-ROUND(N(F15)*10, 0))) | H15: =IF(A15="", "", IF(D15>=C15, "🟢 Cumplida", IF(D15>0, "🟡 En Progreso", "🔴 No Iniciada")))
E16: =IF(A16="", "", MAX(0, C16-D16)) | F16: =IF(OR(A16="", C16=0), "", MIN(1, D16/C16)) | G16: =IF(A16="", "", REPT("█", ROUND(N(F16)*10, 0)) & REPT("░", 10-ROUND(N(F16)*10, 0))) | H16: =IF(A16="", "", IF(D16>=C16, "🟢 Cumplida", IF(D16>0, "🟡 En Progreso", "🔴 No Iniciada")))
E17: =IF(A17="", "", MAX(0, C17-D17)) | F17: =IF(OR(A17="", C17=0), "", MIN(1, D17/C17)) | G17: =IF(A17="", "", REPT("█", ROUND(N(F17)*10, 0)) & REPT("░", 10-ROUND(N(F17)*10, 0))) | H17: =IF(A17="", "", IF(D17>=C17, "🟢 Cumplida", IF(D17>0, "🟡 En Progreso", "🔴 No Iniciada")))
E18: =IF(A18="", "", MAX(0, C18-D18)) | F18: =IF(OR(A18="", C18=0), "", MIN(1, D18/C18)) | G18: =IF(A18="", "", REPT("█", ROUND(N(F18)*10, 0)) & REPT("░", 10-ROUND(N(F18)*10, 0))) | H18: =IF(A18="", "", IF(D18>=C18, "🟢 Cumplida", IF(D18>0, "🟡 En Progreso", "🔴 No Iniciada")))
E19: =IF(A19="", "", MAX(0, C19-D19)) | F19: =IF(OR(A19="", C19=0), "", MIN(1, D19/C19)) | G19: =IF(A19="", "", REPT("█", ROUND(N(F19)*10, 0)) & REPT("░", 10-ROUND(N(F19)*10, 0))) | H19: =IF(A19="", "", IF(D19>=C19, "🟢 Cumplida", IF(D19>0, "🟡 En Progreso", "🔴 No Iniciada")))
E20: =IF(A20="", "", MAX(0, C20-D20)) | F20: =IF(OR(A20="", C20=0), "", MIN(1, D20/C20)) | G20: =IF(A20="", "", REPT("█", ROUND(N(F20)*10, 0)) & REPT("░", 10-ROUND(N(F20)*10, 0))) | H20: =IF(A20="", "", IF(D20>=C20, "🟢 Cumplida", IF(D20>0, "🟡 En Progreso", "🔴 No Iniciada")))
E21: =IF(A21="", "", MAX(0, C21-D21)) | F21: =IF(OR(A21="", C21=0), "", MIN(1, D21/C21)) | G21: =IF(A21="", "", REPT("█", ROUND(N(F21)*10, 0)) & REPT("░", 10-ROUND(N(F21)*10, 0))) | H21: =IF(A21="", "", IF(D21>=C21, "🟢 Cumplida", IF(D21>0, "🟡 En Progreso", "🔴 No Iniciada")))
... E24: =IF(A24="", "", MAX(0, C24-D24)) | F24: =IF(OR(A24="", C24=0), "", MIN(1, D24/C24)) | G24: =IF(A24="", "", REPT("█", ROUND(N(F24)*10, 0)) & REPT("░", 10-ROUND(N(F24)*10, 0))) | H24: =IF(A24="", "", IF(D24>=C24, "🟢 Cumplida", IF(D24>0, "🟡 En Progreso", "🔴 No Iniciada")))

Sheet CUENTAS POR COBRAR
A1: 🤝 CONTROL DE PRÉSTAMOS Y CARTERA POR COBRAR
A2: Control de préstamos a terceros, abonos recibidos y saldos pendientes por recaudar
A4: TOTAL PRESTADO ($) | C4: TOTAL RECUPERADO ($) | E4: SALDO PENDIENTE EN LA CALLE | H4: DEUDORES CON SALDO
A5: =SUM(E10:E34) -> 0 | C5: =SUM(F10:F34) -> 0 | E5: =SUM(G10:G34) -> 0 | H5: =COUNTIF(G10:G34, ">0") -> 0
A9: ID | B9: Fecha Préstamo | C9: Deudor / Persona | D9: Concepto / Motivo | E9: Monto Prestado ($) | F9: Abonado ($) | G9: Saldo Pendiente ($) | H9: Estado | I9: Fecha Último Abono | J9: Notas / Ref. Movimiento
G10: =IF(ISBLANK(A10), "", MAX(0, E10-N(F10))) | H10: =IF(ISBLANK(A10), "", IF(G10<=0, "🟢 Cobrado Total", IF(N(F10)>0, "🟡 Parcial", "🔴 Pendiente")))
G11: =IF(ISBLANK(A11), "", MAX(0, E11-N(F11))) | H11: =IF(ISBLANK(A11), "", IF(G11<=0, "🟢 Cobrado Total", IF(N(F11)>0, "🟡 Parcial", "🔴 Pendiente")))
G12: =IF(ISBLANK(A12), "", MAX(0, E12-N(F12))) | H12: =IF(ISBLANK(A12), "", IF(G12<=0, "🟢 Cobrado Total", IF(N(F12)>0, "🟡 Parcial", "🔴 Pendiente")))
G13: =IF(ISBLANK(A13), "", MAX(0, E13-N(F13))) | H13: =IF(ISBLANK(A13), "", IF(G13<=0, "🟢 Cobrado Total", IF(N(F13)>0, "🟡 Parcial", "🔴 Pendiente")))
G14: =IF(ISBLANK(A14), "", MAX(0, E14-N(F14))) | H14: =IF(ISBLANK(A14), "", IF(G14<=0, "🟢 Cobrado Total", IF(N(F14)>0, "🟡 Parcial", "🔴 Pendiente")))
G15: =IF(ISBLANK(A15), "", MAX(0, E15-N(F15))) | H15: =IF(ISBLANK(A15), "", IF(G15<=0, "🟢 Cobrado Total", IF(N(F15)>0, "🟡 Parcial", "🔴 Pendiente")))
G16: =IF(ISBLANK(A16), "", MAX(0, E16-N(F16))) | H16: =IF(ISBLANK(A16), "", IF(G16<=0, "🟢 Cobrado Total", IF(N(F16)>0, "🟡 Parcial", "🔴 Pendiente")))
G17: =IF(ISBLANK(A17), "", MAX(0, E17-N(F17))) | H17: =IF(ISBLANK(A17), "", IF(G17<=0, "🟢 Cobrado Total", IF(N(F17)>0, "🟡 Parcial", "🔴 Pendiente")))
G18: =IF(ISBLANK(A18), "", MAX(0, E18-N(F18))) | H18: =IF(ISBLANK(A18), "", IF(G18<=0, "🟢 Cobrado Total", IF(N(F18)>0, "🟡 Parcial", "🔴 Pendiente")))
G19: =IF(ISBLANK(A19), "", MAX(0, E19-N(F19))) | H19: =IF(ISBLANK(A19), "", IF(G19<=0, "🟢 Cobrado Total", IF(N(F19)>0, "🟡 Parcial", "🔴 Pendiente")))
G20: =IF(ISBLANK(A20), "", MAX(0, E20-N(F20))) | H20: =IF(ISBLANK(A20), "", IF(G20<=0, "🟢 Cobrado Total", IF(N(F20)>0, "🟡 Parcial", "🔴 Pendiente")))
G21: =IF(ISBLANK(A21), "", MAX(0, E21-N(F21))) | H21: =IF(ISBLANK(A21), "", IF(G21<=0, "🟢 Cobrado Total", IF(N(F21)>0, "🟡 Parcial", "🔴 Pendiente")))
... G34: =IF(ISBLANK(A34), "", MAX(0, E34-N(F34))) | H34: =IF(ISBLANK(A34), "", IF(G34<=0, "🟢 Cobrado Total", IF(N(F34)>0, "🟡 Parcial", "🔴 Pendiente")))

Sheet CATEGORIAS
A1: 🏷️ TAXONOMÍA FINANCIERA Y CLASIFICACIÓN
A2: Catálogo maestro de categorías, tipos de movimiento, métodos de pago y selectores del sistema
A3: Categoría | B3: Tipo | C3: Descripción / Ejemplo | D3: Fondo Colanta | E3: Prioridad | G3: enero | H3: 2024 | J3: Ingreso | K3: Efectivo | L3: Bancolombia Marlon
A4: Alimentación | B4: Gasto | C4: Mercados, almuerzos laborales, víveres | D4: No | E4: Alta | G4: febrero | H4: 2025 | J4: Gasto | K4: Transferencia | L4: Nómina Colanta
A5: Vivienda | B5: Gasto | C5: Arriendo Casa mensual | D5: No | E5: Alta | G5: marzo | H5: 2026 | J5: Abono | K5: Tarjeta Débito | L5: AyC Colanta
A6: Servicios | B6: Gasto | C6: EPM Energía, Agua, Internet Tigo, Celular | D6: No | E6: Alta | G6: abril | H6: 2027 | K6: Transferencia / Nómina | L6: Nequi
A7: Transporte | B7: Gasto | C7: Gasolina, Parqueadero trabajo, Didi/Uber | D7: No | E7: Media | G7: mayo | H7: 2028 | K7: Tarjeta Nequi | L7: Efectivo
A8: Moto | B8: Gasto | C8: Mantenimiento, repuestos, parqueadero moto | D8: No | E8: Media | G8: junio | H8: 2029
A9: Gastos Hormiga / Dulces | B9: Gasto | C9: Helados, granizados, golosinas, pasabocas | D9: No | E9: Baja | G9: julio | H9: 2030
A10: Entretenimiento | B10: Gasto | C10: Spotify, salidas, pizza con amigos | D10: No | E10: Baja | G10: agosto
A11: Suscripciones | B11: Gasto | C11: Telegram Premium, Google One, software | D11: No | E11: Baja | G11: septiembre
A12: Compras | B12: Gasto | C12: Ropa, accesorios trabajo, tecnología, audífonos | D12: No | E12: Media | G12: octubre
A13: Ahorro Ordinario | B13: Ahorro | C13: Descuento por nómina en Fondo Colanta ($33.000) | D13: Sí | E13: Alta | G13: noviembre
A14: Ahorro Navideño | B14: Ahorro | C14: Descuento por nómina para entrega en dic ($120.000) | D14: Sí | E14: Alta | G14: diciembre
A15: Aportes Cooperativos | B15: Ahorro | C15: Capitalización obligatoria Colanta AyC | D15: Sí | E15: Alta
A16: Aporte Afiliación | B16: Ahorro | C16: Fondo y beneficios de asociado Colanta | D16: Sí | E16: Alta
A17: Nómina Colanta | B17: Ingreso | C17: Salario quincenal, recargos y extras Colanta | D17: Sí | E17: Alta

Sheet REGLAS_COMERCIOS
A1: 🤖 CATÁLOGO DE REGLAS Y ASIGNACIÓN AUTOMÁTICA (BOT TELEGRAM)
A2: Diccionario de entrenamiento para que Gemini y Apps Script clasifiquen comercios y conceptos al instante.
A4: Comercio / Palabra Clave | B4: Categoría Asignada | C4: Subcategoría / Tipo | D4: Notas / Comportamiento Bot
A5: Mercatodo | B5: Alimentación | C5: Mercado | D5: Compra de víveres quincenal
A6: Éxito | B6: Alimentación | C6: Supermercado | D6: Mercado o compras para el hogar
A7: D1 | B7: Alimentación | C7: Víveres | D7: Compras cotidianas de despensa
A8: Euro Supermercado | B8: Alimentación | C8: Mercado | D8: Supermercado
A9: Almuerzo | B9: Alimentación | C9: Comidas Laborales | D9: Almuerzo laboral
A10: Restaurante | B10: Alimentación | C10: Comida Fuera | D10: Comida en restaurante
A11: Rappi | B11: Alimentación | C11: Domicilios | D11: Pedido de comida rápida o despensa
A12: Panadería | B12: Alimentación | C12: Desayuno / Onces | D12: Café y pan
A13: Primax | B13: Moto | C13: Gasolina | D13: Tanqueo de moto
A14: Texaco | B14: Moto | C14: Gasolina | D14: Tanqueo de moto
A15: Terpel | B15: Moto | C15: Gasolina | D15: Tanqueo de combustible
... A49: Nómina Colanta | B49: Nómina Colanta | C49: Salario | D49: Ingreso quincenal oficial

Sheet GUIA_SISTEMA
A1: 📖 MANUAL DE USUARIO — FINANZAS MARLON MUÑOZ V26 PRO
A2: Guía operativa del Centro de Control Financiero sincronizado con Telegram y Apps Script.
A4: Módulo / Función del Sistema | B4: Descripción Operativa e Integración con el Bot de Telegram y Gemini IA
A5: 1. Barra de Navegación | B5: Haz clic en cualquier botón de la barra superior en el PANEL para saltar directamente a esa hoja. En cada hoja secundaria hay un botón para volver.
A6: 2. Selector Período | B6: Cambia el mes en L2 y el año en I2 en el PANEL con un solo clic en la flecha desplegable. Todo el libro se recalcula automáticamente.
A7: 3. Balanza Quincenal | B7: En el PANEL puedes ver la proyección de la Quincena 1 (día 1-15) vs Quincena 2 (día 16-30) para controlar tu liquidez quincenal exacta.
A8: 4. Radar Gastos Hormiga | B8: Monitorea en tiempo real los microgastos de golosinas y helados para evitar que drenen tu capacidad de ahorro mensual.
A9: 5. Cierre de Año 2026 | B9: El nuevo módulo proyecta la entrega de tu Fondo Navideño Colanta en diciembre ($2.040.000) y la Prima de Navidad para planear compras sin endeudarte.
A10: 6. Arqueo de Liquidez | B10: Conoce con exactitud cuánto dinero disponible tienes repartido en AyC Colanta, Nequi y Efectivo.
A11: 7. Metas y Cartera | B11: Usa METAS AHORRO para tus proyectos con barras de avance y CUENTAS POR COBRAR para controlar préstamos con semáforos automáticos.
A12: 8. Patrimonio Neto | B12: La hoja PATRIMONIO NETO consolida tus activos, ahorros acumulados, cartera y pasivos para medir tu solvencia real.
A13: 9. Compatibilidad Sheets | B13: 100% compatible al subir a Google Drive y convertir a Google Sheets sin macros, con gráficos OpenXML nativos.
