Workbook

Sheet 01_USUARIOS
A1: PARDOFINANZAS • DIRECTORIO MULTIUSUARIO DE PARTICIPANTES
A4: ID_USUARIO | B4: NOMBRE_COMPLETO | C4: ALIAS | D4: ROL | E4: SALDO_INICIAL_COP | F4: EMAIL_NOTIFICACIONES | G4: ESTADO
A5: U-001 | B5: Marlon Muñoz Pardo | C5: Marlon | D5: Administrador (Pro) | E5: 1065366 | F5: marlon@pardofinanzas.com | G5: ACTIVO
A6: U-002 | B6: Carlos Restrepo | C6: Carlos | D6: Miembro | E6: 500000 | F6: carlos.r@gmail.com | G6: ACTIVO
A7: U-003 | B7: Laura Morales | C7: Laura | D7: Miembro | E7: 750000 | F7: laura.m@hotmail.com | G7: ACTIVO
A8: U-004 | B8: Andrés Gómez | C8: Andrés | D8: Miembro | E8: 620000 | F8: andres.g@gmail.com | G8: ACTIVO

Sheet 02_MOVIMIENTOS
A1: LIBRO MAESTRO DE MOVIMIENTOS FINANCIEROS MULTIUSUARIO
A4: ID_MOV | B4: ID_USUARIO | C4: USUARIO | D4: FECHA | E4: TIPO | F4: CATEGORIA | G4: CONCEPTO_DESCRIPCION | H4: VALOR_COP | I4: MEDIO_PAGO | J4: COMERCIO_DESTINO | K4: ESTADO
A5: M-1001 | B5: U-001 | C5: =IFERROR(VLOOKUP(B5, '01_USUARIOS'!$A$5:$B$20, 2, FALSE), "-") | D5: 2026-10-01 | E5: Ingreso | F5: Salario | G5: Quincena Nómina Colanta | H5: 1850000 | I5: AyC Colanta | J5: Cooperativa Colanta | K5: CONFIRMADO
A6: M-1002 | B6: U-001 | C6: =IFERROR(VLOOKUP(B6, '01_USUARIOS'!$A$5:$B$20, 2, FALSE), "-") | D6: 2026-10-02 | E6: Gasto | F6: Alimentación | G6: Mercado Éxito mensual | H6: 320000 | I6: Nequi | J6: Éxito Colombia | K6: CONFIRMADO
A7: M-1003 | B7: U-001 | C7: =IFERROR(VLOOKUP(B7, '01_USUARIOS'!$A$5:$B$20, 2, FALSE), "-") | D7: 2026-10-03 | E7: Gasto | F7: Transporte/Moto | G7: Tanqueada Gasolina Extra | H7: 35000 | I7: Efectivo | J7: Estación Terpel | K7: CONFIRMADO
A8: M-1004 | B8: U-001 | C8: =IFERROR(VLOOKUP(B8, '01_USUARIOS'!$A$5:$B$20, 2, FALSE), "-") | D8: 2026-10-15 | E8: Gasto | F8: Servicios | G8: Factura EPM Energía | H8: 197000 | I8: AyC Colanta | J8: EPM Medellín | K8: CONFIRMADO
A9: M-1005 | B9: U-002 | C9: =IFERROR(VLOOKUP(B9, '01_USUARIOS'!$A$5:$B$20, 2, FALSE), "-") | D9: 2026-10-01 | E9: Ingreso | F9: Salario | G9: Salario Mensual Carlos | H9: 2200000 | I9: Bancolombia | J9: Empresa Tech | K9: CONFIRMADO
A10: M-1006 | B10: U-002 | C10: =IFERROR(VLOOKUP(B10, '01_USUARIOS'!$A$5:$B$20, 2, FALSE), "-") | D10: 2026-10-04 | E10: Gasto | F10: Alimentación | G10: Almuerzo Restaurante | H10: 28000 | I10: Nequi | J10: Restaurante Central | K10: CONFIRMADO
A11: M-1007 | B11: U-003 | C11: =IFERROR(VLOOKUP(B11, '01_USUARIOS'!$A$5:$B$20, 2, FALSE), "-") | D11: 2026-10-01 | E11: Ingreso | F11: Salario | G11: Honorarios Laura | H11: 1600000 | I11: Bancolombia | J11: Consultoría SAS | K11: CONFIRMADO
A12: M-1008 | B12: U-003 | C12: =IFERROR(VLOOKUP(B12, '01_USUARIOS'!$A$5:$B$20, 2, FALSE), "-") | D12: 2026-10-06 | E12: Gasto | F12: Salud/Gym | G12: Mensualidad Smart Fit | H12: 99000 | I12: Tarjeta Débito | J12: Smart Fit | K12: CONFIRMADO
A13: M-1009 | B13: U-004 | C13: =IFERROR(VLOOKUP(B13, '01_USUARIOS'!$A$5:$B$20, 2, FALSE), "-") | D13: 2026-10-01 | E13: Ingreso | F13: Salario | G13: Pago Quincenal Andrés | H13: 1400000 | I13: Nequi | J13: Comercio Global | K13: CONFIRMADO
A14: M-1010 | B14: U-004 | C14: =IFERROR(VLOOKUP(B14, '01_USUARIOS'!$A$5:$B$20, 2, FALSE), "-") | D14: 2026-10-08 | E14: Gasto | F14: Ocio | G14: Salida Cine y Cena | H14: 65000 | I14: Efectivo | J14: Cine Colombia | K14: CONFIRMADO

Sheet 03_CONTROL_FIJOS
A1: CONTROL DE GASTOS FIJOS (QUINCENA 1 - DÍA 15 vs FIN DE MES - DÍA 30)
A4: ID_FIJO | B4: ID_USUARIO | C4: USUARIO | D4: CONCEPTO_FIJO | E4: CATEGORIA | F4: CUOTA_MENSUAL | G4: DIA_PAGO | H4: QUINCENA | I4: ESTADO_MES
A5: F-01 | B5: U-001 | C5: =IFERROR(VLOOKUP(B5, '01_USUARIOS'!$A$5:$B$20, 2, FALSE), "-") | D5: EPM Energía | E5: Servicios | F5: 197000 | G5: 15 | H5: =IF(G5<=15, "Quincena 1 (Día 15)", "Fin de Mes (Día 30)") | I5: Pagado
A6: F-02 | B6: U-001 | C6: =IFERROR(VLOOKUP(B6, '01_USUARIOS'!$A$5:$B$20, 2, FALSE), "-") | D6: Plan Celular Tigo | E6: Servicios | F6: 55000 | G6: 15 | H6: =IF(G6<=15, "Quincena 1 (Día 15)", "Fin de Mes (Día 30)") | I6: Pagado
A7: F-03 | B7: U-001 | C7: =IFERROR(VLOOKUP(B7, '01_USUARIOS'!$A$5:$B$20, 2, FALSE), "-") | D7: Seguro Moto SURA | E7: Transporte | F7: 135000 | G7: 15 | H7: =IF(G7<=15, "Quincena 1 (Día 15)", "Fin de Mes (Día 30)") | I7: Pendiente
A8: F-04 | B8: U-001 | C8: =IFERROR(VLOOKUP(B8, '01_USUARIOS'!$A$5:$B$20, 2, FALSE), "-") | D8: Arriendo Medellín | E8: Vivienda | F8: 920000 | G8: 30 | H8: =IF(G8<=15, "Quincena 1 (Día 15)", "Fin de Mes (Día 30)") | I8: Pagado
A9: F-05 | B9: U-001 | C9: =IFERROR(VLOOKUP(B9, '01_USUARIOS'!$A$5:$B$20, 2, FALSE), "-") | D9: Internet Fibra Óptica | E9: Servicios | F9: 105000 | G9: 30 | H9: =IF(G9<=15, "Quincena 1 (Día 15)", "Fin de Mes (Día 30)") | I9: Pendiente
A10: F-06 | B10: U-002 | C10: =IFERROR(VLOOKUP(B10, '01_USUARIOS'!$A$5:$B$20, 2, FALSE), "-") | D10: Arriendo Habitación | E10: Vivienda | F10: 650000 | G10: 30 | H10: =IF(G10<=15, "Quincena 1 (Día 15)", "Fin de Mes (Día 30)") | I10: Pendiente
A11: F-07 | B11: U-002 | C11: =IFERROR(VLOOKUP(B11, '01_USUARIOS'!$A$5:$B$20, 2, FALSE), "-") | D11: Gimnasio | E11: Salud | F11: 85000 | G11: 15 | H11: =IF(G11<=15, "Quincena 1 (Día 15)", "Fin de Mes (Día 30)") | I11: Pagado
A12: F-08 | B12: U-003 | C12: =IFERROR(VLOOKUP(B12, '01_USUARIOS'!$A$5:$B$20, 2, FALSE), "-") | D12: Crédito Estudio | E12: Educación | F12: 320000 | G12: 15 | H12: =IF(G12<=15, "Quincena 1 (Día 15)", "Fin de Mes (Día 30)") | I12: Pagado
A13: F-09 | B13: U-004 | C13: =IFERROR(VLOOKUP(B13, '01_USUARIOS'!$A$5:$B$20, 2, FALSE), "-") | D13: Plan Móvil Claro | E13: Servicios | F13: 45000 | G13: 30 | H13: =IF(G13<=15, "Quincena 1 (Día 15)", "Fin de Mes (Día 30)") | I13: Pendiente

Sheet 04_DASHBOARD_RESUMEN
A1: PANEL CONSOLIDADO MULTIUSUARIO • FORMULAS 100% GOOGLE SHEETS
A4: INGRESOS TOTALES GRUPO | C4: GASTOS TOTALES GRUPO | E4: SUPERÁVIT NETO COLECTIVO | G4: TASA DE AHORRO COLECTIVA
A5: =SUMIF('02_MOVIMIENTOS'!E:E, "Ingreso", '02_MOVIMIENTOS'!H:H) | C5: =SUMIF('02_MOVIMIENTOS'!E:E, "Gasto", '02_MOVIMIENTOS'!H:H) | E5: =A5-C5 | G5: =IFERROR(E5/A5, 0)
A8: DESGLOSE INDIVIDUAL POR PARTICIPANTE
A10: ID_USUARIO | B10: NOMBRE_PARTICIPANTE | C10: SALDO_INICIAL | D10: INGRESOS_MES | E10: GASTOS_MES | F10: BALANCE_NETO | G10: TASA_AHORRO | H10: SALDO_ACTUAL_DISPONIBLE
A11: U-001 | B11: =IFERROR(VLOOKUP(A11, '01_USUARIOS'!$A$5:$B$20, 2, FALSE), "-") | C11: =IFERROR(VLOOKUP(A11, '01_USUARIOS'!$A$5:$E$20, 5, FALSE), 0) | D11: =SUMIFS('02_MOVIMIENTOS'!$H:$H, '02_MOVIMIENTOS'!$B:$B, A11, '02_MOVIMIENTOS'!$E:$E, "Ingreso") | E11: =SUMIFS('02_MOVIMIENTOS'!$H:$H, '02_MOVIMIENTOS'!$B:$B, A11, '02_MOVIMIENTOS'!$E:$E, "Gasto") | F11: =D11-E11 | G11: =IFERROR(F11/D11, 0) | H11: =C11+F11
A12: U-002 | B12: =IFERROR(VLOOKUP(A12, '01_USUARIOS'!$A$5:$B$20, 2, FALSE), "-") | C12: =IFERROR(VLOOKUP(A12, '01_USUARIOS'!$A$5:$E$20, 5, FALSE), 0) | D12: =SUMIFS('02_MOVIMIENTOS'!$H:$H, '02_MOVIMIENTOS'!$B:$B, A12, '02_MOVIMIENTOS'!$E:$E, "Ingreso") | E12: =SUMIFS('02_MOVIMIENTOS'!$H:$H, '02_MOVIMIENTOS'!$B:$B, A12, '02_MOVIMIENTOS'!$E:$E, "Gasto") | F12: =D12-E12 | G12: =IFERROR(F12/D12, 0) | H12: =C12+F12
A13: U-003 | B13: =IFERROR(VLOOKUP(A13, '01_USUARIOS'!$A$5:$B$20, 2, FALSE), "-") | C13: =IFERROR(VLOOKUP(A13, '01_USUARIOS'!$A$5:$E$20, 5, FALSE), 0) | D13: =SUMIFS('02_MOVIMIENTOS'!$H:$H, '02_MOVIMIENTOS'!$B:$B, A13, '02_MOVIMIENTOS'!$E:$E, "Ingreso") | E13: =SUMIFS('02_MOVIMIENTOS'!$H:$H, '02_MOVIMIENTOS'!$B:$B, A13, '02_MOVIMIENTOS'!$E:$E, "Gasto") | F13: =D13-E13 | G13: =IFERROR(F13/D13, 0) | H13: =C13+F13
A14: U-004 | B14: =IFERROR(VLOOKUP(A14, '01_USUARIOS'!$A$5:$B$20, 2, FALSE), "-") | C14: =IFERROR(VLOOKUP(A14, '01_USUARIOS'!$A$5:$E$20, 5, FALSE), 0) | D14: =SUMIFS('02_MOVIMIENTOS'!$H:$H, '02_MOVIMIENTOS'!$B:$B, A14, '02_MOVIMIENTOS'!$E:$E, "Ingreso") | E14: =SUMIFS('02_MOVIMIENTOS'!$H:$H, '02_MOVIMIENTOS'!$B:$B, A14, '02_MOVIMIENTOS'!$E:$E, "Gasto") | F14: =D14-E14 | G14: =IFERROR(F14/D14, 0) | H14: =C14+F14
A15: TOTALES | B15: Todos los participantes | C15: =SUM(C11:C14) | D15: =SUM(D11:D14) | E15: =SUM(E11:E14) | F15: =SUM(F11:F14) | G15: =IFERROR(F15/D15, 0) | H15: =SUM(H11:H14)

Sheet 05_PARAMETROS
A2: TIPOS_MOVIMIENTO | C2: CATEGORIAS_GASTO | E2: CATEGORIAS_INGRESO | G2: MEDIOS_PAGO
A3: Ingreso | C3: Alimentación | E3: Salario | G3: AyC Colanta
A4: Gasto | C4: Transporte/Moto | E4: Honorarios | G4: Nequi
A5: Transferencia | C5: Vivienda/Arriendo | E5: Venta | G5: Efectivo
C6: Servicios | E6: Rendimientos | G6: Bancolombia
C7: Salud/Gym | E7: Préstamo Cobrado | G7: Daviplata
C8: Ocio/Restaurante | E8: Otros | G8: Tarjeta Débito
C9: Educación | G9: Tarjeta Crédito
C10: Compras
C11: Imprevistos
